Workbook

Sheet Fixed Income
B1: Ticker/CUSIP | C1: Description | D1: Coupon Rate | E1: Current Price | F1: Share Count | G1: Value | H1: % of Porfolio | I1: Target % of Portfolio | K1: Purchase Price | L1: Purchase Date | M1: Coupon Value | N1: % Return to Date | O1: % Return to Date Over Benchmark ETF | Q1: Latest Thesis | R1: Thesis Date | S1: Thesis Price Target | T1: % Premium Over Thesis
A2: Fixed Income
B3: 629377CC4 | C3: =VLOOKUP($B3, 'Sector Holdings'!$B$2:$C$130, 2, FALSE) -> #N/A | D3: 0.06625 | E3: =OFFSET('Sector Holdings'!$A$1:$H$18, MATCH("Fixed Income", 'Sector Holdings'!$A$1:$A$130, 0), 5, $B$14) -> #REF! | F3: 25 | G3: 22847.5 | H3: 0.0083292957 | I3: 0.015 | K3: 1007.19 | L3: 43864 | M3: =ROUND(DATEDIF(L3,TODAY(),"M")/6,0)*(D3*1000) -> 795 | N3: =(((E3+M3)/K3-1) ) -> #REF! | Q3: =OFFSET('Sector Holdings'!$A$1:$M$18, MATCH("Fixed Income", 'Sector Holdings'!$A$1:$A$130, 0), 17, $B$14) -> #REF! | R3: Hold | S3: 44292 | T3: 1000 | U3: -0.0861
B4: 38148BAD0 | C4: =VLOOKUP(B4, 'Sector Holdings'!$B$2:$C$130, 2, FALSE) -> #N/A | D4: 0.05 | E4: 1058.6 | F4: 25 | G4: 26465 | H4: 0.0096480933 | I4: 0.015 | K4: 1092.5 | L4: 44823 | M4: =ROUND(DATEDIF(L4,TODAY(),"M")/6,0)*(D4*1000) -> 350 | N4: =(((E4+M4)/K4-1) ) -> 0.28933638 | R4: Buy at 1.5% | T4: 1000 | U4: 0.0586
B5: 3133ELEN0 | C5: =VLOOKUP(B5, 'Sector Holdings'!$B$2:$C$130, 2, FALSE) -> FFCB Corp. 2.25 12/18/29 | D5: 0.0225 | E5: 992.2 | F5: 29 | G5: 28773.8 | H5: 0.010489791 | I5: 0.015 | K5: 907.92 | L5: 44830 | M5: =ROUND(DATEDIF(L5,TODAY(),"M")/6,0)*(D5*1000) -> 157.5 | N5: =(((E5+M5)/K5-1) ) -> 0.266301 | R5: Buy at 1.5% | S5: 44824 | T5: 1000 | U5: -0.0078
B6: 449669AK6 | C6: =VLOOKUP(B6, 'Sector Holdings'!$B$2:$C$130, 2, FALSE) -> MOS 7.3 01/15/28 Corp | D6: 0.073 | E6: 909.4 | F6: 33 | G6: 30010.2 | H6: 0.010940533 | I6: 0.015 | K6: 854.34 | L6: 45230 | M6: =ROUND(DATEDIF(L6,TODAY(),"M")/6,0)*(D6*1000) -> 365 | N6: =(((E6+M6)/K6-1) ) -> 0.49167779 | R6: Buy at 1.5% | S6: 45230 | T6: 1000 | U6: -0.0906
B7: 05530QAP5 | C7: =VLOOKUP(B7, 'Sector Holdings'!$B$2:$C$130, 2, FALSE) -> BTI 4.448 03/16/28 Corp | D7: 0.04448 | E7: 996.9 | F7: 43 | G7: 42866.7 | H7: 0.015627505 | I7: 0.02 | K7: 948.61 | L7: 45261 | M7: =ROUND(DATEDIF(L7,TODAY(),"M")/6,0)*(D7*1000) -> 177.92 | N7: =(((E7+M7)/K7-1) ) -> 0.2384647 | R7: Buy at 2% | S7: 45261 | T7: 1000 | U7: -0.0031
B8: BBN | C8: =VLOOKUP(B8, 'Sector Holdings'!$B$2:$C$130, 2, FALSE) -> #N/A | E8: 992.9 | F8: 22 | G8: 21843.8 | H8: 0.0079633864 | I8: 0.0094 | K8: 961.68 | L8: 45359 | M8: =100*4.777% -> 4.777 | N8: =((E8+M8)/K8-1) -> 0.03743137 | R8: Buy at 0.95% | S8: 45356 | T8: 956.4 | U8: 0.038163948
B9: 912797LL9 | C9: =VLOOKUP(B9, 'Sector Holdings'!$B$2:$C$130, 2, FALSE) -> #N/A | D9: 0 | E9: 993.8 | F9: 47 | G9: 46708.6 | H9: 0.01702811 | I9: 0.02 | K9: 1038.1 | L9: 45561 | M9: =ROUND(DATEDIF(L9,TODAY(),"M")/6,0)*(D9*1000) -> 0 | N9: 88.96 | R9: Buy at 2% | S9: 45552 | T9: 1040 | U9: -0.044423077
B10: AGG | C10: =VLOOKUP(B10, 'Sector Holdings'!$B$2:$C$130, 2, FALSE) -> iShares Aggregate Bond ETF | E10: 1105.4 | F10: 43 | G10: 47532.2 | H10: 0.017328362 | I10: 0.02 | K10: 1120.55 | L10: 45590 | N10: =(E10/K10-1) -> -0.013520146 | R10: Buy at 2% | S10: 45590 | T10: 1120 | U10: -0.013035714
B11: Cash | E11: 964.2 | F11: 25 | G11: 24105 | H11: 0.0087877305 | I11: 0.01 | K11: 966.6 | L11: 45611 | R11: Buy at 1% | S11: 45610 | T11: 966 | U11: -0.001863354
A12: Sector Total | E12: 1006.5 | F12: 33 | G12: 33214.5 | H12: 0.012108694 | I12: 0.0125 | K12: 993.26 | L12: 45701 | N12: =(G12/K12-1) -> 32.439885 | R12: Buy at 1.25% | S12: 45700 | T12: 1000 | U12: 0.0065
E13: 1008.94 | F13: 24 | G13: 24214.56 | H13: 0.0088276718 | I13: 0.01 | K13: 1003.1 | L13: 45748 | R13: Buy at 1.00% | S13: 45741 | T13: 1000 | U13: 0.00894
A14: # Of FI Holdings | B14: 13 | E14: 100.44 | F14: 0 | G14: 0 | H14: 0 | I14: 0 | K14: 105.59 | L14: 44113 | R14: NA | S14: NA | T14: NA | U14: NA
G15: 38148.02 | H15: 0.013907261

Sheet Copy of Fixed Income
B1: Ticker/CUSIP | C1: Description | D1: Coupon Rate | E1: Compound Frequency | F1: Current Price | G1: Share Count | H1: Value | I1: % of Porfolio | J1: Target % of Portfolio | L1: Purchase Price | M1: Purchase Date | N1: Coupon Value Earned PTD | O1: % Return to Date | P1: % Return to Date Over Benchmark ETF | R1: Latest Thesis | S1: Thesis Date | T1: Thesis Price Target | U1: % Premium Over Thesis
A2: Fixed Income | W2: Number of FI Holdings | X2: 11
A3: =OFFSET('Sector Holdings'!$A$1:$H$18, MATCH("Fixed Income", 'Sector Holdings'!$A$1:$A$130, 0), 0, $X$2+2,3) -> #REF! | B3: 3133ELEN0 | C3: FFCB Corp. 2.25 12/18/29 | D3: 0.0225 | F3: =OFFSET('Sector Holdings'!$A$1:$H$18, MATCH("Fixed Income", 'Sector Holdings'!$A$1:$A$130, 0), 5, $X$2+2,8) -> #REF! | G3: 25 | H3: 22847.5 | I3: 0.0083292957 | J3: 0.015 | L3: 1007.19 | M3: 43864 | N3: =ROUNDDOWN(DATEDIF(M3,TODAY(),"M")/6,0)*(D3*1000) -> 270 | O3: =OFFSET('Sector Holdings'!$A$1:$H$18, MATCH("Fixed Income", 'Sector Holdings'!$A$1:$A$130, 0), 13, $X$2+2,1) -> #REF! | R3: =OFFSET('Sector Holdings'!$A$1:$H$18, MATCH("Fixed Income", 'Sector Holdings'!$A$1:$A$130, 0), 18, $X$2+2) -> #REF! | S3: 44292 | T3: 1000 | U3: -0.0861
B4: 449669AK6 | C4: MOS 7.3 01/15/28 Corp | D4: 0.073 | F4: 1058.6 | G4: 25 | H4: 26465 | I4: 0.0096480933 | J4: 0.015 | L4: 1092.5 | M4: 44823 | N4: =ROUND(DATEDIF(M4,TODAY(),"M")/6,0)*(D4*1000) -> 511 | O4: -0.031029748 | R4: Buy at 1.5% | T4: 1000 | U4: 0.0586
B5: 05530QAP5 | C5: BTI 4.448 03/16/28 Corp | D5: 0.04448 | F5: 992.2 | G5: 29 | H5: 28773.8 | I5: 0.010489791 | J5: 0.015 | L5: 907.92 | M5: 44830 | N5: =ROUND(DATEDIF(M5,TODAY(),"M")/6,0)*(D5*1000) -> 311.36 | O5: 0.092827562 | R5: Buy at 1.5% | S5: 44824 | T5: 1000 | U5: -0.0078
B6: 3133EJEP0 | C6: FFCB 3.50 03/02/34 | D6: 0.0425 | F6: 909.4 | G6: 33 | H6: 30010.2 | I6: 0.010940533 | J6: 0.015 | L6: 854.34 | M6: 45230 | N6: =ROUND(DATEDIF(M6,TODAY(),"M")/6,0)*(D6*1000) -> 212.5 | O6: 0.06444741 | R6: Buy at 1.5% | S6: 45230 | T6: 1000 | U6: -0.0906
B7: 695114BZ0 | C7: Pacificorp 5.25 06/15/35 | D7: 0.035 | F7: 996.9 | G7: 43 | H7: 42866.7 | I7: 0.015627505 | J7: 0.02 | L7: 948.61 | M7: 45261 | N7: =ROUND(DATEDIF(M7,TODAY(),"M")/6,0)*(D7*1000) -> 140 | O7: 0.050906063 | R7: Buy at 2% | S7: 45261 | T7: 1000 | U7: -0.0031
B8: 517834AH0 | C8: LVS 2.9 06/25/25 | D8: 0.0525 | F8: 992.9 | G8: 22 | H8: 21843.8 | I8: 0.0079633864 | J8: 0.0094 | L8: 961.68 | M8: 45359 | N8: =100*4.777% -> 4.777 | O8: 0.032464021 | R8: Buy at 0.95% | S8: 45356 | T8: 956.4 | U8: 0.038163948
B9: 61747YFT7 | C9: MS 5.32 07/19/35 | D9: 0.029 | F9: 993.8 | G9: 47 | H9: 46708.6 | I9: 0.01702811 | J9: 0.02 | L9: 1038.1 | M9: 45561 | N9: =ROUND(DATEDIF(M9,TODAY(),"M")/6,0)*(D9*1000) -> 87 | O9: -0.042674116 | R9: Buy at 2% | S9: 45552 | T9: 1040 | U9: -0.044423077
B10: 822582AD4 | C10: RDSALN 6.375 12/15/38 | D10: 0.0532 | F10: 1105.4 | G10: 43 | H10: 47532.2 | I10: 0.017328362 | J10: 0.02 | L10: 1120.55 | M10: 45590 | N10: =ROUND(DATEDIF(M10,TODAY(),"M")/6,0)*(D10*1000) -> 159.6 | O10: -0.013520146 | R10: Buy at 2% | S10: 45590 | T10: 1120 | U10: -0.013035714
B11: 626717AP7 | C11: MUR 6 10/01/32 | D11: 0.06375 | F11: 964.2 | G11: 25 | H11: 24105 | I11: 0.0087877305 | J11: 0.01 | L11: 966.6 | M11: 45611 | N11: =ROUND(DATEDIF(M11,TODAY(),"M")/6,0)*(D11*1000) -> 191.25 | O11: -0.0024829299 | R11: Buy at 1% | S11: 45610 | T11: 966 | U11: -0.001863354
B12: 446413BA3 | C12: HII Corp 5.353 1/15/30 | D12: 0.06 | F12: 1006.5 | G12: 33 | H12: 33214.5 | I12: 0.012108694 | J12: 0.0125 | L12: 993.26 | M12: 45701 | N12: =ROUND(DATEDIF(M12,TODAY(),"M")/6,0)*(D12*1000) -> 120 | O12: 0.013329843 | R12: Buy at 1.25% | S12: 45700 | T12: 1000 | U12: 0.0065
B13: 29379VBM4 | C13: EPD Corp SOFR+3.248 08/16/77 | F13: 1008.94 | G13: 24 | H13: 24214.56 | I13: 0.0088276718 | J13: 0.01 | L13: 1003.1 | M13: 45748 | N13: =ROUND(DATEDIF(M13,TODAY(),"M")/6,0)*(D13*1000) -> 0 | O13: 0.0058219519 | R13: Buy at 1.00% | S13: 45741 | T13: 1000 | U13: 0.00894
B14: AGG | C14: iShares Aggregate Bond ETF | F14: 100.44 | G14: 0 | H14: 0 | I14: 0 | J14: 0 | L14: 105.59 | M14: 44113 | O14: -0.048773558 | R14: NA | S14: NA | T14: NA | U14: NA
B15: Cash | H15: 38148.02 | I15: 0.013907261

Sheet Holdings by Weight
A1: Ticker | B1: Description | C1: Sector | D1: Price | E1: Shares | F1: Value | G1: Portfolio Weight | H1: Sector Weight
A2: Total Cash | C2: Total Cash | F2: =VLOOKUP($A$2, 'Sector Holdings'!$A$3:$I$130, 8, FALSE) -> 144078 | G2: =VLOOKUP($A$2, 'Sector Holdings'!$A$3:$I$130, 9, FALSE) -> 0.054049094 | K2: Weight | L2: Value
A3: SPY | B3: =VLOOKUP($A3, 'Sector Holdings'!$B$3:$C$130, 2, FALSE) -> SPDR S&P 500 ETF | C3: Quant | D3: =VLOOKUP($A3, 'Sector Holdings'!$B$3:$H$130, 5, FALSE) -> 682.51 | E3: =VLOOKUP($A3, 'Sector Holdings'!$B$3:$I$130, 6, FALSE) -> 0 | F3: =D3*E3 -> 0 | G3: =VLOOKUP($A3, 'Sector Holdings'!$B$3:$I$130, 8, FALSE) -> 0 | H3: =IF(F3>0, F3/SUMIF(C:C,C3, F:F), "N/A") -> N/A | J3: Equities Total | K3: =L3/$L$6 -> #N/A | L3: =L6-L5-L4 -> #N/A
A4: AGG | B4: =VLOOKUP($A4, 'Sector Holdings'!$B$3:$C$130, 2, FALSE) -> iShares Aggregate Bond ETF | C4: Fixed Income | D4: =VLOOKUP($A4, 'Sector Holdings'!$B$3:$H$130, 5, FALSE) -> 101.07 | E4: =VLOOKUP($A4, 'Sector Holdings'!$B$3:$I$130, 6, FALSE) -> 0 | F4: =D4*E4 -> 0 | G4: =VLOOKUP($A4, 'Sector Holdings'!$B$3:$I$130, 8, FALSE) -> 0 | H4: =IF(F4>0, F4/SUMIF(C:C,C4, F:F), "N/A") -> N/A | J4: Fixed Income | K4: =L4/$L$6 -> #N/A | L4: =SUMIF(C:C, "Fixed Income", F:F) -> #N/A
A5: XLY | B5: =VLOOKUP($A5, 'Sector Holdings'!$B$3:$C$130, 2, FALSE) -> SPDR Discretionary ETF | C5: Consumer Discretionary | D5: =VLOOKUP($A5, 'Sector Holdings'!$B$3:$H$130, 5, FALSE) -> 114.52 | E5: =VLOOKUP($A5, 'Sector Holdings'!$B$3:$I$130, 6, FALSE) -> 0 | F5: =D5*E5 -> 0 | G5: =VLOOKUP($A5, 'Sector Holdings'!$B$3:$I$130, 8, FALSE) -> 0 | H5: =IF(F5>0, F5/SUMIF(C:C,C5, F:F), "N/A") -> N/A | J5: Cash | K5: =L5/$L$6 -> 0.054049094 | L5: =SUMIF(C:C, "Total Cash", F:F) -> 144078
A6: XLP | B6: =VLOOKUP($A6, 'Sector Holdings'!$B$3:$C$130, 2, FALSE) -> SPDR Consumer Staples ETF | C6: Consumer Staples | D6: =VLOOKUP($A6, 'Sector Holdings'!$B$3:$H$130, 5, FALSE) -> 88.74 | E6: =VLOOKUP($A6, 'Sector Holdings'!$B$3:$I$130, 6, FALSE) -> 0 | F6: =D6*E6 -> 0 | G6: =VLOOKUP($A6, 'Sector Holdings'!$B$3:$I$130, 8, FALSE) -> 0 | H6: =IF(F6>0, F6/SUMIF(C:C,C6, F:F), "N/A") -> N/A | J6: Total Portfolio | K6: =SUM(K3:K5) -> #N/A | L6: ='Sector Holdings'!H121 -> 2665687.6
A7: XLE | B7: =VLOOKUP($A7, 'Sector Holdings'!$B$3:$C$130, 2, FALSE) -> SPDR Energy ETF | C7: Energy | D7: =VLOOKUP($A7, 'Sector Holdings'!$B$3:$H$130, 5, FALSE) -> 55.16 | E7: =VLOOKUP($A7, 'Sector Holdings'!$B$3:$I$130, 6, FALSE) -> 0 | F7: =D7*E7 -> 0 | G7: =VLOOKUP($A7, 'Sector Holdings'!$B$3:$I$130, 8, FALSE) -> 0 | H7: =IF(F7>0, F7/SUMIF(C:C,C7, F:F), "N/A") -> N/A
A8: XLF | B8: =VLOOKUP($A8, 'Sector Holdings'!$B$3:$C$130, 2, FALSE) -> SPDR Financials ETF | C8: Financials | D8: =VLOOKUP($A8, 'Sector Holdings'!$B$3:$H$130, 5, FALSE) -> 50.89 | E8: =VLOOKUP($A8, 'Sector Holdings'!$B$3:$I$130, 6, FALSE) -> 0 | F8: =D8*E8 -> 0 | G8: =VLOOKUP($A8, 'Sector Holdings'!$B$3:$I$130, 8, FALSE) -> 0 | H8: =IF(F8>0, F8/SUMIF(C:C,C8, F:F), "N/A") -> N/A
A9: XLV | B9: =VLOOKUP($A9, 'Sector Holdings'!$B$3:$C$130, 2, FALSE) -> SPDR Healthcare ETF | C9: Healthcare | D9: =VLOOKUP($A9, 'Sector Holdings'!$B$3:$H$130, 5, FALSE) -> 158.19 | E9: =VLOOKUP($A9, 'Sector Holdings'!$B$3:$I$130, 6, FALSE) -> 0 | F9: =D9*E9 -> 0 | G9: =VLOOKUP($A9, 'Sector Holdings'!$B$3:$I$130, 8, FALSE) -> 0 | H9: =IF(F9>0, F9/SUMIF(C:C,C9, F:F), "N/A") -> N/A
A10: XLI | B10: =VLOOKUP($A10, 'Sector Holdings'!$B$3:$C$130, 2, FALSE) -> SPDR Industrials ETF | C10: Industrials | D10: =VLOOKUP($A10, 'Sector Holdings'!$B$3:$H$130, 5, FALSE) -> 175.12 | E10: =VLOOKUP($A10, 'Sector Holdings'!$B$3:$I$130, 6, FALSE) -> 0 | F10: =D10*E10 -> 0 | G10: =VLOOKUP($A10, 'Sector Holdings'!$B$3:$I$130, 8, FALSE) -> 0 | H10: =IF(F10>0, F10/SUMIF(C:C,C10, F:F), "N/A") -> N/A
A11: XLRE | B11: =VLOOKUP($A11, 'Sector Holdings'!$B$3:$C$130, 2, FALSE) -> SPDR REITs ETF | C11: REITs | D11: =VLOOKUP($A11, 'Sector Holdings'!$B$3:$H$130, 5, FALSE) -> 43.68 | E11: =VLOOKUP($A11, 'Sector Holdings'!$B$3:$I$130, 6, FALSE) | F11: =D11*E11 -> 0 | G11: =VLOOKUP($A11, 'Sector Holdings'!$B$3:$I$130, 8, FALSE) -> 0 | H11: =IF(F11>0, F11/SUMIF(C:C,C11, F:F), "N/A") -> N/A
A12: XLK | B12: =VLOOKUP($A12, 'Sector Holdings'!$B$3:$C$130, 2, FALSE) -> SPDR Technology ETF | C12: Technology | D12: =VLOOKUP($A12, 'Sector Holdings'!$B$3:$H$130, 5, FALSE) -> 139.25 | E12: =VLOOKUP($A12, 'Sector Holdings'!$B$3:$I$130, 6, FALSE) -> 0 | F12: =D12*E12 -> 0 | G12: =VLOOKUP($A12, 'Sector Holdings'!$B$3:$I$130, 8, FALSE) -> 0 | H12: =IF(F12>0, F12/SUMIF(C:C,C12, F:F), "N/A") -> N/A
A13: XLC | B13: =VLOOKUP($A13, 'Sector Holdings'!$B$3:$C$130, 2, FALSE) -> SPDR Communications Services ETF | C13: Media & Telecom | D13: =VLOOKUP($A13, 'Sector Holdings'!$B$3:$H$130, 5, FALSE) -> 116.06 | E13: =VLOOKUP($A13, 'Sector Holdings'!$B$3:$I$130, 6, FALSE) -> 0 | F13: =D13*E13 -> 0 | G13: =VLOOKUP($A13, 'Sector Holdings'!$B$3:$I$130, 8, FALSE) -> 0 | H13: =IF(F13>0, F13/SUMIF(C:C,C13, F:F), "N/A") -> N/A
A14: XLU | B14: =VLOOKUP($A14, 'Sector Holdings'!$B$3:$C$130, 2, FALSE) -> SPDR Utilities ETF | C14: Utilities | D14: =VLOOKUP($A14, 'Sector Holdings'!$B$3:$H$130, 5, FALSE) -> 46.63 | E14: =VLOOKUP($A14, 'Sector Holdings'!$B$3:$I$130, 6, FALSE) -> 0 | F14: =D14*E14 -> 0 | G14: =VLOOKUP($A14, 'Sector Holdings'!$B$3:$I$130, 8, FALSE) -> 0 | H14: =IF(F14>0, F14/SUMIF(C:C,C14, F:F), "N/A") -> N/A
A15: AMZN | B15: =VLOOKUP(A15, 'Sector Holdings'!$B$3:$C$130, 2, FALSE) -> Amazon.com Inc | C15: Consumer Discretionary | D15: =VLOOKUP($A15, 'Sector Holdings'!$B$3:$H$130, 5, FALSE) -> 204.63 | E15: =VLOOKUP($A15, 'Sector Holdings'!$B$3:$I$130, 6, FALSE) -> 425 | F15: =D15*E15 -> 86967.75 | G15: =VLOOKUP($A15, 'Sector Holdings'!$B$3:$I$130, 8, FALSE) -> 0.032624884 | H15: =IF(F15>0, F15/SUMIF(C:C,C15, F:F), "N/A") -> #N/A
A16: GPC | B16: =VLOOKUP(A16, 'Sector Holdings'!$B$3:$C$130, 2, FALSE) -> #N/A | C16: Consumer Discretionary | D16: =VLOOKUP($A16, 'Sector Holdings'!$B$3:$H$130, 5, FALSE) -> #N/A | E16: =VLOOKUP($A16, 'Sector Holdings'!$B$3:$I$130, 6, FALSE) -> #N/A | F16: =D16*E16 -> #N/A | G16: =VLOOKUP($A16, 'Sector Holdings'!$B$3:$I$130, 8, FALSE) -> #N/A | H16: =IF(F16>0, F16/SUMIF(C:C,C16, F:F), "N/A") -> #N/A
A17: LVMUY | B17: =VLOOKUP(A17, 'Sector Holdings'!$B$3:$C$130, 2, FALSE) -> LVMH Moët Hennessy Louis Vuitton | C17: Consumer Discretionary | D17: =VLOOKUP($A17, 'Sector Holdings'!$B$3:$H$130, 5, FALSE) -> 132.36 | E17: =VLOOKUP($A17, 'Sector Holdings'!$B$3:$I$130, 6, FALSE) -> 258 | F17: =D17*E17 -> 34148.88 | G17: =VLOOKUP($A17, 'Sector Holdings'!$B$3:$I$130, 8, FALSE) -> 0.012810533 | H17: =IF(F17>0, F17/SUMIF(C:C,C17, F:F), "N/A") -> #N/A
A18: ABNB | B18: =VLOOKUP(A18, 'Sector Holdings'!$B$3:$C$130, 2, FALSE) -> Airbnb, Inc. | C18: Consumer Discretionary | D18: =VLOOKUP($A18, 'Sector Holdings'!$B$3:$H$130, 5, FALSE) -> 120.9 | E18: =VLOOKUP($A18, 'Sector Holdings'!$B$3:$I$130, 6, FALSE) -> 334 | F18: =D18*E18 -> 40380.6 | G18: =VLOOKUP($A18, 'Sector Holdings'!$B$3:$I$130, 8, FALSE) -> 0.015148287 | H18: =IF(F18>0, F18/SUMIF(C:C,C18, F:F), "N/A") -> #N/A
A19: IMKTA | B19: =VLOOKUP(A19, 'Sector Holdings'!$B$3:$C$130, 2, FALSE) -> #N/A | C19: Consumer Staples | D19: =VLOOKUP($A19, 'Sector Holdings'!$B$3:$H$130, 5, FALSE) -> #N/A | E19: =VLOOKUP($A19, 'Sector Holdings'!$B$3:$I$130, 6, FALSE) -> #N/A | F19: =D19*E19 -> #N/A | G19: =VLOOKUP($A19, 'Sector Holdings'!$B$3:$I$130, 8, FALSE) -> #N/A | H19: =IF(F19>0, F19/SUMIF(C:C,C19, F:F), "N/A") -> #N/A
A20: PM | B20: =VLOOKUP(A20, 'Sector Holdings'!$B$3:$C$130, 2, FALSE) -> Philip Morris International Inc. | C20: Consumer Staples | D20: =VLOOKUP($A20, 'Sector Holdings'!$B$3:$H$130, 5, FALSE) -> 185.24 | E20: =VLOOKUP($A20, 'Sector Holdings'!$B$3:$I$130, 6, FALSE) -> 243 | F20: =D20*E20 -> 45013.32 | G20: =VLOOKUP($A20, 'Sector Holdings'!$B$3:$I$130, 8, FALSE) -> 0.016886195 | H20: =IF(F20>0, F20/SUMIF(C:C,C20, F:F), "N/A") -> #N/A
A21: LNG | B21: =VLOOKUP(A21, 'Sector Holdings'!$B$3:$C$130, 2, FALSE) -> Cheniere Energy | C21: Energy | D21: =VLOOKUP($A21, 'Sector Holdings'!$B$3:$H$130, 5, FALSE) -> 226.62 | E21: =VLOOKUP($A21, 'Sector Holdings'!$B$3:$I$130, 6, FALSE) -> 323 | F21: =D21*E21 -> 73198.26 | G21: =VLOOKUP($A21, 'Sector Holdings'!$B$3:$I$130, 8, FALSE) -> 0.027459429 | H21: =IF(F21>0, F21/SUMIF(C:C,C21, F:F), "N/A") -> #N/A
A22: FANG | B22: =VLOOKUP(A22, 'Sector Holdings'!$B$3:$C$130, 2, FALSE) -> Diamondback Energy Inc | C22: Energy | D22: =VLOOKUP($A22, 'Sector Holdings'!$B$3:$H$130, 5, FALSE) -> 174.82 | E22: =VLOOKUP($A22, 'Sector Holdings'!$B$3:$I$130, 6, FALSE) -> 168 | F22: =D22*E22 -> 29369.76 | G22: =VLOOKUP($A22, 'Sector Holdings'!$B$3:$I$130, 8, FALSE) -> 0.011017705 | H22: =IF(F22>0, F22/SUMIF(C:C,C22, F:F), "N/A") -> #N/A
A23: TTE | B23: =VLOOKUP(A23, 'Sector Holdings'!$B$3:$C$130, 2, FALSE) -> #N/A | C23: Energy | D23: =VLOOKUP($A23, 'Sector Holdings'!$B$3:$H$130, 5, FALSE) -> #N/A | E23: =VLOOKUP($A23, 'Sector Holdings'!$B$3:$I$130, 6, FALSE) -> #N/A | F23: =D23*E23 -> #N/A | G23: =VLOOKUP($A23, 'Sector Holdings'!$B$3:$I$130, 8, FALSE) -> #N/A | H23: =IF(F23>0, F23/SUMIF(C:C,C23, F:F), "N/A") -> #N/A
A24: ICE | B24: =VLOOKUP(A24, 'Sector Holdings'!$B$3:$C$130, 2, FALSE) -> #N/A | C24: Financials | D24: =VLOOKUP($A24, 'Sector Holdings'!$B$3:$H$130, 5, FALSE) -> #N/A | E24: =VLOOKUP($A24, 'Sector Holdings'!$B$3:$I$130, 6, FALSE) -> #N/A | F24: =D24*E24 -> #N/A | G24: =VLOOKUP($A24, 'Sector Holdings'!$B$3:$I$130, 8, FALSE) -> #N/A | H24: =IF(F24>0, F24/SUMIF(C:C,C24, F:F), "N/A") -> #N/A
A25: MS | B25: =VLOOKUP(A25, 'Sector Holdings'!$B$3:$C$130, 2, FALSE) -> #N/A | C25: Financials | D25: =VLOOKUP($A25, 'Sector Holdings'!$B$3:$H$130, 5, FALSE) -> #N/A | E25: =VLOOKUP($A25, 'Sector Holdings'!$B$3:$I$130, 6, FALSE) -> #N/A | F25: =D25*E25 -> #N/A | G25: =VLOOKUP($A25, 'Sector Holdings'!$B$3:$I$130, 8, FALSE) -> #N/A | H25: =IF(F25>0, F25/SUMIF(C:C,C25, F:F), "N/A") -> #N/A
A26: PFG | B26: =VLOOKUP(A26, 'Sector Holdings'!$B$3:$C$130, 2, FALSE) -> Principal Financial Group Inc | C26: Financials | D26: =VLOOKUP($A26, 'Sector Holdings'!$B$3:$H$130, 5, FALSE) -> 93.27 | E26: =VLOOKUP($A26, 'Sector Holdings'!$B$3:$I$130, 6, FALSE) -> 41 | F26: =D26*E26 -> 3824.07 | G26: =VLOOKUP($A26, 'Sector Holdings'!$B$3:$I$130, 8, FALSE) -> 0.0014345529 | H26: =IF(F26>0, F26/SUMIF(C:C,C26, F:F), "N/A") -> #N/A
... A65: 912797LL9 | B65: =VLOOKUP(A65, 'Sector Holdings'!$B$3:$C$130, 2, FALSE) -> #N/A | C65: Fixed Income | D65: =VLOOKUP($A65, 'Sector Holdings'!$B$3:$H$130, 5, FALSE) -> #N/A | E65: =VLOOKUP($A65, 'Sector Holdings'!$B$3:$I$130, 6, FALSE) -> #N/A | F65: =D65*E65 -> #N/A | G65: =VLOOKUP($A65, 'Sector Holdings'!$B$3:$I$130, 8, FALSE) -> #N/A | H65: =IF(F65>0, F65/SUMIF(C:C,C65, F:F), "N/A") -> #N/A
A66: PXD | B66: =VLOOKUP($A66, OFFSET('Sector Holdings'!$A$1:$M$19, MATCH("Quant", 'Sector Holdings'!$A$1:$A$130, 0), 1), 2, FALSE) -> #N/A | C66: Quant (VC2) | D66: =VLOOKUP($A66, 'Sector Holdings'!$B$3:$H$130, 5, FALSE) -> #N/A | E66: =VLOOKUP($A66, OFFSET('Sector Holdings'!$A$1:$M$19, MATCH("Quant", 'Sector Holdings'!$A$1:$A$130, 0), 1), 6, FALSE) -> #N/A | F66: =D66*E66 -> #N/A | G66: =VLOOKUP($A66, OFFSET('Sector Holdings'!$A$1:$M$19, MATCH("Quant", 'Sector Holdings'!$A$1:$A$130, 0), 1), 8, FALSE) -> #N/A | H66: =IF(F66>0, F66/SUMIF(C:C,C66, F:F), "N/A") -> #N/A
A67: MPC | B67: =VLOOKUP($A67, OFFSET('Sector Holdings'!$A$1:$M$19, MATCH("Quant", 'Sector Holdings'!$A$1:$A$130, 0), 1), 2, FALSE) -> #N/A | C67: Quant (VC2) | D67: =VLOOKUP($A67, 'Sector Holdings'!$B$3:$H$130, 5, FALSE) -> #N/A | E67: =VLOOKUP($A67, OFFSET('Sector Holdings'!$A$1:$M$19, MATCH("Quant", 'Sector Holdings'!$A$1:$A$130, 0), 1), 6, FALSE) -> #N/A | F67: =D67*E67 -> #N/A | G67: =VLOOKUP($A67, OFFSET('Sector Holdings'!$A$1:$M$19, MATCH("Quant", 'Sector Holdings'!$A$1:$A$130, 0), 1), 8, FALSE) -> #N/A | H67: =IF(F67>0, F67/SUMIF(C:C,C67, F:F), "N/A") -> #N/A
A68: VNO | B68: =VLOOKUP($A68, OFFSET('Sector Holdings'!$A$1:$M$19, MATCH("Quant", 'Sector Holdings'!$A$1:$A$130, 0), 1), 2, FALSE) -> #N/A | C68: Quant (VC2) | D68: =VLOOKUP($A68, 'Sector Holdings'!$B$3:$H$130, 5, FALSE) -> #N/A | E68: =VLOOKUP($A68, OFFSET('Sector Holdings'!$A$1:$M$19, MATCH("Quant", 'Sector Holdings'!$A$1:$A$130, 0), 1), 6, FALSE) -> #N/A | F68: =D68*E68 -> #N/A | G68: =VLOOKUP($A68, OFFSET('Sector Holdings'!$A$1:$M$19, MATCH("Quant", 'Sector Holdings'!$A$1:$A$130, 0), 1), 8, FALSE) -> #N/A | H68: =IF(F68>0, F68/SUMIF(C:C,C68, F:F), "N/A") -> #N/A
A69: CF | B69: =VLOOKUP($A69, OFFSET('Sector Holdings'!$A$1:$M$19, MATCH("Quant", 'Sector Holdings'!$A$1:$A$130, 0), 1), 2, FALSE) -> #N/A | C69: Quant (VC2) | D69: =VLOOKUP($A69, 'Sector Holdings'!$B$3:$H$130, 5, FALSE) -> #N/A | E69: =VLOOKUP($A69, OFFSET('Sector Holdings'!$A$1:$M$19, MATCH("Quant", 'Sector Holdings'!$A$1:$A$130, 0), 1), 6, FALSE) -> #N/A | F69: =D69*E69 -> #N/A | G69: =VLOOKUP($A69, OFFSET('Sector Holdings'!$A$1:$M$19, MATCH("Quant", 'Sector Holdings'!$A$1:$A$130, 0), 1), 8, FALSE) -> #N/A | H69: =IF(F69>0, F69/SUMIF(C:C,C69, F:F), "N/A") -> #N/A
A70: NRG | B70: =VLOOKUP($A70, OFFSET('Sector Holdings'!$A$1:$M$19, MATCH("Quant", 'Sector Holdings'!$A$1:$A$130, 0), 1), 2, FALSE) -> #N/A | C70: Quant (VC2) | D70: =VLOOKUP($A70, 'Sector Holdings'!$B$3:$H$130, 5, FALSE) -> #N/A | E70: =VLOOKUP($A70, OFFSET('Sector Holdings'!$A$1:$M$19, MATCH("Quant", 'Sector Holdings'!$A$1:$A$130, 0), 1), 6, FALSE) -> #N/A | F70: =D70*E70 -> #N/A | G70: =VLOOKUP($A70, OFFSET('Sector Holdings'!$A$1:$M$19, MATCH("Quant", 'Sector Holdings'!$A$1:$A$130, 0), 1), 8, FALSE) -> #N/A | H70: =IF(F70>0, F70/SUMIF(C:C,C70, F:F), "N/A") -> #N/A
A71: SRE | B71: =VLOOKUP($A71, OFFSET('Sector Holdings'!$A$1:$M$19, MATCH("Quant", 'Sector Holdings'!$A$1:$A$130, 0), 1), 2, FALSE) -> #N/A | C71: Quant (G-Score) | D71: =VLOOKUP($A71, 'Sector Holdings'!$B$3:$H$130, 5, FALSE) -> #N/A | E71: =VLOOKUP($A71, OFFSET('Sector Holdings'!$A$1:$M$19, MATCH("Quant", 'Sector Holdings'!$A$1:$A$130, 0), 1), 6, FALSE) -> #N/A | F71: =D71*E71 -> #N/A | G71: =VLOOKUP($A71, OFFSET('Sector Holdings'!$A$1:$M$19, MATCH("Quant", 'Sector Holdings'!$A$1:$A$130, 0), 1), 8, FALSE) -> #N/A | H71: =IF(F71>0, F71/SUMIF(C:C,C71, F:F), "N/A") -> #N/A
A72: ADM | B72: =VLOOKUP($A72, OFFSET('Sector Holdings'!$A$1:$M$19, MATCH("Quant", 'Sector Holdings'!$A$1:$A$130, 0), 1), 2, FALSE) -> Archer-Daniels-Midland Co | C72: Quant (G-Score) | D72: =VLOOKUP($A72, 'Sector Holdings'!$B$3:$H$130, 5, FALSE) -> 67.98 | E72: =VLOOKUP($A72, OFFSET('Sector Holdings'!$A$1:$M$19, MATCH("Quant", 'Sector Holdings'!$A$1:$A$130, 0), 1), 6, FALSE) -> 59 | F72: =D72*E72 -> 4010.82 | G72: =VLOOKUP($A72, OFFSET('Sector Holdings'!$A$1:$M$19, MATCH("Quant", 'Sector Holdings'!$A$1:$A$130, 0), 1), 8, FALSE) -> 0.0015046099 | H72: =IF(F72>0, F72/SUMIF(C:C,C72, F:F), "N/A") -> #N/A
A73: HST | B73: =VLOOKUP($A73, OFFSET('Sector Holdings'!$A$1:$M$19, MATCH("Quant", 'Sector Holdings'!$A$1:$A$130, 0), 1), 2, FALSE) -> #N/A | C73: Quant (G-Score) | D73: =VLOOKUP($A73, 'Sector Holdings'!$B$3:$H$130, 5, FALSE) -> #N/A | E73: =VLOOKUP($A73, OFFSET('Sector Holdings'!$A$1:$M$19, MATCH("Quant", 'Sector Holdings'!$A$1:$A$130, 0), 1), 6, FALSE) -> #N/A | F73: =D73*E73 -> #N/A | G73: =VLOOKUP($A73, OFFSET('Sector Holdings'!$A$1:$M$19, MATCH("Quant", 'Sector Holdings'!$A$1:$A$130, 0), 1), 8, FALSE) -> #N/A | H73: =IF(F73>0, F73/SUMIF(C:C,C73, F:F), "N/A") -> #N/A
A74: PFE | B74: =VLOOKUP($A74, OFFSET('Sector Holdings'!$A$1:$M$19, MATCH("Quant", 'Sector Holdings'!$A$1:$A$130, 0), 1), 2, FALSE) -> #N/A | C74: Quant (G-Score) | D74: =VLOOKUP($A74, 'Sector Holdings'!$B$3:$H$130, 5, FALSE) -> #N/A | E74: =VLOOKUP($A74, OFFSET('Sector Holdings'!$A$1:$M$19, MATCH("Quant", 'Sector Holdings'!$A$1:$A$130, 0), 1), 6, FALSE) -> #N/A | F74: =D74*E74 -> #N/A | G74: =VLOOKUP($A74, OFFSET('Sector Holdings'!$A$1:$M$19, MATCH("Quant", 'Sector Holdings'!$A$1:$A$130, 0), 1), 8, FALSE) -> #N/A | H74: =IF(F74>0, F74/SUMIF(C:C,C74, F:F), "N/A") -> #N/A
A75: NI | B75: =VLOOKUP($A75, OFFSET('Sector Holdings'!$A$1:$M$19, MATCH("Quant", 'Sector Holdings'!$A$1:$A$130, 0), 1), 2, FALSE) -> #N/A | C75: Quant (G-Score) | D75: =VLOOKUP($A75, 'Sector Holdings'!$B$3:$H$130, 5, FALSE) -> #N/A | E75: =VLOOKUP($A75, OFFSET('Sector Holdings'!$A$1:$M$19, MATCH("Quant", 'Sector Holdings'!$A$1:$A$130, 0), 1), 6, FALSE) -> #N/A | F75: =D75*E75 -> #N/A | G75: =VLOOKUP($A75, OFFSET('Sector Holdings'!$A$1:$M$19, MATCH("Quant", 'Sector Holdings'!$A$1:$A$130, 0), 1), 8, FALSE) -> #N/A | H75: =IF(F75>0, F75/SUMIF(C:C,C75, F:F), "N/A") -> #N/A
A76: LKQ | B76: =VLOOKUP($A76, OFFSET('Sector Holdings'!$A$1:$M$19, MATCH("Quant", 'Sector Holdings'!$A$1:$A$130, 0), 1), 2, FALSE) -> #N/A | C76: Quant (G-Score) | D76: =VLOOKUP($A76, 'Sector Holdings'!$B$3:$H$130, 5, FALSE) -> #N/A | E76: =VLOOKUP($A76, OFFSET('Sector Holdings'!$A$1:$M$19, MATCH("Quant", 'Sector Holdings'!$A$1:$A$130, 0), 1), 6, FALSE) -> #N/A | F76: =D76*E76 -> #N/A | G76: =VLOOKUP($A76, OFFSET('Sector Holdings'!$A$1:$M$19, MATCH("Quant", 'Sector Holdings'!$A$1:$A$130, 0), 1), 8, FALSE) -> #N/A | H76: =IF(F76>0, F76/SUMIF(C:C,C76, F:F), "N/A") -> #N/A
A77: PM | B77: =VLOOKUP($A77, OFFSET('Sector Holdings'!$A$1:$M$19, MATCH("Quant", 'Sector Holdings'!$A$1:$A$130, 0), 1), 2, FALSE) -> #N/A | C77: Quant (G-Score) | D77: =VLOOKUP($A77, 'Sector Holdings'!$B$3:$H$130, 5, FALSE) -> 185.24 | E77: =VLOOKUP($A77, OFFSET('Sector Holdings'!$A$1:$M$19, MATCH("Quant", 'Sector Holdings'!$A$1:$A$130, 0), 1), 6, FALSE) -> #N/A | F77: =D77*E77 -> #N/A | G77: =VLOOKUP($A77, OFFSET('Sector Holdings'!$A$1:$M$19, MATCH("Quant", 'Sector Holdings'!$A$1:$A$130, 0), 1), 8, FALSE) -> #N/A | H77: =IF(F77>0, F77/SUMIF(C:C,C77, F:F), "N/A") -> #N/A
... A80: MRNA | B80: =VLOOKUP($A80, OFFSET('Sector Holdings'!$A$1:$M$19, MATCH("Quant", 'Sector Holdings'!$A$1:$A$130, 0), 1), 2, FALSE) -> #N/A | C80: Quant (G-Score) | D80: =VLOOKUP($A80, 'Sector Holdings'!$B$3:$H$130, 5, FALSE) -> #N/A | E80: =VLOOKUP($A80, OFFSET('Sector Holdings'!$A$1:$M$19, MATCH("Quant", 'Sector Holdings'!$A$1:$A$130, 0), 1), 6, FALSE) -> #N/A | F80: =D80*E80 -> #N/A | G80: =VLOOKUP($A80, OFFSET('Sector Holdings'!$A$1:$M$19, MATCH("Quant", 'Sector Holdings'!$A$1:$A$130, 0), 1), 8, FALSE) -> #N/A | H80: =IF(F80>0, F80/SUMIF(C:C,C80, F:F), "N/A") -> #N/A

Sheet Sector Holdings
B1: Ticker/CUSIP | C1: Description | E1: Last 1Y Performance | F1: Current Price | G1: Share Count | H1: Value | I1: % of Porfolio | J1: Target % of Portfolio | L1: Purchase Price | M1: Purchase Date | N1: % Return to Date | O1: % Return to Date Over Benchmark ETF | P1: % Return to Date Over S&P | Q1: Beta | S1: Latest Thesis | T1: Thesis Date | U1: Thesis Price Target | V1: % Premium Over Thesis
A2: Consumer Discretionary
B3: AMZN | C3: Amazon.com Inc | E3: =IFERROR(__xludf.DUMMYFUNCTION("SPARKLINE(GOOGLEFINANCE(B3, ""price"", TODAY()-365, TODAY(), ""DAILY""))"),"") | F3: =IFERROR(__xludf.DUMMYFUNCTION("IFERROR(GOOGLEFINANCE(B3), 0)"),204.63) -> 204.63 | G3: 425 | H3: =F3*G3 -> 86967.75 | I3: =H3/$H$121 -> 0.032624884 | J3: 0.015 | L3: 90.851349 | M3: 43293.535 | N3: =(F3/L3-1) -> 1.2523606 | O3: =IFERROR(__xludf.DUMMYFUNCTION("N3 - ((GOOGLEFINANCE(""XLY"")/INDEX(GOOGLEFINANCE(""XLY"",""price"",M3),2,2))-1)"),0.21354985343165156) -> 0.21354985 | P3: =IFERROR(__xludf.DUMMYFUNCTION("N3 - ((GOOGLEFINANCE(""SPY"")/INDEX(GOOGLEFINANCE(""SPY"",""price"",M3),2,2))-1)"),-0.19067193099239255) -> -0.19067193 | Q3: =IFERROR(__xludf.DUMMYFUNCTION("IFERROR(GOOGLEFINANCE(B3, ""beta""), ""N/A"")"),1.37) -> 1.37 | S3: Hold | T3: 45748 | U3: 211.08 | V3: =IFERROR(F3/U3-1, "NA") -> -0.030557135
B4: LVMUY | C4: LVMH Moët Hennessy Louis Vuitton | E4: =IFERROR(__xludf.DUMMYFUNCTION("SPARKLINE(GOOGLEFINANCE(B4, ""price"", TODAY()-365, TODAY(), ""DAILY""))"),"") | F4: =IFERROR(__xludf.DUMMYFUNCTION("IFERROR(GOOGLEFINANCE(B4), 0)"),132.36) -> 132.36 | G4: 258 | H4: =F4*G4 -> 34148.88 | I4: =H4/$H$121 -> 0.012810533 | J4: 0.015 | L4: 131.05 | M4: 44676 | N4: =(F4/L4-1) -> 0.0099961847 | O4: =IFERROR(__xludf.DUMMYFUNCTION("N4 - ((GOOGLEFINANCE(""XLY"")/INDEX(GOOGLEFINANCE(""XLY"",""price"",M4),2,2))-1)"),-0.28328444774872463) -> -0.28328445 | P4: =IFERROR(__xludf.DUMMYFUNCTION("N4 - ((GOOGLEFINANCE(""SPY"")/INDEX(GOOGLEFINANCE(""SPY"",""price"",M4),2,2))-1)"),-0.5827554430709658) -> -0.58275544 | Q4: =IFERROR(__xludf.DUMMYFUNCTION("IFERROR(GOOGLEFINANCE(B4, ""beta""), ""N/A"")"),1.14) -> 1.14 | S4: Hold | T4: 45589 | U4: 172.46 | V4: =IFERROR(F4/U4-1, "NA") -> -0.23251769
B5: ABNB | C5: Airbnb, Inc. | E5: =IFERROR(__xludf.DUMMYFUNCTION("SPARKLINE(GOOGLEFINANCE(B5, ""price"", TODAY()-365, TODAY(), ""DAILY""))"),"") | F5: =IFERROR(__xludf.DUMMYFUNCTION("IFERROR(GOOGLEFINANCE(B5), 0)"),120.9) -> 120.9 | G5: 334 | H5: =F5*G5 -> 40380.6 | I5: =H5/$H$121 -> 0.015148287 | J5: 0.015 | L5: 97.8 | M5: 44883 | N5: =(F5/L5-1) -> 0.23619632 | O5: =IFERROR(__xludf.DUMMYFUNCTION("N5 - ((GOOGLEFINANCE(""XLY"")/INDEX(GOOGLEFINANCE(""XLY"",""price"",M5),2,2))-1)"),-0.38820084410216227) -> -0.38820084 | P5: =IFERROR(__xludf.DUMMYFUNCTION("N5 - ((GOOGLEFINANCE(""SPY"")/INDEX(GOOGLEFINANCE(""SPY"",""price"",M5),2,2))-1)"),-0.4871832229354873) -> -0.48718322 | Q5: =IFERROR(__xludf.DUMMYFUNCTION("IFERROR(GOOGLEFINANCE(B5, ""beta""), ""N/A"")"),1.15) -> 1.15 | S5: Hold | T5: 45951 | U5: 138.11 | V5: =IFERROR(F5/U5-1, "NA") -> -0.12461082
B6: EVVTY | C6: Evolution ADR | E6: =IFERROR(__xludf.DUMMYFUNCTION("SPARKLINE(GOOGLEFINANCE(B6, ""price"", TODAY()-365, TODAY(), ""DAILY""))"),"") | F6: =IFERROR(__xludf.DUMMYFUNCTION("IFERROR(GOOGLEFINANCE(B6), 0)"),57.42) -> 57.42 | G6: 608 | H6: =F6*G6 -> 34911.36 | I6: =H6/$H$121 -> 0.013096568 | J6: 0.015 | L6: 90.75699 | M6: 45219 | N6: =(F6/L6-1) -> -0.36732146 | O6: =IFERROR(__xludf.DUMMYFUNCTION("N6 - ((GOOGLEFINANCE(""XLY"")/INDEX(GOOGLEFINANCE(""XLY"",""price"",M6),2,2))-1)"),-0.8771434772629572) -> -0.87714348 | P6: =IFERROR(__xludf.DUMMYFUNCTION("N6 - ((GOOGLEFINANCE(""SPY"")/INDEX(GOOGLEFINANCE(""SPY"",""price"",M6),2,2))-1)"),-0.9877540439933794) -> -0.98775404 | Q6: =IFERROR(__xludf.DUMMYFUNCTION("IFERROR(GOOGLEFINANCE(B6, ""beta""), ""N/A"")"),1.38) -> 1.38 | S6: Hold | T6: 45741 | U6: 96.86 | V6: =IFERROR(F6/U6-1, "NA") -> -0.40718563
B7: XLY | C7: SPDR Discretionary ETF | E7: =IFERROR(__xludf.DUMMYFUNCTION("SPARKLINE(GOOGLEFINANCE(B7, ""price"", TODAY()-365, TODAY(), ""DAILY""))"),"") | F7: =IFERROR(__xludf.DUMMYFUNCTION("IFERROR(GOOGLEFINANCE(B7), 0)"),114.52) -> 114.52 | G7: 0 | H7: =F7*G7 -> 0 | I7: =H7/$H$121 -> 0 | J7: =I7 -> 0 | L7: 179.75 | M7: 45191 | N7: =(F7/L7-1) -> -0.36289291 | Q7: =IFERROR(__xludf.DUMMYFUNCTION("IFERROR(GOOGLEFINANCE(B7, ""beta""), ""N/A"")"),"N/A") -> N/A | S7: NA | T7: NA | U7: NA | V7: =IFERROR(F7/U7-1, "NA") -> NA
A8: Sector Total | H8: =SUM(H3:H7) -> 196408.59 | I8: =H8/$H$121 -> 0.073680273 | J8: 0.08 | L8: =SUMPRODUCT(L3:L7*G3:G7) -> 160268.17 | M8: =AVERAGE(M3:M7) -> 44652.507 | N8: =H8/L8-1 -> 0.22549965 | Q8: =SUMPRODUCT(I3:I5/SUMIF(Q3:Q5, "<>N/A", I3:I5),Q3:Q5) -> 1.2663575
A10: Consumer Staples
B11: PM | C11: Philip Morris International Inc. | E11: =IFERROR(__xludf.DUMMYFUNCTION("SPARKLINE(GOOGLEFINANCE(B11, ""price"", TODAY()-365, TODAY(), ""DAILY""))"),"") | F11: =IFERROR(__xludf.DUMMYFUNCTION("GOOGLEFINANCE(B11)"),185.24) -> 185.24 | G11: 243 | H11: =F11*G11 -> 45013.32 | I11: =H11/$H$121 -> 0.016886195 | J11: 0.015 | L11: 90.63 | M11: 44862 | N11: =(F11/L11-1) -> 1.0439148 | O11: =IFERROR(__xludf.DUMMYFUNCTION("N11 - ((GOOGLEFINANCE(""XLP"")/INDEX(GOOGLEFINANCE(""XLP"",""price"",M11),2,2))-1)"),0.8311226905714939) -> 0.83112269 | P11: =IFERROR(__xludf.DUMMYFUNCTION("N11 - ((GOOGLEFINANCE(""SPY"")/INDEX(GOOGLEFINANCE(""SPY"",""price"",M11),2,2))-1)"),0.28948059917242963) -> 0.2894806 | Q11: =IFERROR(__xludf.DUMMYFUNCTION("IFERROR(GOOGLEFINANCE(B11, ""beta""), ""N/A"")"),0.39) -> 0.39 | S11: Buy at 1.5% | T11: 44859 | U11: 95.36 | V11: =IFERROR(F11/U11-1, "NA") -> 0.94253356
B12: POST | C12: Post Holdings Inc | E12: =IFERROR(__xludf.DUMMYFUNCTION("SPARKLINE(GOOGLEFINANCE(B12, ""price"", TODAY()-365, TODAY(), ""DAILY""))"),"") | F12: =IFERROR(__xludf.DUMMYFUNCTION("GOOGLEFINANCE(B12)"),106.42) -> 106.42 | G12: 612 | H12: =F12*G12 -> 65129.04 | I12: =H12/$H$121 -> 0.02443236 | J12: 0.015 | L12: 85.08 | M12: 45212 | N12: =(F12/L12-1) -> 0.25082276 | O12: =IFERROR(__xludf.DUMMYFUNCTION("N12 - ((GOOGLEFINANCE(""XLP"")/INDEX(GOOGLEFINANCE(""XLP"",""price"",M12),2,2))-1)"),-0.07762035871838835) -> -0.077620359 | P12: =IFERROR(__xludf.DUMMYFUNCTION("N12 - ((GOOGLEFINANCE(""SPY"")/INDEX(GOOGLEFINANCE(""SPY"",""price"",M12),2,2))-1)"),-0.33089219280224835) -> -0.33089219 | Q12: =IFERROR(__xludf.DUMMYFUNCTION("IFERROR(GOOGLEFINANCE(B12, ""beta""), ""N/A"")"),0.44) -> 0.44 | S12: Hold | T12: 45552 | U12: 127.43 | V12: =IFERROR(F12/U12-1, "NA") -> -0.16487483
B13: SFM | C13: Sprouts Farmers Market Inc | E13: =IFERROR(__xludf.DUMMYFUNCTION("SPARKLINE(GOOGLEFINANCE(B13, ""price"", TODAY()-365, TODAY(), ""DAILY""))"),"") | F13: =IFERROR(__xludf.DUMMYFUNCTION("GOOGLEFINANCE(B13)"),71.22) -> 71.22 | G13: 400 | H13: =F13*G13 -> 28488 | I13: =H13/$H$121 -> 0.010686924 | J13: 0.0125 | L13: 43.19 | M13: 45240 | N13: =(F13/L13-1) -> 0.64899282 | O13: =IFERROR(__xludf.DUMMYFUNCTION("N13 - ((GOOGLEFINANCE(""XLP"")/INDEX(GOOGLEFINANCE(""XLP"",""price"",M13),2,2))-1)"),0.3621598757768647) -> 0.36215988 | P13: =IFERROR(__xludf.DUMMYFUNCTION("N13 - ((GOOGLEFINANCE(""SPY"")/INDEX(GOOGLEFINANCE(""SPY"",""price"",M13),2,2))-1)"),0.09998122485466454) -> 0.099981225 | Q13: =IFERROR(__xludf.DUMMYFUNCTION("IFERROR(GOOGLEFINANCE(B13, ""beta""), ""N/A"")"),0.75) -> 0.75 | S13: Trim to 1.25% | T13: 45575 | U13: 115.69 | V13: =IFERROR(F13/U13-1, "NA") -> -0.38438932
B14: XLP | C14: SPDR Consumer Staples ETF | E14: =IFERROR(__xludf.DUMMYFUNCTION("SPARKLINE(GOOGLEFINANCE(B14, ""price"", TODAY()-365, TODAY(), ""DAILY""))"),"") | F14: =IFERROR(__xludf.DUMMYFUNCTION("GOOGLEFINANCE(B14)"),88.74) -> 88.74 | G14: 0 | H14: =F14*G14 -> 0 | I14: =H14/$H$121 -> 0 | J14: =I14 -> 0 | L14: 72.98 | M14: 44594 | N14: =(F14/L14-1) -> 0.21594958 | Q14: =IFERROR(__xludf.DUMMYFUNCTION("IFERROR(GOOGLEFINANCE(B14, ""beta""), ""N/A"")"),"N/A") -> N/A | S14: NA | T14: NA | U14: NA | V14: =IFERROR(F14/U14-1, "NA") -> NA
A15: Sector Total | H15: =SUM(H11:H14) -> 138630.36 | I15: =H15/$H$121 -> 0.052005479 | J15: 0.05 | L15: =SUMPRODUCT(L11:L14*G11:G14) -> 91368.05 | M15: =AVERAGE(M11:M14) -> 44977 | N15: =H15/L15-1 -> 0.51727393 | Q15: =SUMPRODUCT(I11:I13/SUMIF(Q11:Q13, "<>N/A", I11:I13),Q11:Q13) -> 0.48746878
A17: Energy
B18: LNG | C18: Cheniere Energy | E18: =IFERROR(__xludf.DUMMYFUNCTION("SPARKLINE(GOOGLEFINANCE(B18, ""price"", TODAY()-365, TODAY(), ""DAILY""))"),"") | F18: =IFERROR(__xludf.DUMMYFUNCTION("IFERROR(GOOGLEFINANCE(B18), 0)"),226.62) -> 226.62 | G18: 323 | H18: =F18*G18 -> 73198.26 | I18: =H18/$H$121 -> 0.027459429 | J18: 0.0075 | L18: 65.12 | M18: 43580 | N18: =(F18/L18-1) -> 2.4800369 | O18: =IFERROR(__xludf.DUMMYFUNCTION("N18 - ((GOOGLEFINANCE(""XLE"")/INDEX(GOOGLEFINANCE(""XLE"",""price"",M18),2,2))-1)"),1.8359235912514598) -> 1.8359236 | P18: =IFERROR(__xludf.DUMMYFUNCTION("N18 - ((GOOGLEFINANCE(""SPY"")/INDEX(GOOGLEFINANCE(""SPY"",""price"",M18),2,2))-1)"),1.1430740062095994) -> 1.143074 | Q18: =IFERROR(__xludf.DUMMYFUNCTION("IFERROR(GOOGLEFINANCE(B18, ""beta""), ""N/A"")"),0.27) -> 0.27 | S18: Hold | T18: 45566 | U18: 225.45 | V18: =IFERROR(F18/U18-1, "NA") -> 0.0051896208
B19: FANG | C19: Diamondback Energy Inc | E19: =IFERROR(__xludf.DUMMYFUNCTION("SPARKLINE(GOOGLEFINANCE(B19, ""price"", TODAY()-365, TODAY(), ""DAILY""))"),"") | F19: =IFERROR(__xludf.DUMMYFUNCTION("IFERROR(GOOGLEFINANCE(B19), 0)"),174.82) -> 174.82 | G19: 168 | H19: =F19*G19 -> 29369.76 | I19: =H19/$H$121 -> 0.011017705 | J19: 0.015 | L19: 80.61 | M19: 43873 | N19: =(F19/L19-1) -> 1.1687136 | O19: =IFERROR(__xludf.DUMMYFUNCTION("N19 - ((GOOGLEFINANCE(""XLE"")/INDEX(GOOGLEFINANCE(""XLE"",""price"",M19),2,2))-1)"),0.1643530939954938) -> 0.16435309 | P19: =IFERROR(__xludf.DUMMYFUNCTION("N19 - ((GOOGLEFINANCE(""SPY"")/INDEX(GOOGLEFINANCE(""SPY"",""price"",M19),2,2))-1)"),0.14598224502250723) -> 0.14598225 | Q19: =IFERROR(__xludf.DUMMYFUNCTION("IFERROR(GOOGLEFINANCE(B19, ""beta""), ""N/A"")"),0.61) -> 0.61 | S19: Hold | T19: 45610 | U19: 213.57 | V19: =IFERROR(F19/U19-1, "NA") -> -0.18143934
B20: GEV | C20: GE Vernova | E20: =IFERROR(__xludf.DUMMYFUNCTION("SPARKLINE(GOOGLEFINANCE(B20, ""price"", TODAY()-365, TODAY(), ""DAILY""))"),"") | F20: =IFERROR(__xludf.DUMMYFUNCTION("IFERROR(GOOGLEFINANCE(B20), 0)"),822.8) -> 822.8 | G20: 32 | H20: =F20*G20 -> 26329.6 | I20: =H20/$H$121 -> 0.0098772264 | J20: 0.0016 | L20: 146.63 | M20: 45372 | N20: =(F20/L20-1) -> 4.6114029 | O20: =IFERROR(__xludf.DUMMYFUNCTION("N20 - ((GOOGLEFINANCE(""XLI"")/INDEX(GOOGLEFINANCE(""XLI"",""price"",M20),2,2))-1)"),4.217579227662694) -> 4.2175792 | P20: =IFERROR(__xludf.DUMMYFUNCTION("N20 - ((GOOGLEFINANCE(""SPY"")/INDEX(GOOGLEFINANCE(""SPY"",""price"",M20),2,2))-1)"),4.304413191578247) -> 4.3044132 | Q20: =IFERROR(__xludf.DUMMYFUNCTION("IFERROR(GOOGLEFINANCE(B20, ""beta""), ""N/A"")"),"N/A") -> N/A | S20: Hold | T20: 45700 | U20: 336.63 | V20: =IFERROR(F20/U20-1, "NA") -> 1.4442266
B21: SLB | C21: Schlumberger Ltd | E21: =IFERROR(__xludf.DUMMYFUNCTION("SPARKLINE(GOOGLEFINANCE(B21, ""price"", TODAY()-365, TODAY(), ""DAILY""))"),"") | F21: =IFERROR(__xludf.DUMMYFUNCTION("IFERROR(GOOGLEFINANCE(B21), 0)"),50.73) -> 50.73 | G21: 502 | H21: =F21*G21 -> 25466.46 | I21: =H21/$H$121 -> 0.00955343 | J21: 0.007 | L21: 36.691 | M21: 45964 | N21: =(F21/L21-1) -> 0.38262789 | O21: =IFERROR(__xludf.DUMMYFUNCTION("N21 - ((GOOGLEFINANCE(""XLI"")/INDEX(GOOGLEFINANCE(""XLI"",""price"",M21),2,2))-1)"),0.24843100120697104) -> 0.248431 | P21: =IFERROR(__xludf.DUMMYFUNCTION("N21 - ((GOOGLEFINANCE(""SPY"")/INDEX(GOOGLEFINANCE(""SPY"",""price"",M21),2,2))-1)"),0.3838425146950487) -> 0.38384251 | Q21: =IFERROR(__xludf.DUMMYFUNCTION("IFERROR(GOOGLEFINANCE(B21, ""beta""), ""N/A"")"),0.72) -> 0.72 | S21: Buy at 0.7% | T21: 45958 | U21: 47.51 | V21: =IFERROR(F21/U21-1, "NA") -> 0.067775205
B22: XLE | C22: SPDR Energy ETF | E22: =IFERROR(__xludf.DUMMYFUNCTION("SPARKLINE(GOOGLEFINANCE(B22, ""price"", TODAY()-365, TODAY(), ""DAILY""))"),"") | F22: =IFERROR(__xludf.DUMMYFUNCTION("IFERROR(GOOGLEFINANCE(B22), 0)"),55.16) -> 55.16 | G22: 0 | H22: =F22*G22 -> 0 | I22: =H22/$H$121 -> 0 | J22: =I22 -> 0 | L22: 80.25 | M22: 44624 | N22: =(F22/L22-1) -> -0.31264798 | Q22: =IFERROR(__xludf.DUMMYFUNCTION("IFERROR(GOOGLEFINANCE(B22, ""beta""), ""N/A"")"),"N/A") -> N/A | S22: NA | T22: NA | U22: NA | V22: =IFERROR(F22/U22-1, "NA") -> NA
A23: Sector Total | H23: =SUM(H18:H22) -> 154364.08 | I23: =H23/$H$121 -> 0.057907791 | J23: 0.055 | L23: =SUMPRODUCT(L18:L22*G18:G22) -> 57687.282 | M23: =AVERAGE(M18:M22) -> 44682.6 | N23: =H23/L23-1 -> 1.6758772 | Q23: =SUMPRODUCT(I18:I19/SUMIF(Q18:Q19, "<>N/A", I18:I19), Q18:Q19) -> 0.36735704
A25: Financials
B26: FISV | C26: Fiserv Inc | E26: =IFERROR(__xludf.DUMMYFUNCTION("SPARKLINE(GOOGLEFINANCE(B26, ""price"", TODAY()-365, TODAY(), ""DAILY""))"),"") | F26: =IFERROR(__xludf.DUMMYFUNCTION("IFERROR(GOOGLEFINANCE(""ETR:FIV"", ""price""), 0)*GOOGLEFINANCE(""CURRENCY:EURUSD"")"),59.552955000000004) -> 59.552955 | G26: 401 | H26: =F26*G26 -> 23880.735 | I26: =H26/$H$121 -> 0.0089585647 | J26: 0.01 | L26: 94.914 | M26: 44524 | N26: =(F26/L26-1) -> -0.37255879 | O26: =IFERROR(__xludf.DUMMYFUNCTION("N26 - ((GOOGLEFINANCE(""XLF"")/INDEX(GOOGLEFINANCE(""XLF"",""price"",M26),2,2))-1)"),-0.6416360967957501) -> -0.6416361 | P26: =IFERROR(__xludf.DUMMYFUNCTION("N26 - ((GOOGLEFINANCE(""SPY"")/INDEX(GOOGLEFINANCE(""SPY"",""price"",M26),2,2))-1)"),-0.8264400102398154) -> -0.82644001 | Q26: =IFERROR(__xludf.DUMMYFUNCTION("IFERROR(GOOGLEFINANCE(B26, ""beta""), ""N/A"")"),0.78) -> 0.78 | S26: Raise to 1% | T26: 45960 | U26: 117.26 | V26: =IFERROR(F26/U26-1, "NA") -> -0.49212899
B27: ACGL | C27: Arch Capital Group Ltd | E27: =IFERROR(__xludf.DUMMYFUNCTION("SPARKLINE(GOOGLEFINANCE(B27, ""price"", TODAY()-365, TODAY(), ""DAILY""))"),"") | F27: =IFERROR(__xludf.DUMMYFUNCTION("IFERROR(GOOGLEFINANCE(B27), 0)"),98.38) -> 98.38 | G27: 561 | H27: =F27*G27 -> 55191.18 | I27: =H27/$H$121 -> 0.020704294 | J27: 0.0145 | L27: 55.14 | M27: 44790.204 | N27: =(F27/L27-1) -> 0.78418571 | O27: =IFERROR(__xludf.DUMMYFUNCTION("N27 - ((GOOGLEFINANCE(""XLF"")/INDEX(GOOGLEFINANCE(""XLF"",""price"",M27),2,2))-1)"),0.3558949428958471) -> 0.35589494 | P27: =IFERROR(__xludf.DUMMYFUNCTION("N27 - ((GOOGLEFINANCE(""SPY"")/INDEX(GOOGLEFINANCE(""SPY"",""price"",M27),2,2))-1)"),0.18449040850641873) -> 0.18449041 | Q27: =IFERROR(__xludf.DUMMYFUNCTION("IFERROR(GOOGLEFINANCE(B27, ""beta""), ""N/A"")"),0.42) -> 0.42 | S27: Hold | T27: 45706 | U27: 101.5 | V27: =IFERROR(F27/U27-1, "NA") -> -0.030738916
B28: AGM | C28: Farmer Mac | E28: =IFERROR(__xludf.DUMMYFUNCTION("SPARKLINE(GOOGLEFINANCE(B28, ""price"", TODAY()-365, TODAY(), ""DAILY""))"),"") | F28: =IFERROR(__xludf.DUMMYFUNCTION("IFERROR(GOOGLEFINANCE(B28), 0)"),152.99) -> 152.99 | G28: 162 | H28: =F28*G28 -> 24784.38 | I28: =H28/$H$121 -> 0.009297556 | J28: 0.0145 | L28: 147.16 | M28: 45212 | N28: =(F28/L28-1) -> 0.039616744 | O28: =IFERROR(__xludf.DUMMYFUNCTION("N28 - ((GOOGLEFINANCE(""XLF"")/INDEX(GOOGLEFINANCE(""XLF"",""price"",M28),2,2))-1)"),-0.4927530244617777) -> -0.49275302 | P28: =IFERROR(__xludf.DUMMYFUNCTION("N28 - ((GOOGLEFINANCE(""SPY"")/INDEX(GOOGLEFINANCE(""SPY"",""price"",M28),2,2))-1)"),-0.542098204175967) -> -0.5420982 | Q28: =IFERROR(__xludf.DUMMYFUNCTION("IFERROR(GOOGLEFINANCE(B28, ""beta""), ""N/A"")"),0.99) -> 0.99 | S28: Hold | T28: 45729 | U28: 245 | V28: =IFERROR(F28/U28-1, "NA") -> -0.37555102
B29: SPGI | C29: S&P Global Inc | E29: =IFERROR(__xludf.DUMMYFUNCTION("SPARKLINE(GOOGLEFINANCE(B29, ""price"", TODAY()-365, TODAY(), ""DAILY""))"),"") | F29: =IFERROR(__xludf.DUMMYFUNCTION("IFERROR(GOOGLEFINANCE(B29), 0)"),409.79) -> 409.79 | G29: 150 | H29: =F29*G29 -> 61468.5 | I29: =H29/$H$121 -> 0.023059154 | J29: 0.0167 | L29: 442.15124 | M29: 45372 | N29: =(F29/L29-1) -> -0.073190429 | O29: =IFERROR(__xludf.DUMMYFUNCTION("N29 - ((GOOGLEFINANCE(""XLF"")/INDEX(GOOGLEFINANCE(""XLF"",""price"",M29),2,2))-1)"),-0.28774890172851597) -> -0.2877489 | P29: =IFERROR(__xludf.DUMMYFUNCTION("N29 - ((GOOGLEFINANCE(""SPY"")/INDEX(GOOGLEFINANCE(""SPY"",""price"",M29),2,2))-1)"),-0.3801800883092479) -> -0.38018009 | Q29: =IFERROR(__xludf.DUMMYFUNCTION("IFERROR(GOOGLEFINANCE(B29, ""beta""), ""N/A"")"),1.2) -> 1.2 | S29: Buy at 1.67% | T29: 45365 | U29: 505.86 | V29: =IFERROR(F29/U29-1, "NA") -> -0.18991421
B30: SNEX | C30: Stonex Group Inc | E30: =IFERROR(__xludf.DUMMYFUNCTION("SPARKLINE(GOOGLEFINANCE(B30, ""price"", TODAY()-365, TODAY(), ""DAILY""))"),"") | F30: =IFERROR(__xludf.DUMMYFUNCTION("IFERROR(GOOGLEFINANCE(B30), 0)"),127.48) -> 127.48 | G30: 802 | H30: =F30*G30 -> 102238.96 | I30: =H30/$H$121 -> 0.038353691 | J30: 0.0165 | L30: 62.006892 | M30: 45597 | N30: =(F30/L30-1) -> 1.0559005 | O30: =IFERROR(__xludf.DUMMYFUNCTION("N30 - ((GOOGLEFINANCE(""XLF"")/INDEX(GOOGLEFINANCE(""XLF"",""price"",M30),2,2))-1)"),0.9647769940272952) -> 0.96477699 | P30: =IFERROR(__xludf.DUMMYFUNCTION("N30 - ((GOOGLEFINANCE(""SPY"")/INDEX(GOOGLEFINANCE(""SPY"",""price"",M30),2,2))-1)"),0.8606952536067594) -> 0.86069525 | Q30: =IFERROR(__xludf.DUMMYFUNCTION("IFERROR(GOOGLEFINANCE(B30, ""beta""), ""N/A"")"),0.22) -> 0.22 | S30: Buy at 1.65% | T30: 45597 | U30: 101.14 | V30: =IFERROR(F30/U30-1, "NA") -> 0.26043109
B31: NATL | C31: NCR Atleos Corp | E31: =IFERROR(__xludf.DUMMYFUNCTION("SPARKLINE(GOOGLEFINANCE(B31, ""price"", TODAY()-365, TODAY(), ""DAILY""))"),"") | F31: =IFERROR(__xludf.DUMMYFUNCTION("IFERROR(GOOGLEFINANCE(B31), 0)"),40.29) -> 40.29 | G31: 910 | H31: =F31*G31 -> 36663.9 | I31: =H31/$H$121 -> 0.013754012 | J31: 0.0125 | L31: 36.219 | M31: 45964 | N31: =(F31/L31-1) -> 0.11239957 | O31: =IFERROR(__xludf.DUMMYFUNCTION("N31 - ((GOOGLEFINANCE(""XLF"")/INDEX(GOOGLEFINANCE(""XLF"",""price"",M31),2,2))-1)"),0.13656064311234162) -> 0.13656064 | P31: =IFERROR(__xludf.DUMMYFUNCTION("N31 - ((GOOGLEFINANCE(""SPY"")/INDEX(GOOGLEFINANCE(""SPY"",""price"",M31),2,2))-1)"),0.11361419158320618) -> 0.11361419 | Q31: =IFERROR(__xludf.DUMMYFUNCTION("IFERROR(GOOGLEFINANCE(B31, ""beta""), ""N/A"")"),"N/A") -> N/A | S31: Buy at 1.25% | T31: 45958 | U31: 63.07 | V31: =IFERROR(F31/U31-1, "NA") -> -0.36118598
B32: XLF | C32: SPDR Financials ETF | E32: =IFERROR(__xludf.DUMMYFUNCTION("SPARKLINE(GOOGLEFINANCE(B32, ""price"", TODAY()-365, TODAY(), ""DAILY""))"),"") | F32: =IFERROR(__xludf.DUMMYFUNCTION("IFERROR(GOOGLEFINANCE(B32), 0)"),50.89) -> 50.89 | G32: 0 | H32: =F32*G32 -> 0 | I32: =H32/$H$121 -> 0 | J32: =I32 -> 0 | L32: 38.69 | M32: 45317 | N32: =(F32/L32-1) -> 0.31532696 | Q32: =IFERROR(__xludf.DUMMYFUNCTION("IFERROR(GOOGLEFINANCE(B32, ""beta""), ""N/A"")"),"N/A") -> N/A | S32: NA | T32: NA | U32: NA | V32: NA
A33: Sector Total | H33: =SUM(H26:H32) -> 304227.66 | I33: =H33/$H$121 -> 0.11412727 | J33: 0.115 | L33: =SUMPRODUCT(L26:L32*G26:G32) -> 241845.48 | M33: =AVERAGE(M26:M32) -> 45253.743 | N33: =H33/L33-1 -> 0.2579423 | Q33: =SUMPRODUCT(I26:I29/SUMIF(Q26:Q29, "<>N/A", I26:I29),Q26:Q29) -> 0.84745912
A35: Healthcare
B36: TMO | C36: Thermo Fisher Scientific Inc. | E36: =IFERROR(__xludf.DUMMYFUNCTION("SPARKLINE(GOOGLEFINANCE(B36, ""price"", TODAY()-365, TODAY(), ""DAILY""))"),"") | F36: =IFERROR(__xludf.DUMMYFUNCTION("IFERROR(GOOGLEFINANCE(B36), 0)"),509.54) -> 509.54 | G36: 84 | H36: =F36*G36 -> 42801.36 | I36: =H36/$H$121 -> 0.016056405 | J36: 0.015 | L36: 433 | M36: 43768 | N36: =(F36/L36-1) -> 0.17676674 | O36: =IFERROR(__xludf.DUMMYFUNCTION("N36 - ((GOOGLEFINANCE(""XLV"")/INDEX(GOOGLEFINANCE(""XLV"",""price"",M36),2,2))-1)"),-0.49084868962112127) -> -0.49084869 | P36: =IFERROR(__xludf.DUMMYFUNCTION("N36 - ((GOOGLEFINANCE(""SPY"")/INDEX(GOOGLEFINANCE(""SPY"",""price"",M36),2,2))-1)"),-1.0672984894673672) -> -1.0672985 | Q36: =IFERROR(__xludf.DUMMYFUNCTION("IFERROR(GOOGLEFINANCE(B36, ""beta""), ""N/A"")"),0.93) -> 0.93 | S36: Buy at 2% | T36: 45200 | U36: 306.96 | V36: =IFERROR(F36/U36-1, "NA") -> 0.65995569
B37: UNH | C37: UnitedHealth Group Inc | E37: =IFERROR(__xludf.DUMMYFUNCTION("SPARKLINE(GOOGLEFINANCE(B37, ""price"", TODAY()-365, TODAY(), ""DAILY""))"),"") | F37: =IFERROR(__xludf.DUMMYFUNCTION("IFERROR(GOOGLEFINANCE(B37), 0)"),287.76) -> 287.76 | G37: 224 | H37: =F37*G37 -> 64458.24 | I37: =H37/$H$121 -> 0.024180718 | J37: 0.015 | L37: 336.88797 | M37: 44313 | N37: =(F37/L37-1) -> -0.1458288 | O37: =IFERROR(__xludf.DUMMYFUNCTION("N37 - ((GOOGLEFINANCE(""XLV"")/INDEX(GOOGLEFINANCE(""XLV"",""price"",M37),2,2))-1)"),-0.43664887502079863) -> -0.43664887 | P37: =IFERROR(__xludf.DUMMYFUNCTION("N37 - ((GOOGLEFINANCE(""SPY"")/INDEX(GOOGLEFINANCE(""SPY"",""price"",M37),2,2))-1)"),-0.7805049847582402) -> -0.78050498 | Q37: =IFERROR(__xludf.DUMMYFUNCTION("IFERROR(GOOGLEFINANCE(B37, ""beta""), ""N/A"")"),0.41) -> 0.41 | S37: Raise to 3% | T37: 45930 | U37: 450.21 | V37: =IFERROR(F37/U37-1, "NA") -> -0.36083161
B38: VEEV | C38: Veeva Systems Inc. | E38: =IFERROR(__xludf.DUMMYFUNCTION("SPARKLINE(GOOGLEFINANCE(B38, ""price"", TODAY()-365, TODAY(), ""DAILY""))"),"") | F38: =IFERROR(__xludf.DUMMYFUNCTION("IFERROR(GOOGLEFINANCE(B38), 0)"),174.01) -> 174.01 | G38: 223 | H38: =F38*G38 -> 38804.23 | I38: =H38/$H$121 -> 0.014556931 | J38: 0.015 | L38: 181.05 | M38: 44991 | N38: =(F38/L38-1) -> -0.038884286 | O38: =IFERROR(__xludf.DUMMYFUNCTION("N38 - ((GOOGLEFINANCE(""XLV"")/INDEX(GOOGLEFINANCE(""XLV"",""price"",M38),2,2))-1)"),-0.26411858244526687) -> -0.26411858 | P38: =IFERROR(__xludf.DUMMYFUNCTION("N38 - ((GOOGLEFINANCE(""SPY"")/INDEX(GOOGLEFINANCE(""SPY"",""price"",M38),2,2))-1)"),-0.7263023888111114) -> -0.72630239 | Q38: =IFERROR(__xludf.DUMMYFUNCTION("IFERROR(GOOGLEFINANCE(B38, ""beta""), ""N/A"")"),1.08) -> 1.08 | S38: Buy at 1.5% | T38: 44985 | U38: 203.57 | V38: =IFERROR(F38/U38-1, "NA") -> -0.14520804
B39: RPRX | C39: Royalty Pharma plc | E39: =IFERROR(__xludf.DUMMYFUNCTION("SPARKLINE(GOOGLEFINANCE(B39, ""price"", TODAY()-365, TODAY(), ""DAILY""))"),"") | F39: =IFERROR(__xludf.DUMMYFUNCTION("IFERROR(GOOGLEFINANCE(B39), 0)"),45.23) -> 45.23 | G39: 1696 | H39: =F39*G39 -> 76710.08 | I39: =H39/$H$121 -> 0.028776845 | J39: 0.0136 | L39: 28.594829 | M39: 45401 | N39: =(F39/L39-1) -> 0.58175454 | O39: =IFERROR(__xludf.DUMMYFUNCTION("N39 - ((GOOGLEFINANCE(""XLV"")/INDEX(GOOGLEFINANCE(""XLV"",""price"",M39),2,2))-1)"),0.4432874702903298) -> 0.44328747 | P39: =IFERROR(__xludf.DUMMYFUNCTION("N39 - ((GOOGLEFINANCE(""SPY"")/INDEX(GOOGLEFINANCE(""SPY"",""price"",M39),2,2))-1)"),0.2033919952985992) -> 0.203392 | Q39: =IFERROR(__xludf.DUMMYFUNCTION("IFERROR(GOOGLEFINANCE(B39, ""beta""), ""N/A"")"),0.42) -> 0.42 | S39: Buy at 1.36% | T39: 45400 | U39: 40.76 | V39: =IFERROR(F39/U39-1, "NA") -> 0.10966634
B40: MRK | C40: Merck & Co Inc | E40: =IFERROR(__xludf.DUMMYFUNCTION("SPARKLINE(GOOGLEFINANCE(B40, ""price"", TODAY()-365, TODAY(), ""DAILY""))"),"") | F40: =IFERROR(__xludf.DUMMYFUNCTION("IFERROR(GOOGLEFINANCE(B40), 0)"),123.15) -> 123.15 | G40: 332 | H40: =F40*G40 -> 40885.8 | I40: =H40/$H$121 -> 0.015337806 | J40: 0.01 | L40: 83.581 | M40: 45964 | N40: =(F40/L40-1) -> 0.47342099 | O40: =IFERROR(__xludf.DUMMYFUNCTION("N40 - ((GOOGLEFINANCE(""XLV"")/INDEX(GOOGLEFINANCE(""XLV"",""price"",M40),2,2))-1)"),0.3783015743254661) -> 0.37830157 | P40: =IFERROR(__xludf.DUMMYFUNCTION("N40 - ((GOOGLEFINANCE(""SPY"")/INDEX(GOOGLEFINANCE(""SPY"",""price"",M40),2,2))-1)"),0.4746356151057386) -> 0.47463562 | Q40: =IFERROR(__xludf.DUMMYFUNCTION("IFERROR(GOOGLEFINANCE(B40, ""beta""), ""N/A"")"),0.28) -> 0.28 | S40: Buy at 1.00% | T40: 45958 | U40: 109.66 | V40: =IFERROR(F40/U40-1, "NA") -> 0.1230166
B41: XLV | C41: SPDR Healthcare ETF | E41: =IFERROR(__xludf.DUMMYFUNCTION("SPARKLINE(GOOGLEFINANCE(B41, ""price"", TODAY()-365, TODAY(), ""DAILY""))"),"") | F41: =IFERROR(__xludf.DUMMYFUNCTION("IFERROR(GOOGLEFINANCE(B41), 0)"),158.19) -> 158.19 | G41: 0 | H41: =F41*G41 -> 0 | I41: =H41/$H$121 -> 0 | J41: =I41 -> 0 | L41: 139.31 | M41: 45317 | N41: =(F41/L41-1) -> 0.13552509 | Q41: =IFERROR(__xludf.DUMMYFUNCTION("IFERROR(GOOGLEFINANCE(B41, ""beta""), ""N/A"")"),"N/A") -> N/A | S41: NA | T41: NA | U41: NA | V41: =IFERROR(F41/U41-1, "NA") -> NA
A42: Sector Total | H42: =SUM(H36:H41) -> 263659.71 | I42: =H42/$H$121 -> 0.098908705 | J42: 0.1 | L42: =SUMPRODUCT(L36:L41*G36:G41) -> 228454.78 | M42: =AVERAGE(M36:M41) -> 44959 | N42: =H42/L42-1 -> 0.15410023 | Q42: =SUMPRODUCT(I36:I41/SUMIF(Q36:Q41, "<>N/A", I36:I41),Q36:Q41) -> 0.57577234
A44: Industrials
B45: APD | C45: Air Products & Chemicals, Inc. | E45: =IFERROR(__xludf.DUMMYFUNCTION("SPARKLINE(GOOGLEFINANCE(B45, ""price"", TODAY()-365, TODAY(), ""DAILY""))"),"") | F45: =IFERROR(__xludf.DUMMYFUNCTION("IFERROR(GOOGLEFINANCE(B45), 0)"),281.66) -> 281.66 | G45: 106 | H45: =F45*G45 -> 29855.96 | I45: =H45/$H$121 -> 0.011200097 | J45: 0.015 | L45: 233.63859 | M45: 44627 | N45: =(F45/L45-1) -> 0.20553714 | O45: =IFERROR(__xludf.DUMMYFUNCTION("N45 - ((GOOGLEFINANCE(""XLI"")/INDEX(GOOGLEFINANCE(""XLI"",""price"",M45),2,2))-1)"),-0.5868886508904183) -> -0.58688865 | P45: =IFERROR(__xludf.DUMMYFUNCTION("N45 - ((GOOGLEFINANCE(""SPY"")/INDEX(GOOGLEFINANCE(""SPY"",""price"",M45),2,2))-1)"),-0.42169505372141836) -> -0.42169505 | Q45: =IFERROR(__xludf.DUMMYFUNCTION("IFERROR(GOOGLEFINANCE(B45, ""beta""), ""N/A"")"),0.87) -> 0.87 | S45: Trim to 1.5% | T45: 45729 | U45: 294.455 | V45: =IFERROR(F45/U45-1, "NA") -> -0.043453159
B46: GE | C46: General Electric Co | E46: =IFERROR(__xludf.DUMMYFUNCTION("SPARKLINE(GOOGLEFINANCE(B46, ""price"", TODAY()-365, TODAY(), ""DAILY""))"),"") | F46: =IFERROR(__xludf.DUMMYFUNCTION("IFERROR(GOOGLEFINANCE(B46), 0)"),339.52) -> 339.52 | G46: 285 | H46: =F46*G46 -> 96763.2 | I46: =H46/$H$121 -> 0.036299527 | J46: 0.0084 | L46: 154.51156 | M46: 45372 | N46: =(F46/L46-1) -> 1.1973761 | O46: =IFERROR(__xludf.DUMMYFUNCTION("N46 - ((GOOGLEFINANCE(""XLI"")/INDEX(GOOGLEFINANCE(""XLI"",""price"",M46),2,2))-1)"),0.8035524867628887) -> 0.80355249 | P46: =IFERROR(__xludf.DUMMYFUNCTION("N46 - ((GOOGLEFINANCE(""SPY"")/INDEX(GOOGLEFINANCE(""SPY"",""price"",M46),2,2))-1)"),0.8903864506784416) -> 0.89038645 | Q46: =IFERROR(__xludf.DUMMYFUNCTION("IFERROR(GOOGLEFINANCE(B46, ""beta""), ""N/A"")"),1.41) -> 1.41 | S46: Buy at 1% | T46: 45923 | U46: 183.64 | V46: =IFERROR(F46/U46-1, "NA") -> 0.84883468
B47: AMRZ | C47: Amrize | E47: =IFERROR(__xludf.DUMMYFUNCTION("SPARKLINE(GOOGLEFINANCE(B47, ""price"", TODAY()-365, TODAY(), ""DAILY""))"),"") | F47: =IFERROR(__xludf.DUMMYFUNCTION("IFERROR(GOOGLEFINANCE(B47), 0)"),63.79) -> 63.79 | G47: 921 | H47: =F47*G47 -> 58750.59 | I47: =H47/$H$121 -> 0.022039563 | J47: 0.0084 | L47: 48.7 | M47: 45950 | N47: =(F47/L47-1) -> 0.30985626 | O47: =IFERROR(__xludf.DUMMYFUNCTION("N47 - ((GOOGLEFINANCE(""XLI"")/INDEX(GOOGLEFINANCE(""XLI"",""price"",M47),2,2))-1)"),0.16915798247932412) -> 0.16915798 | P47: =IFERROR(__xludf.DUMMYFUNCTION("N47 - ((GOOGLEFINANCE(""SPY"")/INDEX(GOOGLEFINANCE(""SPY"",""price"",M47),2,2))-1)"),0.29315732048301246) -> 0.29315732 | Q47: =IFERROR(__xludf.DUMMYFUNCTION("IFERROR(GOOGLEFINANCE(B47, ""beta""), ""N/A"")"),"N/A") -> N/A | S47: Buy at 1.5% | T47: 45944 | U47: 65 | V47: =IFERROR(F47/U47-1, "NA") -> -0.018615385
B48: FLS | C48: Flowserve | E48: =IFERROR(__xludf.DUMMYFUNCTION("SPARKLINE(GOOGLEFINANCE(B48, ""price"", TODAY()-365, TODAY(), ""DAILY""))"),"") | F48: =IFERROR(__xludf.DUMMYFUNCTION("IFERROR(GOOGLEFINANCE(B48), 0)"),88.07) -> 88.07 | G48: 295 | H48: =F48*G48 -> 25980.65 | I48: =H48/$H$121 -> 0.0097463221 | J48: 0.01 | L48: 89.47 | M48: 46070 | N48: =(F48/L48-1) -> -0.015647703 | O48: =IFERROR(__xludf.DUMMYFUNCTION("N48 - ((GOOGLEFINANCE(""XLI"")/INDEX(GOOGLEFINANCE(""XLI"",""price"",M48),2,2))-1)"),-0.015876170127238076) -> -0.01587617 | P48: =IFERROR(__xludf.DUMMYFUNCTION("N48 - ((GOOGLEFINANCE(""SPY"")/INDEX(GOOGLEFINANCE(""SPY"",""price"",M48),2,2))-1)"),-0.015149789982630169) -> -0.01514979 | Q48: =IFERROR(__xludf.DUMMYFUNCTION("IFERROR(GOOGLEFINANCE(B48, ""beta""), ""N/A"")"),1.29) -> 1.29 | S48: Buy at 1% | T48: 46070 | U48: 108.55 | V48: =IFERROR(F48/U48-1, "NA") -> -0.18866882
B49: XLI | C49: SPDR Industrials ETF | E49: =IFERROR(__xludf.DUMMYFUNCTION("SPARKLINE(GOOGLEFINANCE(B49, ""price"", TODAY()-365, TODAY(), ""DAILY""))"),"") | F49: =IFERROR(__xludf.DUMMYFUNCTION("IFERROR(GOOGLEFINANCE(B49), 0)"),175.12) -> 175.12 | G49: 0 | H49: =F49*G49 -> 0 | I49: =H49/$H$121 -> 0 | J49: =I49 -> 0 | L49: 105.76 | N49: =(F49/L49-1) -> 0.65582451 | Q49: =IFERROR(__xludf.DUMMYFUNCTION("IFERROR(GOOGLEFINANCE(B49, ""beta""), ""N/A"")"),"N/A") -> N/A | S49: NA | T49: NA | U49: NA | V49: =IFERROR(F49/U49-1, "NA") -> NA
A50: Sector Total | H50: =SUM(H45:H49) -> 211350.4 | I50: =H50/$H$121 -> 0.079285509 | J50: 0.075 | L50: =SUMPRODUCT(L45:L49*G45:G49) -> 140047.83 | M50: =AVERAGE(M45:M49) -> 45504.75 | N50: =H50/L50-1 -> 0.50913009 | Q50: =SUMPRODUCT(I45:I49/SUMIF(Q45:Q49, "<>N/A", I45:I49),Q45:Q49) -> 1.2839193
A52: REITs
B53: PLD | C53: Prologis Inc. | E53: =IFERROR(__xludf.DUMMYFUNCTION("SPARKLINE(GOOGLEFINANCE(B53, ""price"", TODAY()-365, TODAY(), ""DAILY""))"),"") | F53: =IFERROR(__xludf.DUMMYFUNCTION("IFERROR(GOOGLEFINANCE(B53), 0)"),141.1) -> 141.1 | G53: 213 | H53: =F53*G53 -> 30054.3 | I53: =H53/$H$121 -> 0.011274502 | J53: 0.015 | L53: 74.89 | M53: 43903 | N53: =(F53/L53-1) -> 0.88409668 | O53: =IFERROR(__xludf.DUMMYFUNCTION("N53 - ((GOOGLEFINANCE(""XLRE"")/INDEX(GOOGLEFINANCE(""XLRe"",""price"",M53),2,2))-1)"),0.6470533446222402) -> 0.64705334 | P53: =IFERROR(__xludf.DUMMYFUNCTION("N53 - ((GOOGLEFINANCE(""SPY"")/INDEX(GOOGLEFINANCE(""SPY"",""price"",M53),2,2))-1)"),-0.6501005623634901) -> -0.65010056 | Q53: =IFERROR(__xludf.DUMMYFUNCTION("IFERROR(GOOGLEFINANCE(B53, ""beta""), ""N/A"")"),1.41) -> 1.41 | S53: Hold | T53: 45566 | U53: 132.99 | V53: =IFERROR(F53/U53-1, "NA") -> 0.060982029
B54: ADC | C54: Agree Realty Corporation | E54: =IFERROR(__xludf.DUMMYFUNCTION("SPARKLINE(GOOGLEFINANCE(B54, ""price"", TODAY()-365, TODAY(), ""DAILY""))"),"") | F54: =IFERROR(__xludf.DUMMYFUNCTION("IFERROR(GOOGLEFINANCE(B54), 0)"),79.23) -> 79.23 | G54: 161 | H54: =F54*G54 -> 12756.03 | I54: =H54/$H$121 -> 0.0047852681 | J54: 0.0061 | L54: 62.8 | M54: 44631 | N54: =(F54/L54-1) -> 0.2616242 | O54: =IFERROR(__xludf.DUMMYFUNCTION("N54 - ((GOOGLEFINANCE(""XLRE"")/INDEX(GOOGLEFINANCE(""XLRe"",""price"",M54),2,2))-1)"),0.30936782710484767) -> 0.30936783 | P54: =IFERROR(__xludf.DUMMYFUNCTION("N54 - ((GOOGLEFINANCE(""SPY"")/INDEX(GOOGLEFINANCE(""SPY"",""price"",M54),2,2))-1)"),-0.3631288135325945) -> -0.36312881 | Q54: =IFERROR(__xludf.DUMMYFUNCTION("IFERROR(GOOGLEFINANCE(B54, ""beta""), ""N/A"")"),0.54) -> 0.54 | S54: Hold | T54: 45729 | U54: 87.36 | V54: =IFERROR(F54/U54-1, "NA") -> -0.093063187
B55: XLRE | C55: SPDR REITs ETF | E55: =IFERROR(__xludf.DUMMYFUNCTION("SPARKLINE(GOOGLEFINANCE(B55, ""price"", TODAY()-365, TODAY(), ""DAILY""))"),"") | F55: =IFERROR(__xludf.DUMMYFUNCTION("IFERROR(GOOGLEFINANCE(B55), 0)"),43.68) -> 43.68 | H55: =F55*G55 -> 0 | I55: =H55/$H$121 -> 0 | J55: =I55 -> 0 | L55: 33.97 | M55: 45198 | N55: =(F55/L55-1) -> 0.28584045 | Q55: =IFERROR(__xludf.DUMMYFUNCTION("IFERROR(GOOGLEFINANCE(B55, ""beta""), ""N/A"")"),"N/A") -> N/A | S55: NA | T55: NA | U55: NA | V55: NA
A56: Sector Total | H56: =SUM(H53:H55) -> 42810.33 | I56: =H56/$H$121 -> 0.01605977 | J56: 0.015 | L56: =SUMPRODUCT(L53:L55,G53:G55) -> 26062.37 | M56: =AVERAGE(M53:M54) -> 44267 | N56: =H56/L56-1 -> 0.64261078 | Q56: =SUMPRODUCT(I53:I54/SUMIF(Q53:Q54, "<>N/A", I53:I54),Q53:Q54) -> 1.1507694
A58: Technology
B59: GOOGL | C59: Alphabet Inc | E59: =IFERROR(__xludf.DUMMYFUNCTION("SPARKLINE(GOOGLEFINANCE(B59, ""price"", TODAY()-365, TODAY(), ""DAILY""))"),"") | F59: =IFERROR(__xludf.DUMMYFUNCTION("IFERROR(GOOGLEFINANCE(B59), 0)"),314.7) -> 314.7 | G59: 380 | H59: =F59*G59 -> 119586 | I59: =H59/$H$121 -> 0.044861221 | J59: 0.0391 | L59: 58.937184 | M59: 40284 | N59: =(F59/L59-1) -> 4.3395833 | O59: =IFERROR(__xludf.DUMMYFUNCTION("N59 - ((GOOGLEFINANCE(""SPY"")/INDEX(GOOGLEFINANCE(""SPY"",""price"",M59),2,2))-1)"),-0.37849649989154344) -> -0.3784965 | P59: =IFERROR(__xludf.DUMMYFUNCTION("N59 - ((GOOGLEFINANCE(""SPY"")/INDEX(GOOGLEFINANCE(""SPY"",""price"",M59),2,2))-1)"),-0.37849649989154344) -> -0.3784965 | Q59: =IFERROR(__xludf.DUMMYFUNCTION("IFERROR(GOOGLEFINANCE(B59, ""beta""), ""N/A"")"),1.09) -> 1.09 | S59: Hold | T59: 44117 | U59: 88.65 | V59: =IFERROR(F59/U59-1, "NA") -> 2.5499154
B60: MSFT | C60: Microsoft | E60: =IFERROR(__xludf.DUMMYFUNCTION("SPARKLINE(GOOGLEFINANCE(B60, ""price"", TODAY()-365, TODAY(), ""DAILY""))"),"") | F60: =IFERROR(__xludf.DUMMYFUNCTION("IFERROR(GOOGLEFINANCE(B60), 0)"),386.77) -> 386.77 | G60: 241 | H60: =F60*G60 -> 93211.57 | I60: =H60/$H$121 -> 0.034967177 | J60: 0.0362 | L60: 194.85233 | M60: 43750.916 | N60: =(F60/L60-1) -> 0.98493909 | O60: =IFERROR(__xludf.DUMMYFUNCTION("N60 - ((GOOGLEFINANCE(""XLK"")/INDEX(GOOGLEFINANCE(""XLK"",""price"",M60),2,2))-1)"),-1.431400457078755) -> -1.4314005 | P60: =IFERROR(__xludf.DUMMYFUNCTION("N60 - ((GOOGLEFINANCE(""SPY"")/INDEX(GOOGLEFINANCE(""SPY"",""price"",M60),2,2))-1)"),-0.3212274906946566) -> -0.32122749 | Q60: =IFERROR(__xludf.DUMMYFUNCTION("IFERROR(GOOGLEFINANCE(B60, ""beta""), ""N/A"")"),1.08) -> 1.08 | S60: Hold | T60: 44236 | U60: NA | V60: =IFERROR(F60/U60-1, "NA") -> NA
B61: AMAT | C61: Applied Materials, Inc. | E61: =IFERROR(__xludf.DUMMYFUNCTION("SPARKLINE(GOOGLEFINANCE(B61, ""price"", TODAY()-365, TODAY(), ""DAILY""))"),"") | F61: =IFERROR(__xludf.DUMMYFUNCTION("IFERROR(GOOGLEFINANCE(B61), 0)"),373.74) -> 373.74 | G61: 297 | H61: =F61*G61 -> 111000.78 | I61: =H61/$H$121 -> 0.041640581 | J61: 0.018 | L61: 154.05024 | M61: 44740.958 | N61: =(F61/L61-1) -> 1.4260916 | O61: =IFERROR(__xludf.DUMMYFUNCTION("N61 - ((GOOGLEFINANCE(""XLK"")/INDEX(GOOGLEFINANCE(""XLK"",""price"",M61),2,2))-1)"),0.260124892360011) -> 0.26012489 | P61: =IFERROR(__xludf.DUMMYFUNCTION("N61 - ((GOOGLEFINANCE(""SPY"")/INDEX(GOOGLEFINANCE(""SPY"",""price"",M61),2,2))-1)"),0.6330796524523503) -> 0.63307965 | Q61: =IFERROR(__xludf.DUMMYFUNCTION("IFERROR(GOOGLEFINANCE(B61, ""beta""), ""N/A"")"),1.7) -> 1.7 | S61: Hold | T61: 45720 | U61: 179.24 | V61: =IFERROR(F61/U61-1, "NA") -> 1.0851372
B62: SNPS | C62: Synopsys Inc. | E62: =IFERROR(__xludf.DUMMYFUNCTION("SPARKLINE(GOOGLEFINANCE(B62, ""price"", TODAY()-365, TODAY(), ""DAILY""))"),"") | F62: =IFERROR(__xludf.DUMMYFUNCTION("IFERROR(GOOGLEFINANCE(B62), 0)"),419.98) -> 419.98 | G62: 184 | H62: =F62*G62 -> 77276.32 | I62: =H62/$H$121 -> 0.028989263 | J62: 0.0197 | L62: 403.0632 | M62: 44970.655 | N62: =(F62/L62-1) -> 0.041970598 | O62: =IFERROR(__xludf.DUMMYFUNCTION("N62 - ((GOOGLEFINANCE(""XLK"")/INDEX(GOOGLEFINANCE(""XLK"",""price"",M62),2,2))-1)"),-0.9080364041169442) -> -0.9080364 | P62: =IFERROR(__xludf.DUMMYFUNCTION("N62 - ((GOOGLEFINANCE(""SPY"")/INDEX(GOOGLEFINANCE(""SPY"",""price"",M62),2,2))-1)"),-0.6112765015867356) -> -0.6112765 | Q62: =IFERROR(__xludf.DUMMYFUNCTION("IFERROR(GOOGLEFINANCE(B62, ""beta""), ""N/A"")"),1.12) -> 1.12 | S62: Hold | T62: 45575 | U62: 571.27 | V62: =IFERROR(F62/U62-1, "NA") -> -0.26483099
B63: CNSWF | C63: Constellation Software | E63: =IFERROR(__xludf.DUMMYFUNCTION("SPARKLINE(GOOGLEFINANCE(B63, ""price"", TODAY()-365, TODAY(), ""DAILY""))"),"") | F63: =IFERROR(__xludf.DUMMYFUNCTION("IFERROR(GOOGLEFINANCE(B63), 0)"),1774.93) -> 1774.93 | G63: 26 | H63: =F63*G63 -> 46148.18 | I63: =H63/$H$121 -> 0.017311923 | J63: 0.0332 | L63: 2004.06 | M63: 45072 | N63: =(F63/L63-1) -> -0.1143329 | O63: =IFERROR(__xludf.DUMMYFUNCTION("N63 - ((GOOGLEFINANCE(""XLK"")/INDEX(GOOGLEFINANCE(""XLK"",""price"",M63),2,2))-1)"),-0.8044652018133979) -> -0.8044652 | P63: =IFERROR(__xludf.DUMMYFUNCTION("N63 - ((GOOGLEFINANCE(""SPY"")/INDEX(GOOGLEFINANCE(""SPY"",""price"",M63),2,2))-1)"),-0.7392793353267925) -> -0.73927934 | Q63: =IFERROR(__xludf.DUMMYFUNCTION("IFERROR(GOOGLEFINANCE(B63, ""beta""), ""N/A"")"),1.04) -> 1.04 | S63: Buy at 1.5% | T63: 44985 | U63: 2106 | V63: =IFERROR(F63/U63-1, "NA") -> -0.15720323
B64: TSM | C64: Taiwan Semiconductor | E64: =IFERROR(__xludf.DUMMYFUNCTION("SPARKLINE(GOOGLEFINANCE(B64, ""price"", TODAY()-365, TODAY(), ""DAILY""))"),"") | F64: =IFERROR(__xludf.DUMMYFUNCTION("IFERROR(GOOGLEFINANCE(B64), 0)"),368.54) -> 368.54 | G64: 303 | H64: =F64*G64 -> 111667.62 | I64: =H64/$H$121 -> 0.041890737 | J64: 0.022 | L64: 275.55 | M64: 45929 | N64: =(F64/L64-1) -> 0.33747051 | O64: =IFERROR(__xludf.DUMMYFUNCTION("N64 - ((GOOGLEFINANCE(""XLK"")/INDEX(GOOGLEFINANCE(""XLK"",""price"",M64),2,2))-1)"),0.34403397217576226) -> 0.34403397 | P64: =IFERROR(__xludf.DUMMYFUNCTION("N64 - ((GOOGLEFINANCE(""SPY"")/INDEX(GOOGLEFINANCE(""SPY"",""price"",M64),2,2))-1)"),0.3090984064788804) -> 0.30909841 | Q64: =IFERROR(__xludf.DUMMYFUNCTION("IFERROR(GOOGLEFINANCE(B64, ""beta""), ""N/A"")"),1.29) -> 1.29 | S64: Buy at 2.2% | T64: 45923 | U64: 297.17 | V64: =IFERROR(F64/U64-1, "NA") -> 0.24016556
B65: XLK | C65: SPDR Technology ETF | E65: =IFERROR(__xludf.DUMMYFUNCTION("SPARKLINE(GOOGLEFINANCE(B65, ""price"", TODAY()-365, TODAY(), ""DAILY""))"),"") | F65: =IFERROR(__xludf.DUMMYFUNCTION("IFERROR(GOOGLEFINANCE(B65), 0)"),139.25) -> 139.25 | G65: 0 | H65: =F65*G65 -> 0 | I65: =H65/$H$121 -> 0 | J65: =I65 -> 0 | L65: 208.79 | M65: 45554 | N65: =(F65/L65-1) -> -0.33306193 | Q65: =IFERROR(__xludf.DUMMYFUNCTION("IFERROR(GOOGLEFINANCE(B65, ""beta""), ""N/A"")"),"N/A") -> N/A | S65: NA | T65: NA | U65: NA | V65: =IFERROR(F65/U65-1, "NA") -> NA
A66: Sector Total | H66: =SUM(H59:H65) -> 558890.47 | I66: =H66/$H$121 -> 0.2096609 | J66: 0.215 | L66: =SUMPRODUCT(L59:L65,G59:G65) -> 324869.3 | M66: =AVERAGE(M59:M65) -> 44328.79 | N66: =H66/L66-1 -> 0.72035483 | Q66: =SUMPRODUCT(I59:I63/SUMIF(Q59:Q63, "<>N/A", I59:I63),Q59:Q63) -> 1.2393422
A68: Media & Telecom
B69: META | C69: Meta Platforms, Inc. | E69: =IFERROR(__xludf.DUMMYFUNCTION("SPARKLINE(GOOGLEFINANCE(B69, ""price"", TODAY()-365, TODAY(), ""DAILY""))"),"") | F69: =IFERROR(__xludf.DUMMYFUNCTION("IFERROR(GOOGLEFINANCE(B69), 0)"),645.4) -> 645.4 | G69: 153 | H69: =F69*G69 -> 98746.2 | I69: =H69/$H$121 -> 0.037043425 | J69: 0.015 | L69: 243.75 | M69: 44655 | N69: =(F69/L69-1) -> 1.6477949 | O69: =IFERROR(__xludf.DUMMYFUNCTION("N69 - ((GOOGLEFINANCE(""XLC"")/INDEX(GOOGLEFINANCE(""XLC"",""price"",M69),2,2))-1)"),1.0177386920195908) -> 1.0177387 | P69: =IFERROR(__xludf.DUMMYFUNCTION("N69 - ((GOOGLEFINANCE(""SPY"")/INDEX(GOOGLEFINANCE(""SPY"",""price"",M69),2,2))-1)"),1.153683663388567) -> 1.1536837 | Q69: =IFERROR(__xludf.DUMMYFUNCTION("IFERROR(GOOGLEFINANCE(B69, ""beta""), ""N/A"")"),1.28) -> 1.28 | S69: Hold | T69: 45720 | U69: 816.71 | V69: =IFERROR(F69/U69-1, "NA") -> -0.20975622
B70: LYV | C70: Live Nation Entertainment Inc | E70: =IFERROR(__xludf.DUMMYFUNCTION("SPARKLINE(GOOGLEFINANCE(B70, ""price"", TODAY()-365, TODAY(), ""DAILY""))"),"") | F70: =IFERROR(__xludf.DUMMYFUNCTION("IFERROR(GOOGLEFINANCE(B70), 0)"),163.36) -> 163.36 | G70: 396 | H70: =F70*G70 -> 64690.56 | I70: =H70/$H$121 -> 0.02426787 | J70: 0.0095 | L70: 84.38 | M70: 45261 | N70: =(F70/L70-1) -> 0.93600379 | O70: =IFERROR(__xludf.DUMMYFUNCTION("N70 - ((GOOGLEFINANCE(""XLC"")/INDEX(GOOGLEFINANCE(""XLC"",""price"",M70),2,2))-1)"),0.2758693337782445) -> 0.27586933 | P70: =IFERROR(__xludf.DUMMYFUNCTION("N70 - ((GOOGLEFINANCE(""SPY"")/INDEX(GOOGLEFINANCE(""SPY"",""price"",M70),2,2))-1)"),0.44937778496206615) -> 0.44937778 | Q70: =IFERROR(__xludf.DUMMYFUNCTION("IFERROR(GOOGLEFINANCE(B70, ""beta""), ""N/A"")"),1.18) -> 1.18 | S70: Buy at 0.95% | T70: 45261 | U70: 123.99 | V70: =IFERROR(F70/U70-1, "NA") -> 0.31752561
B71: XLC | C71: SPDR Communications Services ETF | E71: =IFERROR(__xludf.DUMMYFUNCTION("SPARKLINE(GOOGLEFINANCE(B71, ""price"", TODAY()-365, TODAY(), ""DAILY""))"),"") | F71: =IFERROR(__xludf.DUMMYFUNCTION("IFERROR(GOOGLEFINANCE(B71), 0)"),116.06) -> 116.06 | G71: 0 | H71: =F71*G71 -> 0 | I71: =H71/$H$121 -> 0 | J71: =I71 -> 0 | L71: 68.9 | M71: 45191 | N71: =(F71/L71-1) -> 0.68447025 | Q71: =IFERROR(__xludf.DUMMYFUNCTION("IFERROR(GOOGLEFINANCE(B71, ""beta""), ""N/A"")"),"N/A") -> N/A | S71: NA | T71: NA | U71: NA | V71: =IFERROR(F71/U71-1, "NA") -> NA
A72: Sector Total | H72: =SUM(H69:H71) -> 163436.76 | I72: =H72/$H$121 -> 0.061311295 | J72: 0.06 | L72: =SUMPRODUCT(L69:L71, G69:G71) -> 70708.23 | M72: =AVERAGE(M69:M71) -> 45035.667 | N72: =H72/L72-1 -> 1.3114249 | Q72: =SUMPRODUCT(I69:I70/SUMIF(Q69:Q70, "<>N/A", I69:I70),Q69:Q70) -> 1.2404186
A74: Utilities
B75: NEE | C75: NextEra Energy Inc | E75: =IFERROR(__xludf.DUMMYFUNCTION("SPARKLINE(GOOGLEFINANCE(B75, ""price"", TODAY()-365, TODAY(), ""DAILY""))"),"") | F75: =IFERROR(__xludf.DUMMYFUNCTION("IFERROR(GOOGLEFINANCE(B75), 0)"),93.55) -> 93.55 | G75: 156 | H75: =F75*G75 -> 14593.8 | I75: =H75/$H$121 -> 0.005474685 | J75: 0.015 | L75: 44.96 | M75: 43199 | N75: =(F75/L75-1) -> 1.0807384 | O75: =IFERROR(__xludf.DUMMYFUNCTION("N75 - ((GOOGLEFINANCE(""XLU"")/INDEX(GOOGLEFINANCE(""XLU"",""price"",M75),2,2))-1)"),0.2347368506324261) -> 0.23473685 | P75: =IFERROR(__xludf.DUMMYFUNCTION("N75 - ((GOOGLEFINANCE(""SPY"")/INDEX(GOOGLEFINANCE(""SPY"",""price"",M75),2,2))-1)"),-0.5342424087481765) -> -0.53424241 | Q75: =IFERROR(__xludf.DUMMYFUNCTION("IFERROR(GOOGLEFINANCE(B75, ""beta""), ""N/A"")"),0.76) -> 0.76 | S75: Hold | T75: 45923 | U75: 89.11 | V75: =IFERROR(F75/U75-1, "NA") -> 0.049826058
B76: CEG | C76: Constellation Energy Corp | E76: =IFERROR(__xludf.DUMMYFUNCTION("SPARKLINE(GOOGLEFINANCE(B76, ""price"", TODAY()-365, TODAY(), ""DAILY""))"),"") | F76: =IFERROR(__xludf.DUMMYFUNCTION("IFERROR(GOOGLEFINANCE(B76), 0)"),296.07) -> 296.07 | G76: 86 | H76: =F76*G76 -> 25462.02 | I76: =H76/$H$121 -> 0.0095517644 | J76: 0.015 | L76: 88.69 | M76: 44852 | N76: =(F76/L76-1) -> 2.3382569 | O76: =IFERROR(__xludf.DUMMYFUNCTION("N76 - ((GOOGLEFINANCE(""XLU"")/INDEX(GOOGLEFINANCE(""XLU"",""price"",M76),2,2))-1)"),1.8950504120657996) -> 1.8950504 | P76: =IFERROR(__xludf.DUMMYFUNCTION("N76 - ((GOOGLEFINANCE(""SPY"")/INDEX(GOOGLEFINANCE(""SPY"",""price"",M76),2,2))-1)"),1.499251649367092) -> 1.4992516 | Q76: =IFERROR(__xludf.DUMMYFUNCTION("IFERROR(GOOGLEFINANCE(B76, ""beta""), ""N/A"")"),1.13) -> 1.13 | S76: Hold | T76: 45748 | U76: 273.05 | V76: =IFERROR(F76/U76-1, "NA") -> 0.084306904
B77: VST | C77: Vistra Corp | E77: =IFERROR(__xludf.DUMMYFUNCTION("SPARKLINE(GOOGLEFINANCE(B77, ""price"", TODAY()-365, TODAY(), ""DAILY""))"),"") | F77: =IFERROR(__xludf.DUMMYFUNCTION("IFERROR(GOOGLEFINANCE(B77), 0)"),168.73) -> 168.73 | G77: 194 | H77: =F77*G77 -> 32733.62 | I77: =H77/$H$121 -> 0.012279616 | J77: 0.0066 | L77: 35.94 | M77: 45247 | N77: =(F77/L77-1) -> 3.6947691 | O77: =IFERROR(__xludf.DUMMYFUNCTION("N77 - ((GOOGLEFINANCE(""XLU"")/INDEX(GOOGLEFINANCE(""XLU"",""price"",M77),2,2))-1)"),3.197818818773218) -> 3.1978188 | P77: =IFERROR(__xludf.DUMMYFUNCTION("N77 - ((GOOGLEFINANCE(""SPY"")/INDEX(GOOGLEFINANCE(""SPY"",""price"",M77),2,2))-1)"),3.1807381360538107) -> 3.1807381 | Q77: =IFERROR(__xludf.DUMMYFUNCTION("IFERROR(GOOGLEFINANCE(B77, ""beta""), ""N/A"")"),1.41) -> 1.41 | S77: Hold | T77: 45960 | U77: 143.54 | V77: =IFERROR(F77/U77-1, "NA") -> 0.17549115
B78: XLU | C78: SPDR Utilities ETF | E78: =IFERROR(__xludf.DUMMYFUNCTION("SPARKLINE(GOOGLEFINANCE(B78, ""price"", TODAY()-365, TODAY(), ""DAILY""))"),"") | F78: =IFERROR(__xludf.DUMMYFUNCTION("IFERROR(GOOGLEFINANCE(B78), 0)"),46.63) -> 46.63 | G78: 0 | H78: =F78*G78 -> 0 | I78: =H78/$H$121 -> 0 | J78: =I78 -> 0 | L78: 68.08 | M78: 45191 | N78: =(F78/L78-1) -> -0.31507051 | Q78: =IFERROR(__xludf.DUMMYFUNCTION("IFERROR(GOOGLEFINANCE(B78, ""beta""), ""N/A"")"),"N/A") -> N/A | S78: NA | T78: NA | U78: NA | V78: =IFERROR(F78/U78-1, "NA") -> NA
A79: Sector Total | H79: =SUM(H75:H78) -> 72789.44 | I79: =H79/$H$121 -> 0.027306065 | J79: 0.025 | L79: =SUMPRODUCT(L75:L78*G75:G78) -> 21613.46 | M79: =AVERAGE(M75:M78) -> 44622.25 | N79: =H79/L79-1 -> 2.3677829 | Q79: =SUMPRODUCT(I75:I76/SUMIF(Q75:Q76, "<>N/A", I75:I76),Q75:Q76) -> 0.99519547
A81: Quant
B82: VC2 Strategy
B83: ADM | C83: =IFERROR(__xludf.DUMMYFUNCTION("GOOGLEFINANCE(B83, ""Name"")"),"Archer-Daniels-Midland Co") -> Archer-Daniels-Midland Co | E83: =IFERROR(__xludf.DUMMYFUNCTION("SPARKLINE(GOOGLEFINANCE(B83, ""price"", TODAY()-365, TODAY(), ""DAILY""))"),"") | F83: =IFERROR(__xludf.DUMMYFUNCTION("IFERROR(GOOGLEFINANCE(B83), 0)"),67.98) -> 67.98 | G83: 59 | H83: =F83*G83 -> 4010.82 | I83: =H83/$H$121 -> 0.0015046099 | J83: 0.002 | L83: 64.96 | M83: 45693 | N83: =(F83/L83-1) -> 0.046490148 | O83: =IFERROR(__xludf.DUMMYFUNCTION("N83 - ((GOOGLEFINANCE(""SPY"")/INDEX(GOOGLEFINANCE(""SPY"",""price"",M83),2,2))-1)"),-0.08308186241171067) -> -0.083081862 | Q83: =IFERROR(__xludf.DUMMYFUNCTION("IFERROR(GOOGLEFINANCE(B83, ""beta""), ""N/A"")"),0.71) -> 0.71 | S83: Buy at 0.20% | T83: 45691
B84: PFG | C84: =IFERROR(__xludf.DUMMYFUNCTION("GOOGLEFINANCE(B84, ""Name"")"),"Principal Financial Group Inc") -> Principal Financial Group Inc | E84: =IFERROR(__xludf.DUMMYFUNCTION("SPARKLINE(GOOGLEFINANCE(B84, ""price"", TODAY()-365, TODAY(), ""DAILY""))"),"") | F84: =IFERROR(__xludf.DUMMYFUNCTION("IFERROR(GOOGLEFINANCE(B84), 0)"),93.27) -> 93.27 | G84: 41 | H84: =F84*G84 -> 3824.07 | I84: =H84/$H$121 -> 0.0014345529 | J84: 0.002 | L84: 95.91 | M84: 45693 | N84: =(F84/L84-1) -> -0.027525805 | O84: =IFERROR(__xludf.DUMMYFUNCTION("N84 - ((GOOGLEFINANCE(""SPY"")/INDEX(GOOGLEFINANCE(""SPY"",""price"",M84),2,2))-1)"),-0.15709781563756442) -> -0.15709782 | Q84: =IFERROR(__xludf.DUMMYFUNCTION("IFERROR(GOOGLEFINANCE(B84, ""beta""), ""N/A"")"),0.89) -> 0.89 | S84: Buy at 0.20% | T84: 45691
B85: VTRS | C85: =IFERROR(__xludf.DUMMYFUNCTION("GOOGLEFINANCE(B85, ""Name"")"),"Viatris Inc") -> Viatris Inc | E85: =IFERROR(__xludf.DUMMYFUNCTION("SPARKLINE(GOOGLEFINANCE(B85, ""price"", TODAY()-365, TODAY(), ""DAILY""))"),"") | F85: =IFERROR(__xludf.DUMMYFUNCTION("IFERROR(GOOGLEFINANCE(B85), 0)"),15.89) -> 15.89 | G85: 292 | H85: =F85*G85 -> 4639.88 | I85: =H85/$H$121 -> 0.001740594 | J85: 0.002 | L85: 14.32 | M85: 45693 | N85: =(F85/L85-1) -> 0.10963687 | O85: =IFERROR(__xludf.DUMMYFUNCTION("N85 - ((GOOGLEFINANCE(""SPY"")/INDEX(GOOGLEFINANCE(""SPY"",""price"",M85),2,2))-1)"),-0.019935138686582032) -> -0.019935139 | Q85: =IFERROR(__xludf.DUMMYFUNCTION("IFERROR(GOOGLEFINANCE(B85, ""beta""), ""N/A"")"),0.79) -> 0.79 | S85: Buy at 0.20% | T85: 45691
B86: T | C86: =IFERROR(__xludf.DUMMYFUNCTION("GOOGLEFINANCE(B86, ""Name"")"),"AT&T Inc") -> AT&T Inc | E86: =IFERROR(__xludf.DUMMYFUNCTION("SPARKLINE(GOOGLEFINANCE(B86, ""price"", TODAY()-365, TODAY(), ""DAILY""))"),"") | F86: =IFERROR(__xludf.DUMMYFUNCTION("IFERROR(GOOGLEFINANCE(B86), 0)"),28.82) -> 28.82 | G86: 149 | H86: =F86*G86 -> 4294.18 | I86: =H86/$H$121 -> 0.0016109089 | J86: 0.002 | L86: 27.17 | M86: 45693 | N86: =(F86/L86-1) -> 0.060728745 | O86: =IFERROR(__xludf.DUMMYFUNCTION("N86 - ((GOOGLEFINANCE(""SPY"")/INDEX(GOOGLEFINANCE(""SPY"",""price"",M86),2,2))-1)"),-0.06884326525569073) -> -0.068843265 | Q86: =IFERROR(__xludf.DUMMYFUNCTION("IFERROR(GOOGLEFINANCE(B86, ""beta""), ""N/A"")"),0.4) -> 0.4 | S86: Buy at 0.20% | T86: 45691
B87: CVX | C87: =IFERROR(__xludf.DUMMYFUNCTION("GOOGLEFINANCE(B87, ""Name"")"),"Chevron Corp") -> Chevron Corp | E87: =IFERROR(__xludf.DUMMYFUNCTION("SPARKLINE(GOOGLEFINANCE(B87, ""price"", TODAY()-365, TODAY(), ""DAILY""))"),"") | F87: =IFERROR(__xludf.DUMMYFUNCTION("IFERROR(GOOGLEFINANCE(B87), 0)"),185.33) -> 185.33 | G87: 22 | H87: =F87*G87 -> 4077.26 | I87: =H87/$H$121 -> 0.0015295341 | J87: 0.002 | L87: 179.27 | M87: 45693 | N87: =(F87/L87-1) -> 0.03380376 | O87: =IFERROR(__xludf.DUMMYFUNCTION("N87 - ((GOOGLEFINANCE(""SPY"")/INDEX(GOOGLEFINANCE(""SPY"",""price"",M87),2,2))-1)"),-0.0957682505028774) -> -0.09576825 | Q87: =IFERROR(__xludf.DUMMYFUNCTION("IFERROR(GOOGLEFINANCE(B87, ""beta""), ""N/A"")"),0.7) -> 0.7 | S87: Buy at 0.20% | T87: 45691
A88: VC2 Total | H88: =SUM(H83:H87) -> 20846.21 | I88: =H88/$H$121 -> 0.0078201999 | J88: 0.01 | L88: =SUMPRODUCT(G83:G87,L83:L87) -> 19938.66 | M88: =AVERAGE(M83:M87) -> 45693 | N88: =(H88/L88-1) -> 0.045517101 | O88: =IFERROR(__xludf.DUMMYFUNCTION("N88 - ((GOOGLEFINANCE(""SPY"")/INDEX(GOOGLEFINANCE(""SPY"",""price"",M88),2,2))-1)"),-0.08405490924635273) -> -0.084054909 | Q88: =SUMPRODUCT(I83:I87/SUMIF(Q83:Q87, "<>N/A", I83:I87),Q83:Q87) -> 0.69501188
B89: Auto-DCF Strategy
B90: CMG | C90: =IFERROR(__xludf.DUMMYFUNCTION("GOOGLEFINANCE(B90, ""Name"")"),"Chipotle Mexican Grill Inc") -> Chipotle Mexican Grill Inc | E90: =IFERROR(__xludf.DUMMYFUNCTION("SPARKLINE(GOOGLEFINANCE(B90, ""price"", TODAY()-365, TODAY(), ""DAILY""))"),"") | F90: =IFERROR(__xludf.DUMMYFUNCTION("IFERROR(GOOGLEFINANCE(B90), 0)"),36.39) -> 36.39 | G90: 153 | H90: =F90*G90 -> 5567.67 | I90: =H90/$H$121 -> 0.0020886431 | J90: 0.00167 | L90: 38.88 | M90: 45693 | N90: =(F90/L90-1) -> -0.06404321 | O90: =IFERROR(__xludf.DUMMYFUNCTION("N90 - ((GOOGLEFINANCE(""SPY"")/INDEX(GOOGLEFINANCE(""SPY"",""price"",M90),2,2))-1)"),-0.19361522007150522) -> -0.19361522 | Q90: =IFERROR(__xludf.DUMMYFUNCTION("IFERROR(GOOGLEFINANCE(B90, ""beta""), ""N/A"")"),0.99) -> 0.99 | S90: Buy at 0.20% | T90: 45691
B91: TPL | C91: =IFERROR(__xludf.DUMMYFUNCTION("GOOGLEFINANCE(B91, ""Name"")"),"Texas Pacific Land Corp") -> Texas Pacific Land Corp | E91: =IFERROR(__xludf.DUMMYFUNCTION("SPARKLINE(GOOGLEFINANCE(B91, ""price"", TODAY()-365, TODAY(), ""DAILY""))"),"") | F91: =IFERROR(__xludf.DUMMYFUNCTION("IFERROR(GOOGLEFINANCE(B91), 0)"),525.12) -> 525.12 | G91: 17 | H91: =F91*G91 -> 8927.04 | I91: =H91/$H$121 -> 0.0033488695 | J91: 0.00167 | L91: 343.75 | M91: 45693 | N91: =(F91/L91-1) -> 0.52762182 | O91: =IFERROR(__xludf.DUMMYFUNCTION("N91 - ((GOOGLEFINANCE(""SPY"")/INDEX(GOOGLEFINANCE(""SPY"",""price"",M91),2,2))-1)"),0.3980498079868562) -> 0.39804981 | Q91: =IFERROR(__xludf.DUMMYFUNCTION("IFERROR(GOOGLEFINANCE(B91, ""beta""), ""N/A"")"),0.77) -> 0.77 | S91: Buy at 0.20% | T91: 45691
B92: MPWR | C92: =IFERROR(__xludf.DUMMYFUNCTION("GOOGLEFINANCE(B92, ""Name"")"),"Monolithic Power Systems Inc") -> Monolithic Power Systems Inc | E92: =IFERROR(__xludf.DUMMYFUNCTION("SPARKLINE(GOOGLEFINANCE(B92, ""price"", TODAY()-365, TODAY(), ""DAILY""))"),"") | F92: =IFERROR(__xludf.DUMMYFUNCTION("IFERROR(GOOGLEFINANCE(B92), 0)"),1185.28) -> 1185.28 | G92: 5 | H92: =F92*G92 -> 5926.4 | I92: =H92/$H$121 -> 0.0022232162 | J92: 0.00167 | L92: 1169.7 | M92: 45693 | N92: =(F92/L92-1) -> 0.013319655 | O92: =IFERROR(__xludf.DUMMYFUNCTION("N92 - ((GOOGLEFINANCE(""SPY"")/INDEX(GOOGLEFINANCE(""SPY"",""price"",M92),2,2))-1)"),-0.11625235558266822) -> -0.11625236 | Q92: =IFERROR(__xludf.DUMMYFUNCTION("IFERROR(GOOGLEFINANCE(B92, ""beta""), ""N/A"")"),1.45) -> 1.45 | S92: Buy at 0.20% | T92: 45691
B93: PHM | C93: =IFERROR(__xludf.DUMMYFUNCTION("GOOGLEFINANCE(B93, ""Name"")"),"Pultegroup Inc") -> Pultegroup Inc | E93: =IFERROR(__xludf.DUMMYFUNCTION("SPARKLINE(GOOGLEFINANCE(B93, ""price"", TODAY()-365, TODAY(), ""DAILY""))"),"") | F93: =IFERROR(__xludf.DUMMYFUNCTION("IFERROR(GOOGLEFINANCE(B93), 0)"),138.16) -> 138.16 | G93: 45 | H93: =F93*G93 -> 6217.2 | I93: =H93/$H$121 -> 0.0023323063 | J93: 0.00167 | L93: 133.72 | M93: 45693 | N93: =(F93/L93-1) -> 0.033203709 | O93: =IFERROR(__xludf.DUMMYFUNCTION("N93 - ((GOOGLEFINANCE(""SPY"")/INDEX(GOOGLEFINANCE(""SPY"",""price"",M93),2,2))-1)"),-0.0963683009517673) -> -0.096368301 | Q93: =IFERROR(__xludf.DUMMYFUNCTION("IFERROR(GOOGLEFINANCE(B93, ""beta""), ""N/A"")"),1.33) -> 1.33 | S93: Buy at 0.20% | T93: 45691
B94: INCY | C94: =IFERROR(__xludf.DUMMYFUNCTION("GOOGLEFINANCE(B94, ""Name"")"),"Incyte Corp") -> Incyte Corp | E94: =IFERROR(__xludf.DUMMYFUNCTION("SPARKLINE(GOOGLEFINANCE(B94, ""price"", TODAY()-365, TODAY(), ""DAILY""))"),"") | F94: =IFERROR(__xludf.DUMMYFUNCTION("IFERROR(GOOGLEFINANCE(B94), 0)"),100.53) -> 100.53 | G94: 60 | H94: =F94*G94 -> 6031.8 | I94: =H94/$H$121 -> 0.0022627558 | J94: 0.00167 | L94: 103.98 | M94: 45693 | N94: =(F94/L94-1) -> -0.033179458 | O94: =IFERROR(__xludf.DUMMYFUNCTION("N94 - ((GOOGLEFINANCE(""SPY"")/INDEX(GOOGLEFINANCE(""SPY"",""price"",M94),2,2))-1)"),-0.16275146778295968) -> -0.16275147 | Q94: =IFERROR(__xludf.DUMMYFUNCTION("IFERROR(GOOGLEFINANCE(B94, ""beta""), ""N/A"")"),0.82) -> 0.82 | S94: Buy at 0.20% | T94: 45691
E95: =IFERROR(__xludf.DUMMYFUNCTION("SPARKLINE(GOOGLEFINANCE(B95, ""price"", TODAY()-365, TODAY(), ""DAILY""))"),"#N/A") -> #N/A | F95: =IFERROR(__xludf.DUMMYFUNCTION("IFERROR(GOOGLEFINANCE(B95), 0)"),0.0) -> 0 | G95: 0 | H95: =F95*G95 -> 0 | I95: =H95/$H$121 -> 0 | J95: 0.00167 | L95: 27.24 | M95: 45792 | N95: =(F95/L95-1) -> -1 | O95: =IFERROR(__xludf.DUMMYFUNCTION("N95 - ((GOOGLEFINANCE(""SPY"")/INDEX(GOOGLEFINANCE(""SPY"",""price"",M95),2,2))-1)"),-1.1558954035836466) -> -1.1558954 | Q95: =IFERROR(__xludf.DUMMYFUNCTION("IFERROR(GOOGLEFINANCE(B95, ""beta""), ""N/A"")"),"N/A") -> N/A
A96: Auto-DCF Total | H96: =SUM(H90:H95) -> 32670.11 | I96: =H96/$H$121 -> 0.012255791 | J96: 0.01 | L96: =SUMPRODUCT(G90:G95,L90:L95) -> 29897.09 | M96: =AVERAGE(M90:M95) -> 45709.5 | N96: =(H96/L96-1) -> 0.092752171 | O96: =IFERROR(__xludf.DUMMYFUNCTION("N96 - ((GOOGLEFINANCE(""SPY"")/INDEX(GOOGLEFINANCE(""SPY"",""price"",M96),2,2))-1)"),-0.04487825884618557) -> -0.044878259 | Q96: =SUMPRODUCT(I90:I95/SUMIF(Q90:Q95, "<>N/A", I90:I95),Q90:Q95) -> 1.0466462
B97: SPY | C97: SPDR S&P 500 ETF | E97: =IFERROR(__xludf.DUMMYFUNCTION("SPARKLINE(GOOGLEFINANCE(B97, ""price"", TODAY()-365, TODAY(), ""DAILY""))"),"") | F97: =IFERROR(__xludf.DUMMYFUNCTION("GOOGLEFINANCE(B97)"),682.51) -> 682.51 | G97: 0 | H97: =F97*G97 -> 0 | I97: =H97/$H$121 -> 0 | L97: 409.19 | S97: NA | T97: NA | U97: NA | V97: NA
A98: Sector Total | H98: =SUM(H88,H96,H97) -> 53516.32 | I98: =H98/$H$121 -> 0.020075991 | J98: 0.02 | L98: =SUMPRODUCT(G83:G87,L83:L87)+SUMPRODUCT(G90:G95,L90:L95) -> 49835.75 | M98: =AVERAGE(M88, M96) -> 45701.25 | N98: =(H98/L98-1) -> 0.07385401 | O98: =IFERROR(__xludf.DUMMYFUNCTION("N98 - ((GOOGLEFINANCE(""SPY"")/INDEX(GOOGLEFINANCE(""SPY"",""price"",M98),2,2))-1)"),-0.045510298368172775) -> -0.045510298 | Q98: =AVERAGE(Q88, Q96) -> 0.87082904
A100: Equities Total | H100: =SUM(H8,H15,H23,H33,H42,H50,H56,H66,H72,H79,H98) -> 2160084.1 | I100: =H100/H121 -> 0.81032905 | J100: =SUM(J8,J15,J23,J33,J42,J50,J56,J66,J72,J79,J98) -> 0.81 | L100: =SUM(L8,L15,L23,L33,L42,L50,L56,L66,L72,L79,L98) -> 1412760.7 | M100: =AVERAGE(M8,M15,M23,M33,M42,M50,M56,M66,M72,M79,M98) -> 44907.687 | N100: =((H100-H118)/L100-1) -> 0.42699759 | Q100: =IFERROR(__xludf.DUMMYFUNCTION("AVERAGE.WEIGHTED(Q8,I8,Q15,I15,Q23,I23,Q33,I33,Q42,I42,Q50,I50,Q56,I56,Q66,I66,Q72,I72,Q79,I79,Q98,I98)"),0.9803730069524024) -> 0.98037301
A102: Fixed Income
B103: 449669AK6 | C103: MOS 7.3 01/15/28 Corp | F103: 1066.26 | G103: 25 | H103: =F103*G103 -> 26656.5 | I103: =H103/$H$121 -> 0.0099998589 | J103: 0.015 | L103: 1092.5 | M103: 44823 | N103: =((F103)/L103-1) -> -0.024018307 | S103: Buy at 1.5% | U103: 1000 | V103: =IFERROR(F103/U103-1, "NA") -> 0.06626
B104: 05530QAP5 | C104: BTI 4.448 03/16/28 Corp | F104: 1008.34 | G104: 29 | H104: =F104*G104 -> 29241.86 | I104: =H104/$H$121 -> 0.010969725 | J104: 0.015 | L104: 907.92 | M104: 44830 | N104: =((F104)/L104-1) -> 0.11060446 | S104: Buy at 1.5% | T104: 44824 | U104: 1000 | V104: =IFERROR(F104/U104-1, "NA") -> 0.00834
B105: 695114BZ0 | C105: Pacificorp 5.25 06/15/35 | F105: 1023.38 | G105: 43 | H105: =F105*G105 -> 44005.34 | I105: =H105/$H$121 -> 0.016508063 | J105: 0.02 | L105: 948.61 | M105: 45261 | N105: =(F105/L105-1) -> 0.07882059 | S105: Buy at 2% | T105: 45261 | U105: 1000 | V105: =IFERROR(F105/U105-1, "NA") -> 0.02338
B106: 61747YFT7 | C106: MS 5.32 07/19/35 | F106: 1039.79 | G106: 47 | H106: =F106*G106 -> 48870.13 | I106: =H106/$H$121 -> 0.01833303 | J106: 0.02 | L106: 1038.1 | M106: 45561 | N106: =(F106/L106-1) -> 0.0016279742 | S106: Buy at 2% | T106: 45552 | U106: 1040 | V106: =IFERROR(F106/U106-1, "NA") -> -0.00020192308
B107: 822582AD4 | C107: RDSALN 6.375 12/15/38 | F107: 1146.39 | G107: 43 | H107: =F107*G107 -> 49294.77 | I107: =H107/$H$121 -> 0.018492328 | J107: 0.02 | L107: 1120.55 | M107: 45590 | N107: =(F107/L107-1) -> 0.023060104 | S107: Buy at 2% | T107: 45590 | U107: 1120 | V107: =IFERROR(F107/U107-1, "NA") -> 0.0235625
B108: 626717AP7 | C108: MUR 6 10/01/32 | F108: 991.22 | G108: 25 | H108: =F108*G108 -> 24780.5 | I108: =H108/$H$121 -> 0.0092961005 | J108: 0.01 | L108: 966.6 | M108: 45611 | N108: =(F108/L108-1) -> 0.025470722 | S108: Buy at 1% | T108: 45610 | U108: 966 | V108: =IFERROR(F108/U108-1, "NA") -> 0.02610766
B109: 446413BA3 | C109: HII Corp 5.353 1/15/30 | F109: 1038.97 | G109: 33 | H109: =F109*G109 -> 34286.01 | I109: =H109/$H$121 -> 0.012861976 | J109: 0.0125 | L109: 993.26 | M109: 45701 | N109: =(F109/L109-1) -> 0.046020176 | S109: Buy at 1.25% | T109: 45700 | U109: 1000 | V109: =IFERROR(F109/U109-1, "NA") -> 0.03897
B110: 29379VBM4 | C110: EPD Corp SOFR+3.248 08/16/77 | F110: 1003.57 | G110: 24 | H110: =F110*G110 -> 24085.68 | I110: =H110/$H$121 -> 0.0090354473 | J110: 0.01 | L110: 1003.1 | M110: 45748 | N110: =(F110/L110-1) -> 0.0004685475 | S110: Buy at 1.00% | T110: 45741 | U110: 1000 | V110: =IFERROR(F110/U110-1, "NA") -> 0.00357
B111: 3133ELEN0 | C111: FFCB Corp. 2.25 12/18/29 | F111: 939.38 | G111: 25 | H111: =F111*G111 -> 23484.5 | I111: =H111/$H$121 -> 0.008809922 | J111: 0.015 | L111: 1007.19 | M111: 43864 | N111: =(F111/L111-1) -> -0.067325927 | S111: Hold | T111: 44292 | U111: 1000 | V111: =IFERROR(F111/U111-1, "NA") -> -0.06062
B112: 3133EJEP0 | C112: FFCB 3.50 03/02/34 | F112: 948.12 | G112: 33 | H112: =F112*G112 -> 31287.96 | I112: =H112/$H$121 -> 0.011737294 | J112: 0.015 | L112: 854.34 | M112: 45230 | N112: =(F112/L112-1) -> 0.10976894 | S112: Buy at 1.5% | T112: 45230 | U112: 1000 | V112: =IFERROR(F112/U112-1, "NA") -> -0.05188
...

Sheet Spring 2026 Trades
A1: Ticker | B1: Description | C1: Sector | D1: Trade Type | E1: Shares | F1: Trade Price | G1: Trade Date | H1: % Gain on Sale | I1: Cash Gain/Loss
A2: MPC | B2: =IFERROR(__xludf.DUMMYFUNCTION("GOOGLEFINANCE(A2,""NAME"")"),"Marathon Petroleum Corp") -> Marathon Petroleum Corp | C2: Quant | D2: Sell to Close | E2: 30 | F2: 194.63 | G2: 46057 | H2: =IF(OR(D2="Sell to Trim", D2="Sell to Close"),F2/VLOOKUP(A2, 'Sector Holdings'!$B$3:$M$121, 11, FALSE) - 1, "N/A") -> #N/A | I2: =IFS(D2="Sell to Close", F2*E2*1, D2="Sell to Trim", F2*E2*1, D2="Buy to Add", F2*E2*-1, D2="Buy to Open", F2*E2*-1) -> 5838.9
A3: CHTR | B3: =IFERROR(__xludf.DUMMYFUNCTION("GOOGLEFINANCE(A3,""NAME"")"),"Charter Communications Inc") -> Charter Communications Inc | C3: Quant | D3: Sell to Close | E3: 12 | F3: 226.68 | G3: 46057 | H3: =IF(OR(D3="Sell to Trim", D3="Sell to Close"),F3/VLOOKUP(A3, 'Sector Holdings'!$B$3:$M$121, 11, FALSE) - 1, "N/A") -> #N/A | I3: =IFS(D3="Sell to Close", F3*E3*1, D3="Sell to Trim", F3*E3*1, D3="Buy to Add", F3*E3*-1, D3="Buy to Open", F3*E3*-1) -> 2720.16
A4: CF | B4: =IFERROR(__xludf.DUMMYFUNCTION("GOOGLEFINANCE(A4,""NAME"")"),"CF Industries Holdings, Inc.") -> CF Industries Holdings, Inc. | C4: Quant | D4: Sell to Close | E4: 59 | F4: 93.65 | G4: 46057 | H4: =IF(OR(D4="Sell to Trim", D4="Sell to Close"),F4/VLOOKUP(A4, 'Sector Holdings'!$B$3:$M$121, 11, FALSE) - 1, "N/A") -> #N/A | I4: =IFS(D4="Sell to Close", F4*E4*1, D4="Sell to Trim", F4*E4*1, D4="Buy to Add", F4*E4*-1, D4="Buy to Open", F4*E4*-1) -> 5525.35
A5: WYNN | B5: =IFERROR(__xludf.DUMMYFUNCTION("GOOGLEFINANCE(A5,""NAME"")"),"Wynn Resorts Ltd") -> Wynn Resorts Ltd | C5: Quant | D5: Sell to Close | E5: 52 | F5: 113.69 | G5: 46057 | H5: =IF(OR(D5="Sell to Trim", D5="Sell to Close"),F5/VLOOKUP(A5, 'Sector Holdings'!$B$3:$M$121, 11, FALSE) - 1, "N/A") -> #N/A | I5: =IFS(D5="Sell to Close", F5*E5*1, D5="Sell to Trim", F5*E5*1, D5="Buy to Add", F5*E5*-1, D5="Buy to Open", F5*E5*-1) -> 5911.88
A6: INCY | B6: =IFERROR(__xludf.DUMMYFUNCTION("GOOGLEFINANCE(A6,""NAME"")"),"Incyte Corp") -> Incyte Corp | C6: Quant | D6: Sell to Close | E6: 70 | F6: 101.72 | G6: 46057 | H6: =IF(OR(D6="Sell to Trim", D6="Sell to Close"),F6/VLOOKUP(A6, 'Sector Holdings'!$B$3:$M$121, 11, FALSE) - 1, "N/A") -> -0.021734949 | I6: =IFS(D6="Sell to Close", F6*E6*1, D6="Sell to Trim", F6*E6*1, D6="Buy to Add", F6*E6*-1, D6="Buy to Open", F6*E6*-1) -> 7120.4
A7: PHM | B7: =IFERROR(__xludf.DUMMYFUNCTION("GOOGLEFINANCE(A7,""NAME"")"),"Pultegroup Inc") -> Pultegroup Inc | C7: Quant | D7: Sell to Close | E7: 42 | F7: 133.08 | G7: 46057 | H7: =IF(OR(D7="Sell to Trim", D7="Sell to Close"),F6/VLOOKUP(A6, 'Sector Holdings'!$B$3:$M$121, 11, FALSE) - 1, "N/A") -> -0.021734949 | I7: =IFS(D7="Sell to Close", F7*E7*1, D7="Sell to Trim", F7*E7*1, D7="Buy to Add", F7*E7*-1, D7="Buy to Open", F7*E7*-1) -> 5589.36
A8: EPAM | B8: =IFERROR(__xludf.DUMMYFUNCTION("GOOGLEFINANCE(A8,""NAME"")"),"EPAM Systems Inc") -> EPAM Systems Inc | C8: Quant | D8: Sell to Close | E8: 23 | F8: 181.44 | G8: 46057 | H8: =IF(OR(D8="Sell to Trim", D8="Sell to Close"),F7/VLOOKUP(A7, 'Sector Holdings'!$B$3:$M$121, 11, FALSE) - 1, "N/A") -> -0.0047861203 | I8: =IFS(D8="Sell to Close", F8*E8*1, D8="Sell to Trim", F8*E8*1, D8="Buy to Add", F8*E8*-1, D8="Buy to Open", F8*E8*-1) -> 4173.12
A9: MNST | B9: =IFERROR(__xludf.DUMMYFUNCTION("GOOGLEFINANCE(A9,""NAME"")"),"Monster Beverage Corp") -> Monster Beverage Corp | C9: Quant | D9: Sell to Close | E9: 70 | F9: 81.12 | G9: 46057 | H9: =IF(OR(D9="Sell to Trim", D9="Sell to Close"),F8/VLOOKUP(A8, 'Sector Holdings'!$B$3:$M$121, 11, FALSE) - 1, "N/A") -> #N/A | I9: =IFS(D9="Sell to Close", F9*E9*1, D9="Sell to Trim", F9*E9*1, D9="Buy to Add", F9*E9*-1, D9="Buy to Open", F9*E9*-1) -> 5678.4
A10: XOM | B10: =IFERROR(__xludf.DUMMYFUNCTION("GOOGLEFINANCE(A10,""NAME"")"),"Exxon Mobil Corp") -> Exxon Mobil Corp | C10: Quant | D10: Sell to Close | E10: 39 | F10: 146.52 | G10: 46057 | H10: =IF(OR(D10="Sell to Trim", D10="Sell to Close"),F9/VLOOKUP(A9, 'Sector Holdings'!$B$3:$M$121, 11, FALSE) - 1, "N/A") -> #N/A | I10: =IFS(D10="Sell to Close", F10*E10*1, D10="Sell to Trim", F10*E10*1, D10="Buy to Add", F10*E10*-1, D10="Buy to Open", F10*E10*-1) -> 5714.28
A11: KHC | B11: =IFERROR(__xludf.DUMMYFUNCTION("GOOGLEFINANCE(A11,""NAME"")"),"Kraft Heinz Co") -> Kraft Heinz Co | C11: Quant | D11: Sell to Close | E11: 156 | F11: 24.5 | G11: 46057 | H11: =IF(OR(D11="Sell to Trim", D11="Sell to Close"),F10/VLOOKUP(A10, 'Sector Holdings'!$B$3:$M$121, 11, FALSE) - 1, "N/A") -> #N/A | I11: =IFS(D11="Sell to Close", F11*E11*1, D11="Sell to Trim", F11*E11*1, D11="Buy to Add", F11*E11*-1, D11="Buy to Open", F11*E11*-1) -> 3822
A12: AMZN | B12: =IFERROR(__xludf.DUMMYFUNCTION("GOOGLEFINANCE(A12,""NAME"")"),"Amazon.com Inc") -> Amazon.com Inc | C12: Consumer Discretionary | D12: Buy to Add | E12: 47 | F12: 237.45 | G12: 46057 | H12: =IF(OR(D12="Sell to Trim", D12="Sell to Close"),F11/VLOOKUP(A11, 'Sector Holdings'!$B$3:$M$121, 11, FALSE) - 1, "N/A") -> N/A | I12: =IFS(D12="Sell to Close", F12*E12*1, D12="Sell to Trim", F12*E12*1, D12="Buy to Add", F12*E12*-1, D12="Buy to Open", F12*E12*-1) -> -11160.15
A13: LVMUY | B13: =IFERROR(__xludf.DUMMYFUNCTION("GOOGLEFINANCE(A13,""NAME"")"),"LVMH Moet Hennessy Louis Vuitton SA Unsponsored ADR") -> LVMH Moet Hennessy Louis Vuitton SA Unsponsored ADR | C13: Consumer Discretionary | D13: Buy to Add | E13: 46 | F13: 126.4 | G13: 46057 | H13: =IF(OR(D13="Sell to Trim", D13="Sell to Close"),F13/VLOOKUP(A13, 'Sector Holdings'!$B$3:$M$121, 11, FALSE) - 1, "N/A") -> N/A | I13: =IFS(D13="Sell to Close", F13*E13*1, D13="Sell to Trim", F13*E13*1, D13="Buy to Add", F13*E13*-1, D13="Buy to Open", F13*E13*-1) -> -5814.4
A14: ABNB | B14: =IFERROR(__xludf.DUMMYFUNCTION("GOOGLEFINANCE(A14,""NAME"")"),"Airbnb Inc") -> Airbnb Inc | C14: Consumer Discretionary | D14: Buy to Add | E14: 46 | F14: 124.2 | G14: 46057 | H14: =IF(OR(D14="Sell to Trim", D14="Sell to Close"),F14/VLOOKUP(A14, 'Sector Holdings'!$B$3:$M$121, 11, FALSE) - 1, "N/A") -> N/A | I14: =IFS(D14="Sell to Close", F14*E14*1, D14="Sell to Trim", F14*E14*1, D14="Buy to Add", F14*E14*-1, D14="Buy to Open", F14*E14*-1) -> -5713.2
A15: POST | B15: =IFERROR(__xludf.DUMMYFUNCTION("GOOGLEFINANCE(A15,""NAME"")"),"Post Holdings Inc") -> Post Holdings Inc | C15: Consumer Staples | D15: Sell to Trim | E15: 93 | F15: 103.9 | G15: 46057 | H15: =IF(OR(D15="Sell to Trim", D15="Sell to Close"),F15/VLOOKUP(A15, 'Sector Holdings'!$B$3:$M$121, 11, FALSE) - 1, "N/A") -> 0.22120357 | I15: =IFS(D15="Sell to Close", F15*E15*1, D15="Sell to Trim", F15*E15*1, D15="Buy to Add", F15*E15*-1, D15="Buy to Open", F15*E15*-1) -> 9662.7
A16: SPGI | B16: =IFERROR(__xludf.DUMMYFUNCTION("GOOGLEFINANCE(A16,""NAME"")"),"S&P Global Inc") -> S&P Global Inc | C16: Financials | D16: Buy to Add | E16: 20 | F16: 453.64 | G16: 46057 | H16: =IF(OR(D16="Sell to Trim", D16="Sell to Close"),F16/VLOOKUP(A16, 'Sector Holdings'!$B$3:$M$121, 11, FALSE) - 1, "N/A") -> N/A | I16: =IFS(D16="Sell to Close", F16*E16*1, D16="Sell to Trim", F16*E16*1, D16="Buy to Add", F16*E16*-1, D16="Buy to Open", F16*E16*-1) -> -9072.8
A17: TMO | B17: =IFERROR(__xludf.DUMMYFUNCTION("GOOGLEFINANCE(A17,""NAME"")"),"Thermo Fisher Scientific Inc") -> Thermo Fisher Scientific Inc | C17: Healthcare | D17: Buy to Add | E17: 3 | F17: 574.4 | G17: 46057 | H17: =IF(OR(D17="Sell to Trim", D17="Sell to Close"),F17/VLOOKUP(A17, 'Sector Holdings'!$B$3:$M$121, 11, FALSE) - 1, "N/A") -> N/A | I17: =IFS(D17="Sell to Close", F17*E17*1, D17="Sell to Trim", F17*E17*1, D17="Buy to Add", F17*E17*-1, D17="Buy to Open", F17*E17*-1) -> -1723.2
A18: UNH | B18: =IFERROR(__xludf.DUMMYFUNCTION("GOOGLEFINANCE(A18,""NAME"")"),"UnitedHealth Group Inc") -> UnitedHealth Group Inc | C18: Healthcare | D18: Buy to Add | E18: 7 | F18: 280.32 | G18: 46057 | H18: =IF(OR(D18="Sell to Trim", D18="Sell to Close"),F18/VLOOKUP(A18, 'Sector Holdings'!$B$3:$M$121, 11, FALSE) - 1, "N/A") -> N/A | I18: =IFS(D18="Sell to Close", F18*E18*1, D18="Sell to Trim", F18*E18*1, D18="Buy to Add", F18*E18*-1, D18="Buy to Open", F18*E18*-1) -> -1962.24
A19: VEEV | B19: =IFERROR(__xludf.DUMMYFUNCTION("GOOGLEFINANCE(A19,""NAME"")"),"Veeva Systems Inc") -> Veeva Systems Inc | C19: Healthcare | D19: Buy to Add | E19: 10 | F19: 190.11 | G19: 46057 | H19: =IF(OR(D19="Sell to Trim", D19="Sell to Close"),F19/VLOOKUP(A19, 'Sector Holdings'!$B$3:$M$121, 11, FALSE) - 1, "N/A") -> N/A | I19: =IFS(D19="Sell to Close", F19*E19*1, D19="Sell to Trim", F19*E19*1, D19="Buy to Add", F19*E19*-1, D19="Buy to Open", F19*E19*-1) -> -1901.1
A20: RPRX | B20: =IFERROR(__xludf.DUMMYFUNCTION("GOOGLEFINANCE(A20,""NAME"")"),"Royalty Pharma plc") -> Royalty Pharma plc | C20: Healthcare | D20: Buy to Add | E20: 46 | F20: 43.16 | G20: 46057 | H20: =IF(OR(D20="Sell to Trim", D20="Sell to Close"),F20/VLOOKUP(A20, 'Sector Holdings'!$B$3:$M$121, 11, FALSE) - 1, "N/A") -> N/A | I20: =IFS(D20="Sell to Close", F20*E20*1, D20="Sell to Trim", F20*E20*1, D20="Buy to Add", F20*E20*-1, D20="Buy to Open", F20*E20*-1) -> -1985.36
A21: MRK | B21: =IFERROR(__xludf.DUMMYFUNCTION("GOOGLEFINANCE(A21,""NAME"")"),"Merck & Co Inc") -> Merck & Co Inc | C21: Healthcare | D21: Buy to Add | E21: 17 | F21: 118.74 | G21: 46057 | H21: =IF(OR(D21="Sell to Trim", D21="Sell to Close"),F21/VLOOKUP(A21, 'Sector Holdings'!$B$3:$M$121, 11, FALSE) - 1, "N/A") -> N/A | I21: =IFS(D21="Sell to Close", F21*E21*1, D21="Sell to Trim", F21*E21*1, D21="Buy to Add", F21*E21*-1, D21="Buy to Open", F21*E21*-1) -> -2018.58
A22: GE | B22: =IFERROR(__xludf.DUMMYFUNCTION("GOOGLEFINANCE(A22,""NAME"")"),"General Electric Co") -> General Electric Co | C22: Industrials | D22: Buy to Add | E22: 17 | F22: 304.61 | G22: 46057 | H22: =IF(OR(D22="Sell to Trim", D22="Sell to Close"),F22/VLOOKUP(A22, 'Sector Holdings'!$B$3:$M$121, 11, FALSE) - 1, "N/A") -> N/A | I22: =IFS(D22="Sell to Close", F22*E22*1, D22="Sell to Trim", F22*E22*1, D22="Buy to Add", F22*E22*-1, D22="Buy to Open", F22*E22*-1) -> -5178.37
A23: AMRZ | B23: =IFERROR(__xludf.DUMMYFUNCTION("GOOGLEFINANCE(A23,""NAME"")"),"Amrize AG") -> Amrize AG | C23: Industrials | D23: Buy to Add | E23: 91 | F23: 55.07 | G23: 46057 | H23: =IF(OR(D23="Sell to Trim", D23="Sell to Close"),F23/VLOOKUP(A23, 'Sector Holdings'!$B$3:$M$121, 11, FALSE) - 1, "N/A") -> N/A | I23: =IFS(D23="Sell to Close", F23*E23*1, D23="Sell to Trim", F23*E23*1, D23="Buy to Add", F23*E23*-1, D23="Buy to Open", F23*E23*-1) -> -5011.37
A24: PLD | B24: =IFERROR(__xludf.DUMMYFUNCTION("GOOGLEFINANCE(A24,""NAME"")"),"Prologis Inc") -> Prologis Inc | C24: REITS | D24: Sell to Trim | E24: 5 | F24: 133.71 | G24: 46057 | H24: =IF(OR(D24="Sell to Trim", D24="Sell to Close"),F24/VLOOKUP(A24, 'Sector Holdings'!$B$3:$M$121, 11, FALSE) - 1, "N/A") -> 0.78541861 | I24: =IFS(D24="Sell to Close", F24*E24*1, D24="Sell to Trim", F24*E24*1, D24="Buy to Add", F24*E24*-1, D24="Buy to Open", F24*E24*-1) -> 668.55
A25: ADC | B25: =IFERROR(__xludf.DUMMYFUNCTION("GOOGLEFINANCE(A25,""NAME"")"),"Agree Realty Corp") -> Agree Realty Corp | C25: REITS | D25: Sell to Trim | E25: 7 | F25: 73.55 | G25: 46057 | H25: =IF(OR(D25="Sell to Trim", D25="Sell to Close"),F25/VLOOKUP(A25, 'Sector Holdings'!$B$3:$M$121, 11, FALSE) - 1, "N/A") -> 0.17117834 | I25: =IFS(D25="Sell to Close", F25*E25*1, D25="Sell to Trim", F25*E25*1, D25="Buy to Add", F25*E25*-1, D25="Buy to Open", F25*E25*-1) -> 514.85
A26: SNPS | B26: =IFERROR(__xludf.DUMMYFUNCTION("GOOGLEFINANCE(A26,""NAME"")"),"Synopsys Inc") -> Synopsys Inc | C26: Technology | D26: Buy to Add | E26: 21 | F26: 417.4 | G26: 46057 | H26: =IF(OR(D26="Sell to Trim", D26="Sell to Close"),F26/VLOOKUP(A26, 'Sector Holdings'!$B$3:$M$121, 11, FALSE) - 1, "N/A") -> N/A | I26: =IFS(D26="Sell to Close", F26*E26*1, D26="Sell to Trim", F26*E26*1, D26="Buy to Add", F26*E26*-1, D26="Buy to Open", F26*E26*-1) -> -8765.4
A27: TSM | B27: =IFERROR(__xludf.DUMMYFUNCTION("GOOGLEFINANCE(A27,""NAME"")"),"Taiwan Semicndctr Mnufctrng Co Ltd") -> Taiwan Semicndctr Mnufctrng Co Ltd | C27: Technology | D27: Buy to Add | E27: 26 | F27: 329.4 | G27: 46057 | H27: =IF(OR(D27="Sell to Trim", D27="Sell to Close"),F27/VLOOKUP(A27, 'Sector Holdings'!$B$3:$M$121, 11, FALSE) - 1, "N/A") -> N/A | I27: =IFS(D27="Sell to Close", F27*E27*1, D27="Sell to Trim", F27*E27*1, D27="Buy to Add", F27*E27*-1, D27="Buy to Open", F27*E27*-1) -> -8564.4
A28: META | B28: =IFERROR(__xludf.DUMMYFUNCTION("GOOGLEFINANCE(A28,""NAME"")"),"Meta Platforms Inc") -> Meta Platforms Inc | C28: M&T | D28: Buy to Add | E28: 9 | F28: 678.31 | G28: 46057 | H28: =IF(OR(D28="Sell to Trim", D28="Sell to Close"),F28/VLOOKUP(A28, 'Sector Holdings'!$B$3:$M$121, 11, FALSE) - 1, "N/A") -> N/A | I28: =IFS(D28="Sell to Close", F28*E28*1, D28="Sell to Trim", F28*E28*1, D28="Buy to Add", F28*E28*-1, D28="Buy to Open", F28*E28*-1) -> -6104.79
A29: LYV | B29: =IFERROR(__xludf.DUMMYFUNCTION("GOOGLEFINANCE(A29,""NAME"")"),"Live Nation Entertainment Inc") -> Live Nation Entertainment Inc | C29: M&T | D29: Buy to Add | E29: 43 | F29: 142.24 | G29: 46057 | H29: =IF(OR(D29="Sell to Trim", D29="Sell to Close"),F29/VLOOKUP(A29, 'Sector Holdings'!$B$3:$M$121, 11, FALSE) - 1, "N/A") -> N/A | I29: =IFS(D29="Sell to Close", F29*E29*1, D29="Sell to Trim", F29*E29*1, D29="Buy to Add", F29*E29*-1, D29="Buy to Open", F29*E29*-1) -> -6116.32
A30: VST | B30: =IFERROR(__xludf.DUMMYFUNCTION("GOOGLEFINANCE(A30,""NAME"")"),"Vistra Corp") -> Vistra Corp | C30: Utilities | D30: Buy to Add | E30: 23 | F30: 143.69 | G30: 46057 | H30: =IF(OR(D30="Sell to Trim", D30="Sell to Close"),F30/VLOOKUP(A30, 'Sector Holdings'!$B$3:$M$121, 11, FALSE) - 1, "N/A") -> N/A | I30: =IFS(D30="Sell to Close", F30*E30*1, D30="Sell to Trim", F30*E30*1, D30="Buy to Add", F30*E30*-1, D30="Buy to Open", F30*E30*-1) -> -3304.87
A31: CMG | B31: =IFERROR(__xludf.DUMMYFUNCTION("GOOGLEFINANCE(A31,""NAME"")"),"Chipotle Mexican Grill Inc") -> Chipotle Mexican Grill Inc | C31: Quant | D31: Buy to Open | E31: 153 | F31: 38.88 | G31: 46058 | H31: =IF(OR(D31="Sell to Trim", D31="Sell to Close"),F31/VLOOKUP(A31, 'Sector Holdings'!$B$3:$M$121, 11, FALSE) - 1, "N/A") -> N/A | I31: =IFS(D31="Sell to Close", F31*E31*1, D31="Sell to Trim", F31*E31*1, D31="Buy to Add", F31*E31*-1, D31="Buy to Open", F31*E31*-1) -> -5948.64
A32: TPL | B32: =IFERROR(__xludf.DUMMYFUNCTION("GOOGLEFINANCE(A32,""NAME"")"),"Texas Pacific Land Corp") -> Texas Pacific Land Corp | C32: Quant | D32: Buy to Open | E32: 17 | F32: 343.75 | G32: 46058 | H32: =IF(OR(D32="Sell to Trim", D32="Sell to Close"),F32/VLOOKUP(A32, 'Sector Holdings'!$B$3:$M$121, 11, FALSE) - 1, "N/A") -> N/A | I32: =IFS(D32="Sell to Close", F32*E32*1, D32="Sell to Trim", F32*E32*1, D32="Buy to Add", F32*E32*-1, D32="Buy to Open", F32*E32*-1) -> -5843.75
A33: MPWR | B33: =IFERROR(__xludf.DUMMYFUNCTION("GOOGLEFINANCE(A33,""NAME"")"),"Monolithic Power Systems Inc") -> Monolithic Power Systems Inc | C33: Quant | D33: Buy to Open | E33: 5 | F33: 1169.7 | G33: 46058 | H33: =IF(OR(D33="Sell to Trim", D33="Sell to Close"),F33/VLOOKUP(A33, 'Sector Holdings'!$B$3:$M$121, 11, FALSE) - 1, "N/A") -> N/A | I33: =IFS(D33="Sell to Close", F33*E33*1, D33="Sell to Trim", F33*E33*1, D33="Buy to Add", F33*E33*-1, D33="Buy to Open", F33*E33*-1) -> -5848.5
A34: PHM | B34: =IFERROR(__xludf.DUMMYFUNCTION("GOOGLEFINANCE(A34,""NAME"")"),"Pultegroup Inc") -> Pultegroup Inc | C34: Quant | D34: Buy to Open | E34: 45 | F34: 133.72 | G34: 46058 | H34: =IF(OR(D34="Sell to Trim", D34="Sell to Close"),F34/VLOOKUP(A34, 'Sector Holdings'!$B$3:$M$121, 11, FALSE) - 1, "N/A") -> N/A | I34: =IFS(D34="Sell to Close", F34*E34*1, D34="Sell to Trim", F34*E34*1, D34="Buy to Add", F34*E34*-1, D34="Buy to Open", F34*E34*-1) -> -6017.4
A35: INCY | B35: =IFERROR(__xludf.DUMMYFUNCTION("GOOGLEFINANCE(A35,""NAME"")"),"Incyte Corp") -> Incyte Corp | C35: Quant | D35: Buy to Open | E35: 60 | F35: 103.98 | G35: 46058 | H35: =IF(OR(D35="Sell to Trim", D35="Sell to Close"),F35/VLOOKUP(A35, 'Sector Holdings'!$B$3:$M$121, 11, FALSE) - 1, "N/A") -> N/A | I35: =IFS(D35="Sell to Close", F35*E35*1, D35="Sell to Trim", F35*E35*1, D35="Buy to Add", F35*E35*-1, D35="Buy to Open", F35*E35*-1) -> -6238.8
A36: ADM | B36: =IFERROR(__xludf.DUMMYFUNCTION("GOOGLEFINANCE(A36,""NAME"")"),"Archer-Daniels-Midland Co") -> Archer-Daniels-Midland Co | C36: Quant | D36: Buy to Open | E36: 59 | F36: 64.96 | G36: 46058 | H36: =IF(OR(D36="Sell to Trim", D36="Sell to Close"),F36/VLOOKUP(A36, 'Sector Holdings'!$B$3:$M$121, 11, FALSE) - 1, "N/A") -> N/A | I36: =IFS(D36="Sell to Close", F36*E36*1, D36="Sell to Trim", F36*E36*1, D36="Buy to Add", F36*E36*-1, D36="Buy to Open", F36*E36*-1) -> -3832.64
A37: PFG | B37: =IFERROR(__xludf.DUMMYFUNCTION("GOOGLEFINANCE(A37,""NAME"")"),"Principal Financial Group Inc") -> Principal Financial Group Inc | C37: Quant | D37: Buy to Open | E37: 41 | F37: 95.91 | G37: 46058 | H37: =IF(OR(D37="Sell to Trim", D37="Sell to Close"),F37/VLOOKUP(A37, 'Sector Holdings'!$B$3:$M$121, 11, FALSE) - 1, "N/A") -> N/A | I37: =IFS(D37="Sell to Close", F37*E37*1, D37="Sell to Trim", F37*E37*1, D37="Buy to Add", F37*E37*-1, D37="Buy to Open", F37*E37*-1) -> -3932.31
A38: VTRS | B38: =IFERROR(__xludf.DUMMYFUNCTION("GOOGLEFINANCE(A38,""NAME"")"),"Viatris Inc") -> Viatris Inc | C38: Quant | D38: Buy to Open | E38: 292 | F38: 14.32 | G38: 46058 | H38: =IF(OR(D38="Sell to Trim", D38="Sell to Close"),F38/VLOOKUP(A38, 'Sector Holdings'!$B$3:$M$121, 11, FALSE) - 1, "N/A") -> N/A | I38: =IFS(D38="Sell to Close", F38*E38*1, D38="Sell to Trim", F38*E38*1, D38="Buy to Add", F38*E38*-1, D38="Buy to Open", F38*E38*-1) -> -4181.44
A39: T | B39: =IFERROR(__xludf.DUMMYFUNCTION("GOOGLEFINANCE(A39,""NAME"")"),"AT&T Inc") -> AT&T Inc | C39: Quant | D39: Buy to Open | E39: 149 | F39: 27.17 | G39: 46058 | H39: =IF(OR(D39="Sell to Trim", D39="Sell to Close"),F39/VLOOKUP(A39, 'Sector Holdings'!$B$3:$M$121, 11, FALSE) - 1, "N/A") -> N/A | I39: =IFS(D39="Sell to Close", F39*E39*1, D39="Sell to Trim", F39*E39*1, D39="Buy to Add", F39*E39*-1, D39="Buy to Open", F39*E39*-1) -> -4048.33
A40: CVX | B40: =IFERROR(__xludf.DUMMYFUNCTION("GOOGLEFINANCE(A40,""NAME"")"),"Chevron Corp") -> Chevron Corp | C40: Quant | D40: Buy to Open | E40: 22 | F40: 179.27 | G40: 46058 | H40: =IF(OR(D40="Sell to Trim", D40="Sell to Close"),F40/VLOOKUP(A40, 'Sector Holdings'!$B$3:$M$121, 11, FALSE) - 1, "N/A") -> N/A | I40: =IFS(D40="Sell to Close", F40*E40*1, D40="Sell to Trim", F40*E40*1, D40="Buy to Add", F40*E40*-1, D40="Buy to Open", F40*E40*-1) -> -3943.94
A41: CHRD | B41: =IFERROR(__xludf.DUMMYFUNCTION("GOOGLEFINANCE(A41,""NAME"")"),"Chord Energy Corp") -> Chord Energy Corp | C41: Energy | D41: Sell to Close | E41: 206 | F41: 100.98 | G41: 46063 | H41: =IF(OR(D41="Sell to Trim", D41="Sell to Close"),F41/VLOOKUP(A41, 'Sector Holdings'!$B$3:$M$121, 11, FALSE) - 1, "N/A") -> #N/A | I41: =IFS(D41="Sell to Close", F41*E41*1, D41="Sell to Trim", F41*E41*1, D41="Buy to Add", F41*E41*-1, D41="Buy to Open", F41*E41*-1) -> 20801.88
A42: EHMEF | B42: =IFERROR(__xludf.DUMMYFUNCTION("GOOGLEFINANCE(A42,""NAME"")"),"goeasy Ltd") -> goeasy Ltd | C42: Financials | D42: Sell to Close | E42: 226 | F42: 97.05 | G42: 46063 | H42: =IF(OR(D42="Sell to Trim", D42="Sell to Close"),F42/VLOOKUP(A42, 'Sector Holdings'!$B$3:$M$121, 11, FALSE) - 1, "N/A") -> #N/A | I42: =IFS(D42="Sell to Close", F42*E42*1, D42="Sell to Trim", F42*E42*1, D42="Buy to Add", F42*E42*-1, D42="Buy to Open", F42*E42*-1) -> 21933.3
A43: ADBE | B43: =IFERROR(__xludf.DUMMYFUNCTION("GOOGLEFINANCE(A43,""NAME"")"),"Adobe Inc") -> Adobe Inc | C43: Technology | D43: Sell to Close | E43: 117 | F43: 268.56 | G43: 46063 | H43: =IF(OR(D43="Sell to Trim", D43="Sell to Close"),F43/VLOOKUP(A43, 'Sector Holdings'!$B$3:$M$121, 11, FALSE) - 1, "N/A") -> #N/A | I43: =IFS(D43="Sell to Close", F43*E43*1, D43="Sell to Trim", F43*E43*1, D43="Buy to Add", F43*E43*-1, D43="Buy to Open", F43*E43*-1) -> 31421.52
A44: SPGI | B44: =IFERROR(__xludf.DUMMYFUNCTION("GOOGLEFINANCE(A44,""NAME"")"),"S&P Global Inc") -> S&P Global Inc | C44: Financials | D44: Buy to Add | E44: 43 | F44: 418.74 | G44: 46063 | H44: =IF(OR(D44="Sell to Trim", D44="Sell to Close"),F44/VLOOKUP(A44, 'Sector Holdings'!$B$3:$M$121, 11, FALSE) - 1, "N/A") -> N/A | I44: =IFS(D44="Sell to Close", F44*E44*1, D44="Sell to Trim", F44*E44*1, D44="Buy to Add", F44*E44*-1, D44="Buy to Open", F44*E44*-1) -> -18005.82
A45: SNEX | B45: =IFERROR(__xludf.DUMMYFUNCTION("GOOGLEFINANCE(A45,""NAME"")"),"Stonex Group Inc") -> Stonex Group Inc | C45: Financials | D45: Buy to Add | E45: 70 | F45: 122.74 | G45: 46063 | H45: =IF(OR(D45="Sell to Trim", D45="Sell to Close"),F45/VLOOKUP(A45, 'Sector Holdings'!$B$3:$M$121, 11, FALSE) - 1, "N/A") -> N/A | I45: =IFS(D45="Sell to Close", F45*E45*1, D45="Sell to Trim", F45*E45*1, D45="Buy to Add", F45*E45*-1, D45="Buy to Open", F45*E45*-1) -> -8591.8
A46: GOOGL | B46: =IFERROR(__xludf.DUMMYFUNCTION("GOOGLEFINANCE(A46,""NAME"")"),"Alphabet Inc Class A") -> Alphabet Inc Class A | C46: Technology | D46: Buy to Add | E46: 15 | F46: 317.95 | G46: 46063 | H46: =IF(OR(D46="Sell to Trim", D46="Sell to Close"),F46/VLOOKUP(A46, 'Sector Holdings'!$B$3:$M$121, 11, FALSE) - 1, "N/A") -> N/A | I46: =IFS(D46="Sell to Close", F46*E46*1, D46="Sell to Trim", F46*E46*1, D46="Buy to Add", F46*E46*-1, D46="Buy to Open", F46*E46*-1) -> -4769.25
A47: MSFT | B47: =IFERROR(__xludf.DUMMYFUNCTION("GOOGLEFINANCE(A47,""NAME"")"),"Microsoft Corp") -> Microsoft Corp | C47: Technology | D47: Buy to Add | E47: 14 | F47: 420.25 | G47: 46063 | H47: =IF(OR(D47="Sell to Trim", D47="Sell to Close"),F47/VLOOKUP(A47, 'Sector Holdings'!$B$3:$M$121, 11, FALSE) - 1, "N/A") -> N/A | I47: =IFS(D47="Sell to Close", F47*E47*1, D47="Sell to Trim", F47*E47*1, D47="Buy to Add", F47*E47*-1, D47="Buy to Open", F47*E47*-1) -> -5883.5
A48: TSM | B48: =IFERROR(__xludf.DUMMYFUNCTION("GOOGLEFINANCE(A48,""NAME"")"),"Taiwan Semicndctr Mnufctrng Co Ltd") -> Taiwan Semicndctr Mnufctrng Co Ltd | C48: Technology | D48: Buy to Add | E48: 66 | F48: 360.24 | G48: 46063 | H48: =IF(OR(D48="Sell to Trim", D48="Sell to Close"),F48/VLOOKUP(A48, 'Sector Holdings'!$B$3:$M$121, 11, FALSE) - 1, "N/A") -> N/A | I48: =IFS(D48="Sell to Close", F48*E48*1, D48="Sell to Trim", F48*E48*1, D48="Buy to Add", F48*E48*-1, D48="Buy to Open", F48*E48*-1) -> -23775.84
A49: LNG | B49: =IFERROR(__xludf.DUMMYFUNCTION("GOOGLEFINANCE(A49,""NAME"")"),"Cheniere Energy Inc") -> Cheniere Energy Inc | C49: Energy | D49: Sell to Trim | E49: 5 | F49: 217.5 | G49: 46063 | H49: =IF(OR(D49="Sell to Trim", D49="Sell to Close"),F49/VLOOKUP(A49, 'Sector Holdings'!$B$3:$M$121, 11, FALSE) - 1, "N/A") -> 2.3399877 | I49: =IFS(D49="Sell to Close", F49*E49*1, D49="Sell to Trim", F49*E49*1, D49="Buy to Add", F49*E49*-1, D49="Buy to Open", F49*E49*-1) -> 1087.5
A50: FLS | B50: =IFERROR(__xludf.DUMMYFUNCTION("GOOGLEFINANCE(A50,""NAME"")"),"Flowserve Corp") -> Flowserve Corp | C50: Industrials | D50: Buy to Open | E50: 241 | F50: 89.49 | G50: 46066 | H50: =IF(OR(D50="Sell to Trim", D50="Sell to Close"),F50/VLOOKUP(A50, 'Sector Holdings'!$B$3:$M$121, 11, FALSE) - 1, "N/A") -> N/A | I50: =IFS(D50="Sell to Close", F50*E50*1, D50="Sell to Trim", F50*E50*1, D50="Buy to Add", F50*E50*-1, D50="Buy to Open", F50*E50*-1) -> -21567.09
A51: GE | B51: =IFERROR(__xludf.DUMMYFUNCTION("GOOGLEFINANCE(A51,""NAME"")"),"General Electric Co") -> General Electric Co | C51: Industrials | D51: Sell to Trim | E51: 103 | F51: 328.64 | G51: 46070 | H51: =IF(OR(D51="Sell to Trim", D51="Sell to Close"),F51/VLOOKUP(A51, 'Sector Holdings'!$B$3:$M$121, 11, FALSE) - 1, "N/A") -> 1.1269607 | I51: =IFS(D51="Sell to Close", F51*E51*1, D51="Sell to Trim", F51*E51*1, D51="Buy to Add", F51*E51*-1, D51="Buy to Open", F51*E51*-1) -> 33849.92
A52: FLS | B52: =IFERROR(__xludf.DUMMYFUNCTION("GOOGLEFINANCE(A52,""NAME"")"),"Flowserve Corp") -> Flowserve Corp | C52: Industrials | D52: Buy to Add | E52: 54 | F52: 89.92 | G52: 46071 | H52: =IF(OR(D52="Sell to Trim", D52="Sell to Close"),F52/VLOOKUP(A52, 'Sector Holdings'!$B$3:$M$121, 11, FALSE) - 1, "N/A") -> N/A | I52: =IFS(D52="Sell to Close", F52*E52*1, D52="Sell to Trim", F52*E52*1, D52="Buy to Add", F52*E52*-1, D52="Buy to Open", F52*E52*-1) -> -4855.68
B99: =IFERROR(VLOOKUP($A99, 'Sector Holdings'!$B$3:$C$130, 2, FALSE),"N/A") -> N/A | H99: =IF(OR(D99="Sell to Trim", D99="Sell to Close"),F99/VLOOKUP(A99, 'Sector Holdings'!$B$3:$M$121, 11, FALSE) - 1, "N/A") -> N/A | I99: =F99*E99*-1 -> 0
B100: =IFERROR(VLOOKUP($A100, 'Sector Holdings'!$B$3:$C$130, 2, FALSE),"N/A") -> N/A | H100: =IF(OR(D100="Sell to Trim", D100="Sell to Close"),F100/VLOOKUP(A100, 'Sector Holdings'!$B$3:$M$121, 11, FALSE) - 1, "N/A") -> N/A | I100: =F100*E100*-1 -> 0
B167: =IFERROR(VLOOKUP($A167, 'Sector Holdings'!$B$3:$C$130, 2, FALSE),"N/A") -> N/A | H167: =IF(OR(D167="Sell to Trim", D167="Sell to Close"),F167/VLOOKUP(A167, 'Sector Holdings'!$B$3:$M$121, 11, FALSE) - 1, "N/A") -> N/A | I167: =F167*E167*-1 -> 0

Sheet Fall 2025 Trades
A1: SSF | B1: Description | C1: Sector | D1: Trade Type | E1: Shares | F1: Trade Price | G1: Trade Date | H1: % Gain on Sale | I1: Cash Gain/Loss
A2: PM | B2: =IFERROR(__xludf.DUMMYFUNCTION("GOOGLEFINANCE(A2,""NAME"")"),"Philip Morris International Inc.") -> Philip Morris International Inc. | C2: Consumer Staples | D2: Sell to Trim | E2: -21 | F2: 165.87 | G2: 45898 | H2: =IF(OR(D2="Sell to Trim", D2="Sell to Close"),F2/VLOOKUP(A2, 'Sector Holdings'!$B$3:$M$121, 11, FALSE) - 1, "N/A") -> 0.83018868 | I2: =F2*E2*-1 -> 3483.27
A3: SFM | B3: =IFERROR(__xludf.DUMMYFUNCTION("GOOGLEFINANCE(A3,""NAME"")"),"Sprouts Farmers Market Inc") -> Sprouts Farmers Market Inc | C3: Consumer Staples | D3: Sell to Trim | E3: -26 | F3: 140 | G3: 45898 | H3: =IF(OR(D3="Sell to Trim", D3="Sell to Close"),F3/VLOOKUP(A3, 'Sector Holdings'!$B$3:$M$121, 11, FALSE) - 1, "N/A") -> 2.2414911 | I3: =F3*E3*-1 -> 3640
A4: CEG | B4: =IFERROR(__xludf.DUMMYFUNCTION("GOOGLEFINANCE(A4,""NAME"")"),"Constellation Energy Corp") -> Constellation Energy Corp | C4: Energy | D4: Sell to Trim | E4: -4 | F4: 307 | G4: 45898 | H4: =IF(OR(D4="Sell to Trim", D4="Sell to Close"),F4/VLOOKUP(A4, 'Sector Holdings'!$B$3:$M$121, 11, FALSE) - 1, "N/A") -> 2.4614951 | I4: =F4*E4*-1 -> 1228
A5: FANG | B5: =IFERROR(__xludf.DUMMYFUNCTION("GOOGLEFINANCE(A5,""NAME"")"),"Diamondback Energy Inc") -> Diamondback Energy Inc | C5: Energy | D5: Buy to Add | E5: 11 | F5: 149.03 | G5: 45898 | H5: =IF(OR(D5="Sell to Trim", D5="Sell to Close"),F5/VLOOKUP(A5, 'Sector Holdings'!$B$3:$M$121, 11, FALSE) - 1, "N/A") -> N/A | I5: =F5*E5*-1 -> -1639.33
A6: LNG | B6: =IFERROR(__xludf.DUMMYFUNCTION("GOOGLEFINANCE(A6,""NAME"")"),"Cheniere Energy Inc") -> Cheniere Energy Inc | C6: Energy | D6: Buy to Add | E6: 8 | F6: 243.26 | G6: 45898 | H6: =IF(OR(D6="Sell to Trim", D6="Sell to Close"),F6/VLOOKUP(A6, 'Sector Holdings'!$B$3:$M$121, 11, FALSE) - 1, "N/A") -> N/A | I6: =F6*E6*-1 -> -1946.08
A7: FISV | B7: =IFERROR(__xludf.DUMMYFUNCTION("GOOGLEFINANCE(A7,""NAME"")"),"Fiserv Inc") -> Fiserv Inc | C7: Financials | D7: Buy to Add | E7: 13 | F7: 138 | G7: 45898 | H7: =IF(OR(D7="Sell to Trim", D7="Sell to Close"),F7/VLOOKUP(A7, 'Sector Holdings'!$B$3:$M$121, 11, FALSE) - 1, "N/A") -> N/A | I7: =F7*E7*-1 -> -1794
A8: ALC | B8: =IFERROR(__xludf.DUMMYFUNCTION("GOOGLEFINANCE(A8,""NAME"")"),"Alcon AG") -> Alcon AG | C8: Healthcare | D8: Buy to Add | E8: 62 | F8: 80.06 | G8: 45898 | H8: =IF(OR(D8="Sell to Trim", D8="Sell to Close"),G8/VLOOKUP(A8, 'Sector Holdings'!$B$3:$M$121, 11, FALSE) - 1, "N/A") -> N/A | I8: =F8*E8*-1 -> -4963.72
A9: RPRX | B9: =IFERROR(__xludf.DUMMYFUNCTION("GOOGLEFINANCE(A9,""NAME"")"),"Royalty Pharma plc") -> Royalty Pharma plc | C9: Healthcare | D9: Buy to Add | E9: 141 | F9: 35.84 | G9: 45898 | H9: =IF(OR(D9="Sell to Trim", D9="Sell to Close"),F9/VLOOKUP(A9, 'Sector Holdings'!$B$3:$M$121, 11, FALSE) - 1, "N/A") -> N/A | I9: =F9*E9*-1 -> -5053.44
A10: TMO | B10: =IFERROR(__xludf.DUMMYFUNCTION("GOOGLEFINANCE(A10,""NAME"")"),"Thermo Fisher Scientific Inc") -> Thermo Fisher Scientific Inc | C10: Healthcare | D10: Buy to Add | E10: 10 | F10: 493.35 | G10: 45898 | H10: =IF(OR(D10="Sell to Trim", D10="Sell to Close"),F10/VLOOKUP(A10, 'Sector Holdings'!$B$3:$M$121, 11, FALSE) - 1, "N/A") -> N/A | I10: =F10*E10*-1 -> -4933.5
A11: UNH | B11: =IFERROR(__xludf.DUMMYFUNCTION("GOOGLEFINANCE(A11,""NAME"")"),"UnitedHealth Group Inc") -> UnitedHealth Group Inc | C11: Healthcare | D11: Buy to Add | E11: 16 | F11: 305.44 | G11: 45898 | H11: =IF(OR(D11="Sell to Trim", D11="Sell to Close"),F11/VLOOKUP(A11, 'Sector Holdings'!$B$3:$M$121, 11, FALSE) - 1, "N/A") -> N/A | I11: =F11*E11*-1 -> -4887.04
A12: VEEV | B12: =IFERROR(__xludf.DUMMYFUNCTION("GOOGLEFINANCE(A12,""NAME"")"),"Veeva Systems Inc") -> Veeva Systems Inc | C12: Healthcare | D12: Buy to Add | E12: 19 | F12: 267.6 | G12: 45898 | H12: =IF(OR(D12="Sell to Trim", D12="Sell to Close"),F12/VLOOKUP(A12, 'Sector Holdings'!$B$3:$M$121, 11, FALSE) - 1, "N/A") -> N/A | I12: =F12*E12*-1 -> -5084.4
A13: APD | B13: =IFERROR(__xludf.DUMMYFUNCTION("GOOGLEFINANCE(A13,""NAME"")"),"Air Products and Chemicals Inc") -> Air Products and Chemicals Inc | C13: Industrials | D13: Sell to Trim | E13: -36 | F13: 294.15 | G13: 45898 | H13: =IF(OR(D13="Sell to Trim", D13="Sell to Close"),F13/VLOOKUP(A13, 'Sector Holdings'!$B$3:$M$121, 11, FALSE) - 1, "N/A") -> 0.25899578 | I13: =F13*E13*-1 -> 10589.4
A14: GE | B14: =IFERROR(__xludf.DUMMYFUNCTION("GOOGLEFINANCE(A14,""NAME"")"),"General Electric Co") -> General Electric Co | C14: Industrials | D14: Sell to Trim | E14: -13 | F14: 274.68 | G14: 45898 | H14: =IF(OR(D14="Sell to Trim", D14="Sell to Close"),F14/VLOOKUP(A14, 'Sector Holdings'!$B$3:$M$121, 11, FALSE) - 1, "N/A") -> 0.77773112 | I14: =F14*E14*-1 -> 3570.84
A15: URI | B15: =IFERROR(__xludf.DUMMYFUNCTION("GOOGLEFINANCE(A15,""NAME"")"),"United Rentals Inc") -> United Rentals Inc | C15: Industrials | D15: Sell to Trim | E15: -3 | F15: 952.2 | G15: 45898 | H15: =IF(OR(D15="Sell to Trim", D15="Sell to Close"),F15/VLOOKUP(A15, 'Sector Holdings'!$B$3:$M$121, 11, FALSE) - 1, "N/A") -> #N/A | I15: =F15*E15*-1 -> 2856.6
A16: LYV | B16: =IFERROR(__xludf.DUMMYFUNCTION("GOOGLEFINANCE(A16,""NAME"")"),"Live Nation Entertainment Inc") -> Live Nation Entertainment Inc | C16: Media & Telecom | D16: Sell to Trim | E16: -41 | F16: 166.48 | G16: 45898 | H16: =IF(OR(D16="Sell to Trim", D16="Sell to Close"),F16/VLOOKUP(A16, 'Sector Holdings'!$B$3:$M$121, 11, FALSE) - 1, "N/A") -> 0.97297938 | I16: =F16*E16*-1 -> 6825.68
A17: SNPS | B17: =IFERROR(__xludf.DUMMYFUNCTION("GOOGLEFINANCE(A17,""NAME"")"),"Synopsys Inc") -> Synopsys Inc | C17: Technology | D17: Buy to Add | E17: 5 | F17: 602.65 | G17: 45898 | H17: =IF(OR(D17="Sell to Trim", D17="Sell to Close"),F17/VLOOKUP(A17, 'Sector Holdings'!$B$3:$M$121, 11, FALSE) - 1, "N/A") -> N/A | I17: =F17*E17*-1 -> -3013.25
A18: NEE | B18: =IFERROR(__xludf.DUMMYFUNCTION("GOOGLEFINANCE(A18,""NAME"")"),"NextEra Energy Inc") -> NextEra Energy Inc | C18: Utilities | D18: Sell to Trim | E18: -17 | F18: 72.18 | G18: 45898 | H18: =IF(OR(D18="Sell to Trim", D18="Sell to Close"),F18/VLOOKUP(A18, 'Sector Holdings'!$B$3:$M$121, 11, FALSE) - 1, "N/A") -> 0.60542705 | I18: =F18*E18*-1 -> 1227.06
A19: VST | B19: =IFERROR(__xludf.DUMMYFUNCTION("GOOGLEFINANCE(A19,""NAME"")"),"Vistra Corp") -> Vistra Corp | C19: Utilities | D19: Sell to Trim | E19: -6 | F19: 187.43 | G19: 45898 | H19: =IF(OR(D19="Sell to Trim", D19="Sell to Close"),F19/VLOOKUP(A19, 'Sector Holdings'!$B$3:$M$121, 11, FALSE) - 1, "N/A") -> 4.2150807 | I19: =F19*E19*-1 -> 1124.58
A20: 37045VAF7 | B20: GM | C20: Fixed Income | D20: Buy to Open | E20: 25 | F20: 102.074 | G20: 45929 | H20: =IF(OR(D20="Sell to Trim", D20="Sell to Close"),F20/VLOOKUP(A20, 'Sector Holdings'!$B$3:$M$121, 11, FALSE) - 1, "N/A") -> N/A | I20: =F20*E20*-1 -> -2551.85
A21: URI | B21: =IFERROR(__xludf.DUMMYFUNCTION("GOOGLEFINANCE(A21,""NAME"")"),"United Rentals Inc") -> United Rentals Inc | C21: Industrials | D21: Sell to Close | E21: -83 | F21: 943.4 | G21: 45929 | H21: =IF(OR(D21="Sell to Trim", D21="Sell to Close"),F21/VLOOKUP(A21, 'Sector Holdings'!$B$3:$M$121, 11, FALSE) - 1, "N/A") -> #N/A | I21: =F21*E21*-1 -> 78302.2
A22: GOOGL | B22: =IFERROR(__xludf.DUMMYFUNCTION("GOOGLEFINANCE(A22,""NAME"")"),"Alphabet Inc Class A") -> Alphabet Inc Class A | C22: Technology | D22: Sell to Trim | E22: -106 | F22: 248.08 | G22: 45929 | H22: =IF(OR(D22="Sell to Trim", D22="Sell to Close"),F22/VLOOKUP(A22, 'Sector Holdings'!$B$3:$M$121, 11, FALSE) - 1, "N/A") -> 3.2092272 | I22: =F22*E22*-1 -> 26296.48
A23: TSM | B23: =IFERROR(__xludf.DUMMYFUNCTION("GOOGLEFINANCE(A23,""NAME"")"),"Taiwan Semicndctr Mnufctrng Co Ltd") -> Taiwan Semicndctr Mnufctrng Co Ltd | C23: Technology | D23: Buy to Open | E23: 97 | F23: 275.55 | G23: 45929 | H23: =IF(OR(D23="Sell to Trim", D23="Sell to Close"),F23/VLOOKUP(A23, 'Sector Holdings'!$B$3:$M$121, 11, FALSE) - 1, "N/A") -> N/A | I23: =F23*E23*-1 -> -26728.35
A24: VEEV | B24: =IFERROR(__xludf.DUMMYFUNCTION("GOOGLEFINANCE(A24,""NAME"")"),"Veeva Systems Inc") -> Veeva Systems Inc | C24: Healthcare | D24: Sell to Trim | E24: -27 | F24: 302.44 | G24: 45938 | H24: =IF(OR(D24="Sell to Trim", D24="Sell to Close"),F24/VLOOKUP(A24, 'Sector Holdings'!$B$3:$M$121, 11, FALSE) - 1, "N/A") -> 0.67047777 | I24: =F24*E24*-1 -> 8165.88
A25: ALC | B25: =IFERROR(__xludf.DUMMYFUNCTION("GOOGLEFINANCE(A25,""NAME"")"),"Alcon AG") -> Alcon AG | C25: Healthcare | D25: Sell to Trim | E25: -176 | F25: 76.57 | G25: 45938 | H25: =IF(OR(D25="Sell to Trim", D25="Sell to Close"),F25/VLOOKUP(A25, 'Sector Holdings'!$B$3:$M$121, 11, FALSE) - 1, "N/A") -> #N/A | I25: =F25*E25*-1 -> 13476.32
A26: UNH | B26: =IFERROR(__xludf.DUMMYFUNCTION("GOOGLEFINANCE(A26,""NAME"")"),"UnitedHealth Group Inc") -> UnitedHealth Group Inc | C26: Healthcare | D26: Buy to Add | E26: 55 | F26: 371.09 | G26: 45938 | H26: =IF(OR(D26="Sell to Trim", D26="Sell to Close"),F26/VLOOKUP(A26, 'Sector Holdings'!$B$3:$M$121, 11, FALSE) - 1, "N/A") -> N/A | I26: =F26*E26*-1 -> -20409.95
A27: AMRZ | B27: =IFERROR(__xludf.DUMMYFUNCTION("GOOGLEFINANCE(A27,""NAME"")"),"Amrize AG") -> Amrize AG | C27: Industrials | D27: Buy to Open | E27: 830 | F27: 48.7 | G27: 45950 | H27: =IF(OR(D27="Sell to Trim", D27="Sell to Close"),F27/VLOOKUP(A27, 'Sector Holdings'!$B$3:$M$121, 11, FALSE) - 1, "N/A") -> N/A | I27: =F27*E27*-1 -> -40421
A28: QCOM | B28: =IFERROR(__xludf.DUMMYFUNCTION("GOOGLEFINANCE(A28,""NAME"")"),"Qualcomm Inc") -> Qualcomm Inc | C28: Technology | D28: Sell to Close | E28: -193 | F28: 164.6 | G28: 45950 | H28: =IF(OR(D28="Sell to Trim", D28="Sell to Close"),F28/VLOOKUP(A28, 'Sector Holdings'!$B$3:$M$121, 11, FALSE) - 1, "N/A") -> #N/A | I28: =F28*E28*-1 -> 31767.8
A29: TSM | B29: =IFERROR(__xludf.DUMMYFUNCTION("GOOGLEFINANCE(A29,""NAME"")"),"Taiwan Semicndctr Mnufctrng Co Ltd") -> Taiwan Semicndctr Mnufctrng Co Ltd | C29: Technology | D29: Buy to Add | E29: 105 | F29: 301.85 | G29: 45950 | H29: =IF(OR(D29="Sell to Trim", D29="Sell to Close"),F29/VLOOKUP(A29, 'Sector Holdings'!$B$3:$M$121, 11, FALSE) - 1, "N/A") -> N/A | I29: =F29*E29*-1 -> -31694.25
A30: FI | B30: =IFERROR(__xludf.DUMMYFUNCTION("GOOGLEFINANCE(A30,""NAME"")"),"#N/A") -> #N/A | C30: Financials | D30: Buy to Add | E30: 120 | F30: 65.235 | G30: 45964 | H30: =IF(OR(D30="Sell to Trim", D30="Sell to Close"),F30/VLOOKUP(A30, 'Sector Holdings'!$B$3:$M$121, 11, FALSE) - 1, "N/A") -> N/A | I30: =F30*E30*-1 -> -7828.2
A31: NATL | B31: =IFERROR(__xludf.DUMMYFUNCTION("GOOGLEFINANCE(A31,""NAME"")"),"NCR Atleos Corp") -> NCR Atleos Corp | C31: Financials | D31: Buy to Open | E31: 910 | F31: 36.214 | G31: 45964 | H31: =IF(OR(D31="Sell to Trim", D31="Sell to Close"),F31/VLOOKUP(A31, 'Sector Holdings'!$B$3:$M$121, 11, FALSE) - 1, "N/A") -> N/A | I31: =F31*E31*-1 -> -32954.74
A32: ALC | B32: =IFERROR(__xludf.DUMMYFUNCTION("GOOGLEFINANCE(A32,""NAME"")"),"Alcon AG") -> Alcon AG | C32: Healthcare | D32: Sell to Close | E32: -292 | F32: 72.767 | G32: 45964 | H32: =IF(OR(D32="Sell to Trim", D32="Sell to Close"),F32/VLOOKUP(A32, 'Sector Holdings'!$B$3:$M$121, 11, FALSE) - 1, "N/A") -> #N/A | I32: =F32*E32*-1 -> 21247.964
A33: TMO | B33: =IFERROR(__xludf.DUMMYFUNCTION("GOOGLEFINANCE(A33,""NAME"")"),"Thermo Fisher Scientific Inc") -> Thermo Fisher Scientific Inc | C33: Healthcare | D33: Sell to Trim | E33: -9 | F33: 555.089 | G33: 45964 | H33: =IF(OR(D33="Sell to Trim", D33="Sell to Close"),F33/VLOOKUP(A33, 'Sector Holdings'!$B$3:$M$121, 11, FALSE) - 1, "N/A") -> 0.28196074 | I33: =F33*E33*-1 -> 4995.801
A34: MRK | B34: =IFERROR(__xludf.DUMMYFUNCTION("GOOGLEFINANCE(A34,""NAME"")"),"Merck & Co Inc") -> Merck & Co Inc | C34: Healthcare | D34: Buy to Open | E34: 315 | F34: 83.575 | G34: 45964 | H34: =IF(OR(D34="Sell to Trim", D34="Sell to Close"),F34/VLOOKUP(A34, 'Sector Holdings'!$B$3:$M$121, 11, FALSE) - 1, "N/A") -> N/A | I34: =F34*E34*-1 -> -26326.125
A35: SLB | B35: =IFERROR(__xludf.DUMMYFUNCTION("GOOGLEFINANCE(A35,""NAME"")"),"Slb NV") -> Slb NV | C35: Industrials | D35: Buy to Open | E35: 502 | F35: 36.685 | G35: 45964 | H35: =IF(OR(D35="Sell to Trim", D35="Sell to Close"),F35/VLOOKUP(A35, 'Sector Holdings'!$B$3:$M$121, 11, FALSE) - 1, "N/A") -> N/A | I35: =F35*E35*-1 -> -18415.87
A36: VICI | B36: =IFERROR(__xludf.DUMMYFUNCTION("GOOGLEFINANCE(A36,""NAME"")"),"VICI Properties Inc") -> VICI Properties Inc | C36: REITs | D36: Sell to Close | E36: -872 | F36: 30.14 | G36: 45968 | H36: =IF(OR(D36="Sell to Trim", D36="Sell to Close"),F36/VLOOKUP(A36, 'Sector Holdings'!$B$3:$M$121, 11, FALSE) - 1, "N/A") -> #N/A | I36: =F36*E36*-1 -> 26282.08
A37: PM | B37: =IFERROR(__xludf.DUMMYFUNCTION("GOOGLEFINANCE(A37,""NAME"")"),"Philip Morris International Inc.") -> Philip Morris International Inc. | C37: Consumer Staples | D37: Sell to Trim | E37: -190 | F37: 155.76 | G37: 45982 | H37: =IF(OR(D37="Sell to Trim", D37="Sell to Close"),F37/VLOOKUP(A37, 'Sector Holdings'!$B$3:$M$121, 11, FALSE) - 1, "N/A") -> 0.71863621 | I37: =F37*E37*-1 -> 29594.4
A38: POST | B38: =IFERROR(__xludf.DUMMYFUNCTION("GOOGLEFINANCE(A38,""NAME"")"),"Post Holdings Inc") -> Post Holdings Inc | C38: Consumer Staples | D38: Buy to Add | E38: 190 | F38: 102.26 | G38: 45982 | H38: =IF(OR(D38="Sell to Trim", D38="Sell to Close"),F38/VLOOKUP(A38, 'Sector Holdings'!$B$3:$M$121, 11, FALSE) - 1, "N/A") -> N/A | I38: =F38*E38*-1 -> -19429.4
A39: SFM | B39: =IFERROR(__xludf.DUMMYFUNCTION("GOOGLEFINANCE(A39,""NAME"")"),"Sprouts Farmers Market Inc") -> Sprouts Farmers Market Inc | C39: Consumer Staples | D39: Buy to Add | E39: 240 | F39: 82.38 | G39: 45982 | H39: =IF(OR(D39="Sell to Trim", D39="Sell to Close"),F39/VLOOKUP(A39, 'Sector Holdings'!$B$3:$M$121, 11, FALSE) - 1, "N/A") -> N/A | I39: =F39*E39*-1 -> -19771.2
A40: Bond CUSIP | B40: Macys | C40: Fixed Income | D40: Buy to Open | E40: 20 | F40: =20059.8/200 -> 100.299 | G40: 45982 | H40: =IF(OR(D40="Sell to Trim", D40="Sell to Close"),F40/VLOOKUP(A40, 'Sector Holdings'!$B$3:$M$121, 11, FALSE) - 1, "N/A") -> N/A | I40: =F40*E40*-1 -> -2005.98
A41: GOOGL | B41: =IFERROR(__xludf.DUMMYFUNCTION("GOOGLEFINANCE(A41,""NAME"")"),"Alphabet Inc Class A") -> Alphabet Inc Class A | C41: Technology | D41: Sell to Trim | E41: -75 | F41: 301.89 | G41: 45982 | H41: =IF(OR(D41="Sell to Trim", D41="Sell to Close"),F41/VLOOKUP(A41, 'Sector Holdings'!$B$3:$M$121, 11, FALSE) - 1, "N/A") -> 4.1222332 | I41: =F41*E41*-1 -> 22641.75
A42: NICE | B42: =IFERROR(__xludf.DUMMYFUNCTION("GOOGLEFINANCE(A42,""NAME"")"),"Nice Ltd") -> Nice Ltd | C42: Technology | D42: Sell to Close | E42: -180 | F42: 104.28 | G42: 45982 | H42: =IF(OR(D42="Sell to Trim", D42="Sell to Close"),F42/VLOOKUP(A42, 'Sector Holdings'!$B$3:$M$121, 11, FALSE) - 1, "N/A") -> #N/A | I42: =F42*E42*-1 -> 18770.4
A43: SNPS | B43: =IFERROR(__xludf.DUMMYFUNCTION("GOOGLEFINANCE(A43,""NAME"")"),"Synopsys Inc") -> Synopsys Inc | C43: Technology | D43: Buy to Add | E43: 50 | F43: 388.85 | G43: 45982 | H43: =IF(OR(D43="Sell to Trim", D43="Sell to Close"),F43/VLOOKUP(A43, 'Sector Holdings'!$B$3:$M$121, 11, FALSE) - 1, "N/A") -> N/A | I43: =F43*E43*-1 -> -19442.5
A44: TSM | B44: =IFERROR(__xludf.DUMMYFUNCTION("GOOGLEFINANCE(A44,""NAME"")"),"Taiwan Semicndctr Mnufctrng Co Ltd") -> Taiwan Semicndctr Mnufctrng Co Ltd | C44: Technology | D44: Buy to Add | E44: 75 | F44: 276.65 | G44: 45982 | H44: =IF(OR(D44="Sell to Trim", D44="Sell to Close"),F44/VLOOKUP(A44, 'Sector Holdings'!$B$3:$M$121, 11, FALSE) - 1, "N/A") -> N/A | I44: =F44*E44*-1 -> -20748.75
B100: =IFERROR(VLOOKUP($A100, 'Sector Holdings'!$B$3:$C$130, 2, FALSE),"N/A") -> N/A | H100: =IF(OR(D100="Sell to Trim", D100="Sell to Close"),F100/VLOOKUP(A100, 'Sector Holdings'!$B$3:$M$121, 11, FALSE) - 1, "N/A") -> N/A | I100: =F100*E100*-1 -> 0
B101: =IFERROR(VLOOKUP($A101, 'Sector Holdings'!$B$3:$C$130, 2, FALSE),"N/A") -> N/A | H101: =IF(OR(D101="Sell to Trim", D101="Sell to Close"),F101/VLOOKUP(A101, 'Sector Holdings'!$B$3:$M$121, 11, FALSE) - 1, "N/A") -> N/A | I101: =F101*E101*-1 -> 0
B168: =IFERROR(VLOOKUP($A168, 'Sector Holdings'!$B$3:$C$130, 2, FALSE),"N/A") -> N/A | H168: =IF(OR(D168="Sell to Trim", D168="Sell to Close"),F168/VLOOKUP(A168, 'Sector Holdings'!$B$3:$M$121, 11, FALSE) - 1, "N/A") -> N/A | I168: =F168*E168*-1 -> 0

Sheet Spring 2025 Trades
A1: SSF | B1: Description | C1: Sector | D1: Trade Type | E1: Shares | F1: Trade Price | G1: Trade Date | H1: % Gain on Sale | I1: Cash Gain/Loss
A2: 71654QBV3 | B2: Pemex 4.25 01/15/25 | C2: Fixed Income | D2: Matured | E2: -30 | F2: 1000 | G2: 45672 | H2: 0.03609 | I2: =F2*E2*-1 -> 30000
A3: AMZN | B3: Amazon.com Inc | C3: Consumer Discretionary | D3: Buy to Add | E3: 33 | F3: 238.165 | G3: 45691 | H3: N/A | I3: =F3*E3*-1 -> -7859.445
A4: EVVTY | B4: Evolution ADR | C4: Consumer Discretionary | D4: Buy to Add | E4: 103 | F4: 75.2 | G4: 45691 | H4: N/A | I4: =F4*E4*-1 -> -7745.6
A5: SFM | B5: Sprouts Farmers Market Inc. | C5: Consumer Staples | D5: Sell to Trim | E5: -80 | F5: 161.15 | G5: 45691 | H5: 2.7311878 | I5: =F5*E5*-1 -> 12892
A6: SNEX | B6: Stonex Group Inc | C6: Financials | D6: Buy to Add | E6: 71 | F6: 109.105 | G6: 45691 | H6: N/A | I6: =F6*E6*-1 -> -7746.455
A7: SPGI | B7: S&P Global Inc | C7: Financials | D7: Buy to Add | E7: 15 | F7: 517.74533 | G7: 45691 | H7: N/A | I7: =F7*E7*-1 -> -7766.18
A8: UNH | B8: UnitedHealth Group Inc | C8: Healthcare | D8: Buy to Add | E8: 19 | F8: 549.55 | G8: 45691 | H8: N/A | I8: =F8*E8*-1 -> -10441.45
A9: RPRX | B9: Royalty Pharma plc | C9: Healthcare | D9: Buy to Add | E9: 327 | F9: 31.469924 | G9: 45691 | H9: N/A | I9: =F9*E9*-1 -> -10290.665
A10: LYV | B10: Live Nation Entertainment Inc | C10: Media and Telecomm | D10: Sell to Trim | E10: -172 | F10: 145 | G10: 45691 | H10: 0.71841669 | I10: =F10*E10*-1 -> 24940
A11: APP | B11: Applovin Corp | C11: Technology | D11: Sell to Trim | E11: -71 | F11: 368.14873 | G11: 45691 | H11: 1.9116577 | I11: =F11*E11*-1 -> 26138.56
A12: CEG | B12: Constellation Energy Corp | C12: Utilities | D12: Sell to Trim | E12: -42 | F12: 304.08095 | G12: 45691 | H12: 2.4285822 | I12: =F12*E12*-1 -> 12771.4
A13: VST | B13: Vistra Corp | C13: Utilities | D13: Sell to Trim | E13: -75 | F13: 170 | G13: 45691 | H13: 3.7301057 | I13: =F13*E13*-1 -> 12750
A14: PHM | B14: ='Sector Holdings'!C91 -> Texas Pacific Land Corp | C14: Quant | D14: Buy to Add | E14: 3 | F14: 111.545 | G14: 45693 | H14: N/A | I14: =F14*E14*-1 -> -334.635
A15: CMCSA | B15: Comcast Corp | C15: Quant | D15: Buy to Add | E15: 30 | F15: 33.92 | G15: 45693 | H15: N/A | I15: =F15*E15*-1 -> -1017.6
A16: CMG | B16: Chipotle Mexican Grill Inc | C16: Quant | D16: Buy to Open | E16: 75 | F16: 57.1993 | G16: 45693 | H16: N/A | I16: =F16*E16*-1 -> -4289.9475
A17: CVX | B17: Chevron Corp | C17: Quant | D17: Buy to Open | E17: 28 | F17: 153.32 | G17: 45693 | H17: N/A | I17: =F17*E17*-1 -> -4292.96
A18: APH | B18: Amphenol Corp | C18: Quant | D18: Buy to Open | E18: 62 | F18: 69.57 | G18: 45693 | H18: N/A | I18: =F18*E18*-1 -> -4313.34
A19: CVS | B19: CVS Health Corp | C19: Quant | D19: Buy to Open | E19: 93 | F19: 55.2893 | G19: 45693 | H19: N/A | I19: =F19*E19*-1 -> -5141.9049
A20: IVZ | B20: Invesco LTD | C20: Quant | D20: Buy to Open | E20: 275 | F20: 18.755 | G20: 45693 | H20: N/A | I20: =F20*E20*-1 -> -5157.625
A21: WFC | B21: Wells Fargo & Co | C21: Quant | D21: Buy to Open | E21: 64 | F21: 80.035 | G21: 45693 | H21: N/A | I21: =F21*E21*-1 -> -5122.24
A22: FOX | B22: FOX Corp | C22: Quant | D22: Buy to Open | E22: 100 | F22: 51.26 | G22: 45693 | H22: N/A | I22: =F22*E22*-1 -> -5126
A23: MOS | B23: Mosaic Co | C23: Quant | D23: Buy to Open | E23: 183 | F23: 28.19 | G23: 45693 | H23: N/A | I23: =F23*E23*-1 -> -5158.77
A24: COP | B24: ConocoPhillips (Acquired MRO) | C24: Quant | D24: Sell to Close | E24: -39 | F24: 100.17 | G24: 45693 | H24: -0.0083160083 | I24: =F24*E24*-1 -> 3906.63
A25: MPC | B25: Marathon Petroleum Corp | C25: Quant | D25: Sell to Close | E25: -22 | F25: 157.5417 | G25: 45693 | H25: -0.25880169 | I25: =F25*E25*-1 -> 3465.9174
A26: STLD | B26: Steel Dynamics Inc | C26: Quant | D26: Sell to Close | E26: -32 | F26: 128.73 | G26: 45693 | H26: =(F26-'Sector Holdings'!L85)/'Sector Holdings'!L85 -> 7.9895251 | I26: =F26*E26*-1 -> 4119.36
A27: HAS | B27: Hasbro Inc | C27: Quant | D27: Sell to Close | E27: -81 | F27: 58.885 | G27: 45693 | H27: =(F27-'Sector Holdings'!L86)/'Sector Holdings'!L86 -> 1.1672801 | I27: =F27*E27*-1 -> 4769.685
A28: MAR | B28: Marriott International Inc | C28: Quant | D28: Sell to Close | E28: -15 | F28: 292.2537 | G28: 45693 | H28: =(F28-'Sector Holdings'!L90)/'Sector Holdings'!L90 -> 6.5168133 | I28: =F28*E28*-1 -> 4383.8055
A29: GM | B29: ='Sector Holdings'!C92 -> Monolithic Power Systems Inc | C29: Quant | D29: Sell to Close | E29: -87 | F29: 48.435 | G29: 45693 | H29: =(F29-'Sector Holdings'!L92)/'Sector Holdings'!L92 -> -0.95859195 | I29: =F29*E29*-1 -> 4213.845
A30: LW | B30: ='Sector Holdings'!C93 -> Pultegroup Inc | C30: Quant | D30: Sell to Close | E30: -49 | F30: 58.56 | G30: 45693 | H30: =(F30-'Sector Holdings'!L93)/'Sector Holdings'!L93 -> -0.56207 | I30: =F30*E30*-1 -> 2869.44
A31: 446413BA3 | B31: HII Corp 5.353 1/15/30 | C31: Fixed Income | D31: Buy to Open | E31: 33 | F31: 99.326 | G31: 45700 | H31: N/A | I31: -3277.758
A32: NICE | B32: Nice Ltd | C32: Technology | D32: Buy to Add | E32: 24 | F32: 172.29 | G32: 45700 | H32: N/A | I32: -4134.96
A33: ADBE | B33: Adobe Inc. | C33: Technology | D33: Buy to Add | E33: 7 | F33: 461.33 | G33: 45700 | H33: N/A | I33: -3229.31
A34: GOOGL | B34: Alphabet Inc | C34: Technology | D34: Buy to Add | E34: 144 | F34: 183.36667 | G34: 45700 | H34: N/A | I34: -26404.8
A35: SNPS | B35: Synopsys Inc. | C35: Technology | D35: Buy to Add | E35: 17 | F35: 512.53 | G35: 45700 | H35: N/A | I35: -8713.01
A36: AMAT | B36: Applied Materials, Inc. | C36: Technology | D36: Buy to Add | E36: 38 | F36: 180.8686 | G36: 45700 | H36: N/A | I36: -6873.0068
A37: MSFT | B37: Microsoft Corp | C37: Technology | D37: Buy to Add | E37: 29 | F37: 409.375 | G37: 45700 | H37: N/A | I37: -11871.875
A38: APP | B38: Applovin Corp | C38: Technology | D38: Sell to Close | E38: -163 | F38: 381.775 | G38: 45700 | H38: 2.0194163 | I38: 62229.325
A39: PHM | B39: PulteGroup Inc | C39: Quant | D39: Buy to Add | E39: 4 | F39: 106.13 | G39: 45721 | H39: N/A | I39: -424.52
A40: HSIC | B40: Henry Schein Inc | C40: Quant | D40: Buy to Open | E40: 62 | F40: 71.095 | G40: 45721 | H40: N/A | I40: -4407.89
A41: INCY | B41: Incyte Corp | C41: Quant | D41: Buy to Open | E41: 63 | F41: 69.65 | G41: 45721 | H41: N/A | I41: -4387.95
A42: XOM | B42: Exxon Mobile Corp | C42: Quant | D42: Buy to Open | E42: 42 | F42: 105.56048 | G42: 45721 | H42: N/A | I42: -2318.14
A43: MNST | B43: Monster Beverage Corp | C43: Quant | D43: Buy to Open | E43: 80 | F43: 55.25 | G43: 45721 | H43: N/A | I43: -4420
A44: TAP | B44: Molson Coors Beverage Co | C44: Quant | D44: Buy to Open | E44: 87 | F44: 59.85 | G44: 45721 | H44: N/A | I44: -5206.95
A45: EPAM | B45: EPAM Systems Inc | C45: Quant | D45: Buy to Open | E45: 22 | F45: 201.092 | G45: 45721 | H45: N/A | I45: -4424.024
A46: GL | B46: Globe Life Inc | C46: Quant | D46: Buy to Open | E46: 41 | F46: 126.46 | G46: 45721 | H46: N/A | I46: -5184.86
A47: MO | B47: Altria Group Inc | C47: Quant | D47: Buy to Open | E47: 93 | F47: 56.12 | G47: 45721 | H47: N/A | I47: -5219.16
A48: AOS | B48: A O Smith Corp | C48: Quant | D48: Sell to Close | E48: -65 | F48: 66.545 | G48: 45721 | H48: -0.16096698 | I48: 4325.425
A49: CMCSA | B49: Comcast Corp | C49: Quant | D49: Sell to Close | E49: -126 | F49: 35.56 | G49: 45721 | H49: -0.072854589 | I49: 4480.56
A50: APH | B50: Amphenol Corp | C50: Quant | D50: Sell to Close | E50: -62 | F50: 64.5 | G50: 45721 | H50: -0.07287624 | I50: 3999
A51: CVX | B51: Chevron Corp | C51: Quant | D51: Sell to Close | E51: -28 | F51: 150.7 | G51: 45721 | H51: -0.017088442 | I51: 4219.6
A52: CMG | B52: Chipotle Mexican Grill Inc | C52: Quant | D52: Sell to Close | E52: -75 | F52: 53.650333 | G52: 45721 | H52: -0.062045631 | I52: 4023.775
A53: MOS | B53: Mosaic Co | C53: Quant | D53: Sell to Close | E53: -183 | F53: 24.221 | G53: 45721 | H53: -0.14079461 | I53: 4432.443
A54: WFC | B54: Wells Fargo & Co | C54: Quant | D54: Sell to Close | E54: -64 | F54: 73.74 | G54: 45721 | H54: -0.078653089 | I54: 4719.36
A55: IVZ | B55: Invesco LTD | C55: Quant | D55: Sell to Close | E55: -275 | F55: 16.315 | G55: 45721 | H55: -0.13009864 | I55: 4486.625
A56: CVS | B56: CVS Health Corp | C56: Quant | D56: Sell to Trim | E56: -15 | F56: 66.27 | G56: 45721 | H56: 0.19989136 | I56: 994.05
A57: GE | B57: =IFERROR(VLOOKUP($A57, 'Sector Holdings'!$B$3:$C$130, 2, FALSE),"N/A") -> General Electric Co | C57: Industrials | D57: Buy to Add | E57: 53 | F57: 192.89 | G57: 45729 | H57: =IF(OR(D57="Sell to Trim", D57="Sell to Close"),F57/VLOOKUP(A57, 'Sector Holdings'!$B$3:$M$121, 11, FALSE) - 1, "N/A") -> N/A | I57: =F57*E57*-1 -> -10223.17
A58: URI | B58: =IFERROR(VLOOKUP($A58, 'Sector Holdings'!$B$3:$C$130, 2, FALSE),"N/A") -> N/A | C58: Industrials | D58: Buy to Add | E58: 17 | F58: 596.89 | G58: 45729 | H58: =IF(OR(D58="Sell to Trim", D58="Sell to Close"),F58/VLOOKUP(A58, 'Sector Holdings'!$B$3:$M$121, 11, FALSE) - 1, "N/A") -> N/A | I58: =F58*E58*-1 -> -10147.13
A59: APD | B59: =IFERROR(VLOOKUP($A59, 'Sector Holdings'!$B$3:$C$130, 2, FALSE),"N/A") -> Air Products & Chemicals, Inc. | C59: Industrials | D59: Sell to Trim | E59: -69 | F59: 293.67 | G59: 45729 | H59: =IF(OR(D59="Sell to Trim", D59="Sell to Close"),F59/VLOOKUP(A59, 'Sector Holdings'!$B$3:$M$121, 11, FALSE) - 1, "N/A") -> 0.25694132 | I59: =F59*E59*-1 -> 20263.23
A60: GOOGL | B60: Alphabet Inc | C60: Technology | D60: Sell to Trim | E60: -32 | F60: 164.085 | G60: 45743 | H60: 1.7840658 | I60: 5250.72
A61: ADBE | B61: Adobe Inc. | C61: Technology | D61: Buy to Add | E61: 1 | F61: 399.4 | G61: 45743 | H61: N/A | I61: -399.4
A62: MSFT | B62: Microsoft Corp | C62: Technology | D62: Sell to Trim | E62: -18 | F62: 390.86 | G62: 45743 | H62: 1.0059293 | I62: 7035.48
A63: AMAT | B63: Applied Materials, Inc. | C63: Technology | D63: Sell to Trim | E63: -33 | F63: 149.3 | G63: 45743 | H63: -0.03083567 | I63: 4926.9
A64: SNPS | B64: Synopsys Inc. | C64: Technology | D64: Sell to Trim | E64: -14 | F64: 449.34 | G64: 45743 | H64: 0.11481277 | I64: 6290.76
A65: NICE | B65: Nice Ltd | C65: Technology | D65: Sell to Trim | E65: -30 | F65: 160.46 | G65: 45743 | H65: -0.27922251 | I65: 4813.8
A66: QCOM | B66: Qualcomm Inc. | C66: Technology | D66: Buy to Open | E66: 193 | F66: 158.88518 | G66: 45743 | H66: N/A | I66: -30664.84
A67: 29379VBM4 | B67: EPD Corp SOFR+324.761 08/16/77 | C67: Fixed Income | D67: Buy to Open | E67: 24 | F67: 1003.1 | G67: 45748 | H67: N/A | I67: -24074.4
A68: ATKR | B68: Atkore Inc | C68: Industrials | D68: Sell to Close | E68: -292 | F68: 60.31 | G68: 45749 | H68: -0.60165125 | I68: 17610.52
A69: GE | B69: General Electric Co | C69: Industrials | D69: Buy to Add | E69: 34 | F69: 200.35 | G69: 45749 | H69: N/A | I69: -6811.9
A70: URI | B70: United Rentals Inc | C70: Industrials | D70: Buy to Add | E70: 9 | F70: 633.93 | G70: 45749 | H70: N/A | I70: -5705.37
A71: APD | B71: Air Products & Chemicals, Inc. | C71: Industrials | D71: Buy to Add | E71: 19 | F71: 292.54 | G71: 45749 | H71: N/A | I71: -5558.26
A72: XOM | B72: Exxon Mobile Corp | C72: Quant | D72: Sell to Close | E72: -42 | F72: 101.03 | G72: 45754 | H72: -0.042913983 | I72: 4243.26
A73: CVS | B73: CVS Health Corp | C73: Quant | D73: Sell to Close | E73: -78 | F73: 63.33 | G73: 45754 | H73: 0.14665942 | I73: 4939.74
A74: MO | B74: Altria Group Inc | C74: Quant | D74: Sell to Close | E74: -93 | F74: 55.405 | G74: 45754 | H74: -0.012740556 | I74: 5152.665
A75: MAR | B75: Marriot International | C75: Quant | D75: Buy to Open | E75: 18 | F75: 212.14 | G75: 45754 | H75: N/A | I75: -3818.52
A76: UHS | B76: Universal Health Services | C76: Quant | D76: Buy to Open | E76: 26 | F76: 171.8 | G76: 45754 | H76: N/A | I76: -4466.8
A77: CVX | B77: Chevron Corp | C77: Quant | D77: Buy to Open | E77: 32 | F77: 138.91 | G77: 45754 | H77: N/A | I77: -4445.12
A78: TMO | B78: Thermo Fisher Scientific Inc. | C78: Healthcare | D78: Sell to Trim | E78: -27 | F78: 421.72 | G78: 45771 | H78: 0.40512445 | I78: 11386.44
A79: UNH | B79: UnitedHealth Group Inc | C79: Healthcare | D79: Sell to Trim | E79: -10 | F79: 427.69 | G79: 45771 | H79: 0.26953183 | I79: 4276.9
A80: VEEV | B80: Veeva Systems Inc. | C80: Healthcare | D80: Sell to Trim | E80: -55 | F80: 225.42 | G80: 45771 | H80: 0.24507042 | I80: 12398.1
A81: RPRX | B81: Royalty Pharma plc | C81: Healthcare | D81: Sell to Trim | E81: -299 | F81: 31.89 | G81: 45771 | H81: 0.11523662 | I81: 9535.11
A82: ALC | B82: =IFERROR(VLOOKUP($A82, 'Sector Holdings'!$B$3:$C$130, 2, FALSE),"N/A") -> N/A | C82: Healthcare | D82: Buy to Open | E82: 406 | F82: 94.03 | G82: 45771 | H82: =IF(OR(D82="Sell to Trim", D82="Sell to Close"),F82/VLOOKUP(A82, 'Sector Holdings'!$B$3:$M$121, 11, FALSE) - 1, "N/A") -> N/A | I82: =F82*E82*-1 -> -38176.18
A83: GL | B83: Globe Life Inc | C83: Quant | D83: Sell to Close | E83: -41 | F83: 119.634 | G83: 45791 | H83: -0.053977542 | I83: 4904.994
A84: FOX | B84: FOX Corp | C84: Quant | D84: Sell to Close | E84: -100 | F84: 50.53 | G84: 45791 | H84: -0.014241124 | I84: 5053
A85: CVX | B85: Chevron Corp | C85: Quant | D85: Sell to Close | E85: -32 | F85: 141.3 | G85: 45791 | H85: 0.017205385 | I85: 4521.6
A86: TAP | B86: Molson Coors Beverage Co | C86: Quant | D86: Sell to Close | E86: -87 | F86: 55.461 | G86: 45791 | H86: -0.073333333 | I86: 4825.107
A87: UHS | B87: Universal Health Services | C87: Quant | D87: Sell to Close | E87: -26 | F87: 188.26538 | G87: 45791 | H87: 0.095840423 | I87: 4894.9
A88: MAR | B88: Marriot International | C88: Quant | D88: Sell to Close | E88: -18 | F88: 272.38 | G88: 45791 | H88: 0.28396342 | I88: 4902.84
A89: HSIC | B89: Henry Schein Inc | C89: Quant | D89: Sell to Close | E89: -62 | F89: 69.9 | G89: 45791 | H89: -0.016877637 | I89: 4333.8
A90: MNST | B90: Monster Beverage Corp | C90: Quant | D90: Sell to Trim | E90: -10 | F90: 61.115 | G90: 45791 | H90: 0.10615385 | I90: 611.15
A91: MPC | B91: =IFERROR(VLOOKUP($A91, 'Sector Holdings'!$B$3:$C$130, 2, FALSE),"N/A") -> N/A | C91: Quant | D91: Buy to Open | E91: 30 | F91: 163.91 | G91: 45791 | H91: =IF(OR(D91="Sell to Trim", D91="Sell to Close"),F91/VLOOKUP(A91, 'Sector Holdings'!$B$3:$M$121, 11, FALSE) - 1, "N/A") -> N/A | I91: =F91*E91*-1 -> -4917.3
A92: WYNN | B92: =IFERROR(VLOOKUP($A92, 'Sector Holdings'!$B$3:$C$130, 2, FALSE),"N/A") -> N/A | C92: Quant | D92: Buy to Open | E92: 52 | F92: 96.82 | G92: 45791 | H92: =IF(OR(D92="Sell to Trim", D92="Sell to Close"),F92/VLOOKUP(A92, 'Sector Holdings'!$B$3:$M$121, 11, FALSE) - 1, "N/A") -> N/A | I92: =F92*E92*-1 -> -5034.64
A93: CF | B93: =IFERROR(VLOOKUP($A93, 'Sector Holdings'!$B$3:$C$130, 2, FALSE),"N/A") -> N/A | C93: Quant | D93: Buy to Open | E93: 59 | F93: 85.4686 | G93: 45791 | H93: =IF(OR(D93="Sell to Trim", D93="Sell to Close"),F93/VLOOKUP(A93, 'Sector Holdings'!$B$3:$M$121, 11, FALSE) - 1, "N/A") -> N/A | I93: =F93*E93*-1 -> -5042.6474
A94: WBA | B94: =IFERROR(VLOOKUP($A94, 'Sector Holdings'!$B$3:$C$130, 2, FALSE),"N/A") -> N/A | C94: Quant | D94: Buy to Open | E94: 448 | F94: 11.175 | G94: 45791 | H94: =IF(OR(D94="Sell to Trim", D94="Sell to Close"),F94/VLOOKUP(A94, 'Sector Holdings'!$B$3:$M$121, 11, FALSE) - 1, "N/A") -> N/A | I94: =F94*E94*-1 -> -5006.4
A95: XOM | B95: =IFERROR(VLOOKUP($A95, 'Sector Holdings'!$B$3:$C$130, 2, FALSE),"N/A") -> N/A | C95: Quant | D95: Buy to Open | E95: 39 | F95: 108.435 | G95: 45791 | H95: =IF(OR(D95="Sell to Trim", D95="Sell to Close"),F95/VLOOKUP(A95, 'Sector Holdings'!$B$3:$M$121, 11, FALSE) - 1, "N/A") -> N/A | I95: =F95*E95*-1 -> -4228.965
A96: KHC | B96: =IFERROR(VLOOKUP($A96, 'Sector Holdings'!$B$3:$C$130, 2, FALSE),"N/A") -> N/A | C96: Quant | D96: Buy to Open | E96: 156 | F96: 27.235 | G96: 45791 | H96: =IF(OR(D96="Sell to Trim", D96="Sell to Close"),F96/VLOOKUP(A96, 'Sector Holdings'!$B$3:$M$121, 11, FALSE) - 1, "N/A") -> N/A | I96: =F96*E96*-1 -> -4248.66
A97: CHTR | B97: =IFERROR(VLOOKUP($A97, 'Sector Holdings'!$B$3:$C$130, 2, FALSE),"N/A") -> N/A | C97: Quant | D97: Buy to Open | E97: 12 | F97: 412.3 | G97: 45791 | H97: =IF(OR(D97="Sell to Trim", D97="Sell to Close"),F97/VLOOKUP(A97, 'Sector Holdings'!$B$3:$M$121, 11, FALSE) - 1, "N/A") -> N/A | I97: =F97*E97*-1 -> -4947.6
A98: INCY | B98: Incyte Corp | C98: Quant | D98: Buy to Add | E98: 7 | F98: 61.1 | G98: 45791 | H98: N/A | I98: -427.7
A99: EPAM | B99: EPAM Systems Inc | C99: Quant | D99: Buy to Add | E99: 1 | F99: 184.69 | G99: 45791 | H99: N/A | I99: -184.69
B100: =IFERROR(VLOOKUP($A100, 'Sector Holdings'!$B$3:$C$130, 2, FALSE),"N/A") -> N/A | H100: =IF(OR(D100="Sell to Trim", D100="Sell to Close"),F100/VLOOKUP(A100, 'Sector Holdings'!$B$3:$M$121, 11, FALSE) - 1, "N/A") -> N/A | I100: =F100*E100*-1 -> 0
...

Sheet Fall 2024 Trades
A1: SSF | B1: Description | C1: Sector | D1: Trade Type | E1: Shares | F1: Trade Price | G1: Trade Date | H1: % Gain on Sale | I1: Cash Gain/Loss
A2: AMZN | B2: Amazon.com Inc | C2: Consumer Discretionary | D2: Buy to Add | E2: 4 | F2: 178.05 | G2: 45546 | H2: N/A | I2: =F2*E2*-1 -> -712.2
A3: EVVTY | B3: Evolution ADR | C3: Consumer Discretionary | D3: Buy to Add | E3: 7 | F3: 96.88 | G3: 45546 | H3: N/A | I3: =F3*E3*-1 -> -678.16
A4: SFM | B4: Sprouts Farmers Market Inc | C4: Consumer Staples | D4: Sell to Trim | E4: -232 | F4: 98.91 | G4: 45546 | H4: 1.2901135 | I4: =F4*E4*-1 -> 22947.12
A5: PM | B5: Philip Morris International Inc. | C5: Consumer Staples | D5: Sell to Trim | E5: -46 | F5: 124.76 | G5: 45546 | H5: 0.37658612 | I5: =F5*E5*-1 -> 5738.96
A6: POST | B6: Post Holdings Inc | C6: Consumer Staples | D6: Sell to Trim | E6: -50 | F6: 114.08 | G6: 45546 | H6: 0.34085567 | I6: =F6*E6*-1 -> 5704
A7: NNI | B7: Nelnet Inc | C7: Financials | D7: Sell to Trim | E7: -85 | F7: 108.39 | G7: 45546 | H7: 0.45119829 | I7: =F7*E7*-1 -> 9213.15
A8: AGM | B8: Farmer Mac | C8: Financials | D8: Sell to Trim | E8: -51 | F8: 178.23 | G8: 45546 | H8: 0.21113074 | I8: =F8*E8*-1 -> 9089.73
A9: GE | B9: General Electric Co | C9: Industrials | D9: Buy to Add | E9: 50 | F9: 162.5 | G9: 45546 | H9: N/A | I9: =F9*E9*-1 -> -8125
A10: ADBE | B10: Adobe Inc. | C10: Technology | D10: Buy to Add | E10: 41 | F10: 563.51 | G10: 45546 | H10: N/A | I10: =F10*E10*-1 -> -23103.91
A11: GOOGL | B11: Alphabet Inc | C11: Technology | D11: Buy to Add | E11: 155 | F11: 148.23 | G11: 45546 | H11: N/A | I11: =F11*E11*-1 -> -22975.65
A12: XLK | B12: SPDR Technology ETF | C12: Technology | D12: Buy to Add | E12: 132 | F12: 208.79 | G12: 45546 | H12: N/A | I12: =F12*E12*-1 -> -27560.28
A13: META | B13: Meta Platforms, Inc. | C13: Technology | D13: Buy to Add | E13: 52 | F13: 499.26 | G13: 45546 | H13: N/A | I13: =F13*E13*-1 -> -25961.52
A14: LYV | B14: Live Nation Entertainment Inc | C14: Media and Telecom | D14: Buy to Add | E14: 273 | F14: 95.24 | G14: 45546 | H14: N/A | I14: =F14*E14*-1 -> -26000.52
A15: VST | B15: Vistra Corp | C15: Utilities | D15: Sell to Trim | E15: -183 | F15: 75.81 | G15: 45546 | H15: 1.1093489 | I15: =F15*E15*-1 -> 13873.23
A16: CEG | B16: Constellation Energy Corp | C16: Utilities | D16: Sell to Trim | E16: -77 | F16: 179.99 | G16: 45546 | H16: 1.0294283 | I16: =F16*E16*-1 -> 13859.23
A17: EHMEF | B17: GoEasy Ltd | C17: Financials | D17: Sell to Trim | E17: -71 | F17: 128.5 | G17: 45546 | H17: 0.19568252 | I17: =F17*E17*-1 -> 9123.5
A18: NICE | B18: Nice Ltd | C18: Technology | D18: Sell to Trim | E18: -1 | F18: 167.69 | G18: 45558 | H18: -0.26809681 | I18: =F18*E18*-1 -> 167.69
A19: XLK | B19: SPDR Technology ETF | C19: Technology | D19: Sell to Close | E19: -132 | F19: 221.7 | G19: 45558 | H19: 0.061832463 | I19: =F19*E19*-1 -> 29264.4
A20: APP | B20: Applovin Corp | C20: Technology | D20: Buy to Open | E20: 234 | F20: 126.44 | G20: 45558 | H20: N/A | I20: =F20*E20*-1 -> -29586.96
A21: GOOGL | B21: Alphabet Inc | C21: Technology | D21: Sell to Trim | E21: -82 | F21: 162.61 | G21: 45561 | H21: 7.5449291 | I21: =F21*E21*-1 -> 13334.02
A22: ADBE | B22: Adobe Inc. | C22: Technology | D22: Sell to Trim | E22: -22 | F22: 515.62 | G22: 45561 | H22: 0.6625395 | I22: =F22*E22*-1 -> 11343.64
A23: MSFT | B23: Microsoft Corp | C23: Technology | D23: Sell to Trim | E23: -26 | F23: 430.21 | G23: 45561 | H23: 1.5908461 | I23: =F23*E23*-1 -> 11185.46
A24: AMAT | B24: Applied Materials, Inc. | C24: Technology | D24: Sell to Trim | E24: -48 | F24: 207.34 | G24: 45561 | H24: 0.3771254 | I24: =F24*E24*-1 -> 9952.32
A25: SNPS | B25: Synopsys Inc. | C25: Technology | D25: Sell to Trim | E25: -25 | F25: 513.35 | G25: 45561 | H25: 0.33220013 | I25: =F25*E25*-1 -> 12833.75
A26: 61747YFT7 | B26: MS 5.32 07/19/2035 | C26: Fixed Income | D26: Buy to Open | E26: 47 | F26: 1038.1 | G26: 45561 | H26: N/A | I26: =F26*E26*-1 -> -48790.7
A27: BLCO | B27: Bausch and Lomb Corp | C27: Healthcare | D27: Sell to Close | E27: -2316 | F27: 18.92 | G27: 45562 | H27: 0.19331441 | I27: =F27*E27*-1 -> 43818.72
A28: TMO | B28: Thermo Fisher Scientific Inc. | C28: Healthcare | D28: Buy to Add | E28: 18 | F28: 613.27 | G28: 45565 | H28: N/A | I28: =F28*E28*-1 -> -11038.86
A29: UNH | B29: UnitedHealth Group Inc | C29: Healthcare | D29: Buy to Add | E29: 19 | F29: 582.68 | G29: 45565 | H29: N/A | I29: =F29*E29*-1 -> -11070.92
A30: VEEV | B30: Veeva Systems Inc. | C30: Healthcare | D30: Buy to Add | E30: 52 | F30: 210.08 | G30: 45565 | H30: N/A | I30: =F30*E30*-1 -> -10924.16
A31: RPRX | B31: Royalty Pharma plc | C31: Healthcare | D31: Buy to Add | E31: 390 | F31: 28.09 | G31: 45565 | H31: N/A | I31: =F31*E31*-1 -> -10955.1
A32: NNI | B32: Nelnet Inc | C32: Financials | D32: Sell to Close | E32: -271 | F32: 112.28 | G32: 45576 | H32: 0.50328022 | I32: =F32*E32*-1 -> 30427.88
A33: URI | B33: United Rentals Inc | C33: Industrials | D33: Sell to Trim | E33: -45 | F33: 813.62 | G33: 45576 | H33: 1.4869177 | I33: =F33*E33*-1 -> 36612.9
A34: SFM | B34: Sprouts Farmers Market Inc | C34: Consumer Staples | D34: Sell to Trim | E34: -196 | F34: 115.68 | G34: 45576 | H34: 1.6783978 | I34: =F34*E34*-1 -> 22673.28
A35: POST | B35: Post Holdings Inc | C35: Consumer Staples | D35: Buy to Add | E35: 128 | F35: 115.69 | G35: 45580 | H35: N/A | I35: =F35*E35*-1 -> -14808.32
A36: PM | B36: Philip Morris International Inc. | C36: Consumer Staples | D36: Buy to Add | E36: 113 | F36: 120.44 | G36: 45580 | H36: N/A | I36: =F36*E36*-1 -> -13609.72
A37: APD | B37: Air Products & Chemicals, Inc. | C37: Industrials | D37: Buy to Add | E37: 59 | F37: 322.51 | G37: 45580 | H37: N/A | I37: =F37*E37*-1 -> -19028.09
A38: GE | B38: General Electric Co | C38: Industrials | D38: Buy to Add | E38: 91 | F38: 190.78 | G38: 45580 | H38: N/A | I38: =F38*E38*-1 -> -17360.98
A39: SPGI | B39: S&P Global Inc | C39: Financials | D39: Buy to Add | E39: 12 | F39: 528.73 | G39: 45580 | H39: N/A | I39: =F39*E39*-1 -> -6344.76
A40: FI | B40: Fiserv Inc | C40: Financials | D40: Buy to Add | E40: 11 | F40: 194.33 | G40: 45580 | H40: N/A | I40: =F40*E40*-1 -> -2137.63
A41: EHMEF | B41: GoEasy Ltd | C41: Financials | D41: Buy to Add | E41: 36 | F41: 138.83 | G41: 45580 | H41: N/A | I41: =F41*E41*-1 -> -4997.88
A42: AGM | B42: Farmer Mac | C42: Financials | D42: Buy to Add | E42: 23 | F42: 186.78 | G42: 45580 | H42: N/A | I42: =F42*E42*-1 -> -4295.94
A43: AGCL | B43: Arch Capital Group Ltd | C43: Financials | D43: Buy to Add | E43: 119 | F43: 108.24 | G43: 45580 | H43: N/A | I43: =F43*E43*-1 -> -12880.56
A44: 822582AD4 | B44: RDSALN 6.375 12/15/38 | C44: Fixed Income | D44: Buy to Open | E44: 43 | F44: 1120.55 | G44: 45590 | H44: N/A | I44: =F44*E44*-1 -> -48183.65
A45: EHMEF | B45: GoEasy Ltd | C45: Financials | D45: Sell to Trim | E45: -77 | F45: 125.05 | G45: 45597 | H45: 0.16358053 | I45: =F45*E45*-1 -> 9628.85
A46: FI | B46: Fiserv Inc | C46: Financials | D46: Sell to Trim | E46: -37 | F46: 201.97 | G46: 45597 | H46: 1.0510815 | I46: =F46*E46*-1 -> 7472.89
A47: ACGL | B47: Arch Capital Group Ltd | C47: Financials | D47: Sell to Trim | E47: -134 | F47: 96.47 | G47: 45597 | H47: 0.74954661 | I47: =F47*E47*-1 -> 12926.98
A48: AGM | B48: Farmer Mac | C48: Financials | D48: Sell to Trim | E48: -32 | F48: 183.7 | G48: 45597 | H48: 0.24830117 | I48: =F48*E48*-1 -> 5878.4
A49: SPGI | B49: S&P Global Inc | C49: Financials | D49: Sell to Trim | E49: -4 | F49: 484.61 | G49: 45597 | H49: 0.12548191 | I49: =F49*E49*-1 -> 1938.44
A50: SNEX | B50: Stonex Group Inc | C50: Financials | D50: Buy to Open | E50: 417 | F50: 90.27 | G50: 45597 | H50: N/A | I50: =F50*E50*-1 -> -37642.59
A51: 626717AP7 | B51: MUR 6 10/01/32 | C51: Fixed Income | D51: Buy to Open | E51: 25 | F51: 966 | G51: 45611 | H51: N/A | I51: =F51*E51*-1 -> -24150
H52: =IF(OR(D52="Sell to Trim", D52="Sell to Close"),F52/VLOOKUP(A52, 'Sector Holdings'!$B$3:$M$121, 11, FALSE) - 1, "N/A") -> N/A
B167: =IFERROR(VLOOKUP($A167, 'Sector Holdings'!$B$3:$C$130, 2, FALSE),"N/A") -> N/A | H167: =IF(OR(D167="Sell to Trim", D167="Sell to Close"),F167/VLOOKUP(A167, 'Sector Holdings'!$B$3:$M$121, 11, FALSE) - 1, "N/A") -> N/A | I167: =F167*E167*-1 -> 0

Sheet Spring 2024 Trades
A1: SSF | B1: Description | C1: Sector | D1: Trade Type | E1: Shares | F1: Trade Price | G1: Trade Date | H1: % Gain on Sale | I1: Cash Gain/Loss | J1: Buy 7 Close 22
A2: EMN | B2: Eastman Chemical Co | C2: Quant | D2: Sell to Close | E2: -49 | F2: 86.01 | G2: 45307 | H2: 0.050824679 | I2: =F2*E2*-1 -> 4214.49
A3: GS | B3: Goldman Sachs Group Inc | C3: Quant | D3: Sell to Close | E3: -12 | F3: 376.24 | G3: 45307 | H3: 0.11590936 | I3: =F3*E3*-1 -> 4514.88
A4: HCA | B4: HCA Healthcare Inc | C4: Quant | D4: Sell to Close | E4: -16 | F4: 279.9299 | G4: 45307 | H4: 0.12820369 | I4: =F4*E4*-1 -> 4478.8784
A5: HPQ | B5: HP Inc | C5: Quant | D5: Sell to Close | E5: -142 | F5: 29.0345 | G5: 45307 | H5: 0.015902729 | I5: =F5*E5*-1 -> 4122.899
A6: PARA | B6: Paramount Global Class B Com | C6: Quant | D6: Sell to Close | E6: -288 | F6: 13.2446 | G6: 45307 | H6: -0.056652422 | I6: =F6*E6*-1 -> 3814.4448
A7: CTRA | B7: Coterra Energy Inc | C7: Quant | D7: Sell to Close | E7: -77 | F7: 24.965 | G7: 45307 | H7: -0.058634992 | I7: =F7*E7*-1 -> 1922.305
A8: MRO | B8: Marathon Oil Corp | C8: Quant | D8: Sell to Close | E8: -79 | F8: 22.7255 | G8: 45307 | H8: -0.10915327 | I8: =F8*E8*-1 -> 1795.3145
A9: ANSS | B9: ANSYS Inc | C9: Quant | D9: Sell to Close | E9: -7 | F9: 327.23 | G9: 45307 | H9: 0.1086905 | I9: =F9*E9*-1 -> 2290.61
A10: STLD | B10: Steel Dynamics Inc | C10: Quant | D10: Sell to Close | E10: -17 | F10: 111.8134 | G10: 45307 | H10: -0.034426598 | I10: =F10*E10*-1 -> 1900.8278
A11: EPAM | B11: EPAM Systems Inc | C11: Quant | D11: Sell to Close | E11: -8 | F11: 296.9701 | G11: 45307 | H11: 0.15606548 | I11: =F11*E11*-1 -> 2375.7608
A12: ES | B12: Eversource Energy | C12: Quant | D12: Sell to Close | E12: -34 | F12: 56.43 | G12: 45307 | H12: -0.057457825 | I12: =F12*E12*-1 -> 1918.62
A13: SNA | B13: Snap-On Inc | C13: Quant | D13: Sell to Close | E13: -7 | F13: 284.4186 | G13: 45307 | H13: 0.040530475 | I13: =F13*E13*-1 -> 1990.9302
... A16: DGX | B16: Quest Diagnostics Inc | C16: Quant | D16: Sell to Close | E16: -15 | F16: 133.57 | G16: 45307 | H16: -0.021680217 | I16: =F16*E16*-1 -> 2003.55
A17: OGN | B17: Organon & Co | C17: Quant | D17: Buy to Open | E17: 251 | F17: 16.71 | G17: 45307 | H17: N/A | I17: =F17*E17*-1 -> -4194.21
A18: HCA | B18: HCA Healthcare Inc | C18: Quant | D18: Buy to Open | E18: 15 | F18: 280.04 | G18: 45307 | H18: N/A | I18: =F18*E18*-1 -> -4200.6
A19: XRAY | B19: Dentsply Sirona Inc | C19: Quant | D19: Buy to Open | E19: 116 | F19: 35.98 | G19: 45307 | H19: N/A | I19: =F19*E19*-1 -> -4173.68
A20: IP | B20: International Paper Co | C20: Quant | D20: Buy to Open | E20: 113 | F20: 37.28 | G20: 45307 | H20: N/A | I20: =F20*E20*-1 -> -4212.64
A21: FOXA | B21: Fox Corp Class A | C21: Quant | D21: Buy to Open | E21: 137 | F21: 30.65 | G21: 45307 | H21: N/A | I21: =F21*E21*-1 -> -4199.05
A22: TDG | B22: TransDigm Group Inc | C22: Quant | D22: Buy to Open | E22: 2 | F22: 1025.41 | G22: 45307 | H22: N/A | I22: =F22*E22*-1 -> -2050.82
A23: PSX | B23: Phillips 66 | C23: Quant | D23: Buy to Open | E23: 16 | F23: 130.29 | G23: 45307 | H23: N/A | I23: =F23*E23*-1 -> -2084.64
A24: PM | B24: Philip Morris International Inc. | C24: Quant | D24: Buy to Open | E24: 22 | F24: 94.32 | G24: 45307 | H24: N/A | I24: =F24*E24*-1 -> -2075.04
A25: KEYS | B25: Keysight Technologies Inc | C25: Quant | D25: Buy to Open | E25: 14 | F25: 150.49 | G25: 45307 | H25: N/A | I25: =F25*E25*-1 -> -2106.86
A26: HCA | B26: HCA Healthcare Inc | C26: Quant | D26: Buy to Open | E26: 7 | F26: 280.08 | G26: 45307 | H26: N/A | I26: =F26*E26*-1 -> -1960.56
A27: EQR | B27: Equity Residential | C27: Quant | D27: Buy to Open | E27: 34 | F27: 61.25 | G27: 45307 | H27: N/A | I27: =F27*E27*-1 -> -2082.5
A28: ETR | B28: Entergy Corp | C28: Quant | D28: Buy to Open | E28: 20 | F28: 103.06 | G28: 45307 | H28: N/A | I28: =F28*E28*-1 -> -2061.2
... A31: SBUX | B31: Starbucks Corp | C31: Quant | D31: Buy to Open | E31: 23 | F31: 92.09 | G31: 45307 | H31: N/A | I31: =F31*E31*-1 -> -2118.07
A32: FANG | B32: Diamondback Energy Inc | C32: Energy | D32: Sell to Trim | E32: -72 | F32: 152.524 | G32: 45315 | H32: 0.89212257 | I32: =F32*E32*-1 -> 10981.728
A33: TTE | B33: TotalEnergies SE | C33: Energy | D33: Sell to Trim | E33: -173 | F33: 63.97 | G33: 45315 | H33: 0.25063539 | I33: =F33*E33*-1 -> 11066.81
A34: MRK | B34: Merck & Co., Inc. | C34: Healthcare | D34: Sell to Trim | E34: -138 | F34: 118.86 | G34: 45315 | H34: 0.53864078 | I34: =F34*E34*-1 -> 16402.68
A35: GOOGL | B35: Alphabet Inc | C35: Media & Telecom | D35: Sell to Trim | E35: -63 | F35: 149.23 | G35: 45315 | H35: 9.7747292 | I35: =F35*E35*-1 -> 9401.49
A36: META | B36: Meta Platforms, Inc. | C36: Media & Telecom | D36: Sell to Trim | E36: -27 | F36: 394.57 | G36: 45315 | H36: 0.68951786 | I36: =F36*E36*-1 -> 10653.39
A37: XLV | B37: SPDR Healthcare ETF | C37: Healthcare | D37: Buy to Open | E37: 200 | F37: 139.3099 | G37: 45317 | H37: N/A | I37: =F37*E37*-1 -> -27861.98
A38: AMZN | B38: Amazon.com Inc | C38: Consumer Discretionary | D38: Buy to Add | E38: 27 | F38: 157.79 | G38: 45315 | H38: N/A | I38: =F38*E38*-1 -> -4260.33
A39: EHMEF | B39: GoEasy Ltd | C39: Financials | D39: Buy to Add | E39: 89 | F39: 123.0925 | G39: 45315 | H39: N/A | I39: =F39*E39*-1 -> -10955.233
A40: ACGL | B40: Arch Capital Group Ltd | C40: Financials | D40: Buy to Add | E40: 132 | F40: 80.4 | G40: 45315 | H40: N/A | I40: =F40*E40*-1 -> -10612.8
A41: ICE | B41: Intercontinental Exchange Inc | C41: Financials | D41: Buy to Add | E41: 42 | F41: 126.85 | G41: 45315 | H41: N/A | I41: =F41*E41*-1 -> -5327.7
A42: ATKR | B42: Atkore Inc | C42: Industrials | D42: Buy to Add | E42: 136 | F42: 154.37 | G42: 45315 | H42: N/A | I42: =F42*E42*-1 -> -20994.32
A43: VICI | B43: Vici Properties Inc | C43: REITs | D43: Buy to Add | E43: 121 | F43: 30.65 | G43: 45315 | H43: N/A | I43: =F43*E43*-1 -> -3708.65
A44: MSFT | B44: Microsoft Corp | C44: Technology | D44: Buy to Add | E44: 24 | F44: 405.24 | G44: 45315 | H44: N/A | I44: =F44*E44*-1 -> -9725.76
A45: SNPS | B45: Synopsys Inc. | C45: Technology | D45: Buy to Add | E45: 32 | F45: 551.345 | G45: 45315 | H45: N/A | I45: =F45*E45*-1 -> -17643.04
A46: AMAT | B46: Applied Materials, Inc. | C46: Technology | D46: Buy to Add | E46: 99 | F46: 175.36 | G46: 45315 | H46: N/A | I46: =F46*E46*-1 -> -17360.64
A47: CNSWF | B47: Constellation Software | C47: Technology | D47: Buy to Add | E47: 6 | F47: 2740 | G47: 45315 | H47: N/A | I47: =F47*E47*-1 -> -16440
A48: XLF | B48: SPDR Financials ETF | C48: Financials | D48: Buy to Open | E48: 471 | F48: 38.685 | G48: 45317 | H48: N/A | I48: =F48*E48*-1 -> -18220.635
... A51: GE | B51: General Electric Co | C51: Industrials | D51: Buy to Open | E51: 130 | F51: 176.82 | G51: 45372 | H51: N/A | I51: =F51*E51*-1 -> -22986.6
A52: XLK | B52: SPDR Technology ETF | C52: Technology | D52: Sell to Close | E52: -252 | F52: 204.91 | G52: 45315 | H52: 0.42645318 | I52: =F52*E52*-1 -> 51637.32
A53: MRK | B53: Merck & Co., Inc. | C53: Healthcare | D53: Sell to Close | E53: -230 | F53: 120.84 | G53: 45317 | H53: 0.56427184 | I53: =F53*E53*-1 -> 27793.2
A54: ICE | B54: Intercontinental Exchange Inc | C54: Financials | D54: Buy to Add | E54: 24 | F54: 129.2599 | G54: 45324 | H54: =IF(OR(D54="Sell to Trim", D54="Sell to Close"),F54/VLOOKUP(A54, 'Sector Holdings'!$B$3:$M$121, 11, FALSE) - 1, "N/A") -> N/A | I54: =F54*E54*-1 -> -3102.2376
A55: NNI | B55: Nelnet Inc | C55: Financials | D55: Buy to Add | E55: 35 | F55: 88.3396 | G55: 45324 | H55: =IF(OR(D55="Sell to Trim", D55="Sell to Close"),F55/VLOOKUP(A55, 'Sector Holdings'!$B$3:$M$121, 11, FALSE) - 1, "N/A") -> N/A | I55: =F55*E55*-1 -> -3091.886
A56: FI | B56: Fiserv Inc | C56: Financials | D56: Buy to Add | E56: 21 | F56: 145.69 | G56: 45324 | H56: =IF(OR(D56="Sell to Trim", D56="Sell to Close"),F56/VLOOKUP(A56, 'Sector Holdings'!$B$3:$M$121, 11, FALSE) - 1, "N/A") -> N/A | I56: =F56*E56*-1 -> -3059.49
A57: ACGL | B57: Arch Capital Group Ltd | C57: Financials | D57: Buy to Add | E57: 37 | F57: 83.51 | G57: 45324 | H57: =IF(OR(D57="Sell to Trim", D57="Sell to Close"),F57/VLOOKUP(A57, 'Sector Holdings'!$B$3:$M$121, 11, FALSE) - 1, "N/A") -> N/A | I57: =F57*E57*-1 -> -3089.87
A58: AGM | B58: Farmer Mac | C58: Financials | D58: Buy to Add | E58: 16 | F58: 189.74 | G58: 45324 | H58: =IF(OR(D58="Sell to Trim", D58="Sell to Close"),F58/VLOOKUP(A58, 'Sector Holdings'!$B$3:$M$121, 11, FALSE) - 1, "N/A") -> N/A | I58: =F58*E58*-1 -> -3035.84
A59: EHMEF | B59: GoEasy Ltd | C59: Financials | D59: Buy to Add | E59: 27 | F59: 116.075 | G59: 45324 | H59: =IF(OR(D59="Sell to Trim", D59="Sell to Close"),F59/VLOOKUP(A59, 'Sector Holdings'!$B$3:$M$121, 11, FALSE) - 1, "N/A") -> N/A | I59: =F59*E59*-1 -> -3134.025
A60: MDT | B60: Medtronic PLC | C60: Healthcare | D60: Buy to Add | E60: 65 | F60: 88.0899 | G60: 45324 | H60: =IF(OR(D60="Sell to Trim", D60="Sell to Close"),F60/VLOOKUP(A60, 'Sector Holdings'!$B$3:$M$121, 11, FALSE) - 1, "N/A") -> N/A | I60: =F60*E60*-1 -> -5725.8435
A61: VRTX | B61: Vertex Pharmaceuticals Inc. | C61: Healthcare | D61: Buy to Add | E61: 13 | F61: 426.0599 | G61: 45324 | H61: =IF(OR(D61="Sell to Trim", D61="Sell to Close"),F61/VLOOKUP(A61, 'Sector Holdings'!$B$3:$M$121, 11, FALSE) - 1, "N/A") -> N/A | I61: =F61*E61*-1 -> -5538.7787
A62: TMO | B62: Thermo Fisher Scientific Inc. | C62: Healthcare | D62: Buy to Add | E62: 10 | F62: 553.38 | G62: 45324 | H62: =IF(OR(D62="Sell to Trim", D62="Sell to Close"),F62/VLOOKUP(A62, 'Sector Holdings'!$B$3:$M$121, 11, FALSE) - 1, "N/A") -> N/A | I62: =F62*E62*-1 -> -5533.8
A63: UNH | B63: UnitedHealth Group Inc | C63: Healthcare | D63: Buy to Add | E63: 11 | F63: 511.6404 | G63: 45324 | H63: =IF(OR(D63="Sell to Trim", D63="Sell to Close"),F63/VLOOKUP(A63, 'Sector Holdings'!$B$3:$M$121, 11, FALSE) - 1, "N/A") -> N/A | I63: =F63*E63*-1 -> -5628.0444
A64: VEEV | B64: Veeva Systems Inc. | C64: Healthcare | D64: Buy to Add | E64: 27 | F64: 207.825 | G64: 45324 | H64: =IF(OR(D64="Sell to Trim", D64="Sell to Close"),F64/VLOOKUP(A64, 'Sector Holdings'!$B$3:$M$121, 11, FALSE) - 1, "N/A") -> N/A | I64: =F64*E64*-1 -> -5611.275
A65: PFG | B65: Principal Financial Group Inc | C65: Financials | D65: Sell to Close | E65: -226 | F65: 80.63 | G65: 45317 | H65: 0.75817706 | I65: =F65*E65*-1 -> 18222.38
A66: XLV | B66: SPDR Healthcare ETF | C66: Healthcare | D66: Sell to Close | E66: -200 | F66: 142.55 | G66: 45324 | H66: 0.023257483 | I66: =F66*E66*-1 -> 28510
A67: XLF | B67: SPDR Financials ETF | C67: Financials | D67: Sell to Close | E67: -471 | F67: 39.1309 | G67: 45324 | H67: 0.011395709 | I67: =F67*E67*-1 -> 18430.654
A68: MTCH | B68: Match Group | C68: Media & Telecom | D68: Sell to Close | E68: -186 | F68: 37.31 | G68: 45334 | H68: -0.42872454 | I68: =F68*E68*-1 -> 6939.66
A69: VST | B69: Vistra Corp | C69: Utilities | D69: Buy to Add | E69: 60 | F69: 43.01 | G69: 45334 | H69: N/A | I69: =F69*E69*-1 -> -2580.6
A70: NEE | B70: NextEra Energy Inc | C70: Utilities | D70: Buy to Add | E70: 45 | F70: 57.54 | G70: 45334 | H70: N/A | I70: =F70*E70*-1 -> -2589.3
A71: CEG | B71: Constellation Energy Corp | C71: Utilities | D71: Buy to Add | E71: 10 | F71: 128.5 | G71: 45334 | H71: N/A | I71: =F71*E71*-1 -> -1285
A72: DIS | B72: Walt Disney Co/The | C72: Media & Telecom | D72: Buy to Add | E72: 16 | F72: 109.88 | G72: 45334 | H72: N/A | I72: =F72*E72*-1 -> -1758.08
A73: GOOGL | B73: Alphabet Inc | C73: Media & Telecom | D73: Buy to Add | E73: 12 | F73: 148.47 | G73: 45334 | H73: N/A | I73: =F73*E73*-1 -> -1781.64
A74: META | B74: Meta Platforms, Inc. | C74: Media & Telecom | D74: Buy to Add | E74: 4 | F74: 468.38 | G74: 45334 | H74: N/A | I74: =F74*E74*-1 -> -1873.52
A75: LYV | B75: Live Nation Entertainment Inc | C75: Media & Telecom | D75: Buy to Add | E75: 19 | F75: 89.67 | G75: 45334 | H75: N/A | I75: =F75*E75*-1 -> -1703.73
A76: PLD | B76: Prologis Inc. | C76: REITs | D76: Buy to Add | E76: 15 | F76: 132.58 | G76: 45334 | H76: N/A | I76: =F76*E76*-1 -> -1988.7
A77: ADC | B77: Agree Realty Corporation | C77: REITs | D77: Buy to Add | E77: 33 | F77: 58.16 | G77: 45334 | H77: N/A | I77: =F77*E77*-1 -> -1919.28
A78: VICI | B78: Vici Properties Inc | C78: REITs | D78: Buy to Add | E78: 65 | F78: 29.86 | G78: 45334 | H78: N/A | I78: =F78*E78*-1 -> -1940.9
A79: CWEN | B79: Clearway Energy Inc. | C79: Utilities | D79: Sell to Close | E79: -272 | F79: 23.5514 | G79: 45334 | H79: -0.2565846 | I79: =F79*E79*-1 -> 6405.9808
A80: AMT | B80: American Tower Corporation | C80: REITs | D80: Sell to Close | E80: -30 | F80: 193.1 | G80: 45334 | H80: -0.060340633 | I80: =F80*E80*-1 -> 5793
A81: BBN | B81: BlackRock Taxable Municipal Trust | C81: Fixed Income | D81: Sell to Close | E81: -1241 | F81: 16.9 | G81: 45334 | H81: -0.277469 | I81: =F81*E81*-1 -> 20972.9
A82: PM | B82: Philip Morris International Inc. | C82: Consumer Staples | D82: Buy to Add | E82: 87 | F82: 89.8188 | G82: 45338 | H82: N/A | I82: =F82*E82*-1 -> -7814.2356
A83: SFM | B83: Sprouts Farmers Market Inc | C83: Consumer Staples | D83: Buy to Add | E83: 147 | F83: 53.06 | G83: 45338 | H83: N/A | I83: =F83*E83*-1 -> -7799.82
A84: POST | B84: Post Holdings Inc | C84: Consumer Staples | D84: Buy to Add | E84: 74 | F84: 104.9461 | G84: 45338 | H84: N/A | I84: =F84*E84*-1 -> -7766.0114
A85: APD | B85: Air Products & Chemicals, Inc. | C85: Industrials | D85: Buy to Add | E85: 19 | F85: 226.6699 | G85: 45338 | H85: N/A | I85: =F85*E85*-1 -> -4306.7281
A86: URI | B86: United Rentals Inc | C86: Industrials | D86: Buy to Add | E86: 7 | F86: 653.2861 | G86: 45338 | H86: N/A | I86: =F86*E86*-1 -> -4573.0027
A87: DE | B87: Deere & Co. | C87: Industrials | D87: Buy to Add | E87: 12 | F87: 360.46 | G87: 45338 | H87: N/A | I87: =F87*E87*-1 -> -4325.52
A88: ATKR | B88: Atkore Inc | C88: Industrials | D88: Buy to Add | E88: 30 | F88: 146.11 | G88: 45338 | H88: N/A | I88: =F88*E88*-1 -> -4383.3
A89: ADBE | B89: Adobe Inc. | C89: Technology | D89: Buy to Add | E89: 11 | F89: 558.18 | G89: 45338 | H89: N/A | I89: =F89*E89*-1 -> -6139.98
A90: MSFT | B90: Microsoft Corp | C90: Technology | D90: Buy to Add | E90: 15 | F90: 404.968 | G90: 45338 | H90: N/A | I90: =F90*E90*-1 -> -6074.52
A91: AMAT | B91: Applied Materials, Inc. | C91: Technology | D91: Buy to Add | E91: 29 | F91: 202.3849 | G91: 45338 | H91: N/A | I91: =F91*E91*-1 -> -5869.1621
A92: SNPS | B92: Synopsys Inc. | C92: Technology | D92: Buy to Add | E92: 11 | F92: 556.7746 | G92: 45338 | H92: N/A | I92: =F92*E92*-1 -> -6124.5206
A93: CNSWF | B93: Constellation Software | C93: Technology | D93: Buy to Add | E93: 2 | F93: 2785.97 | G93: 45338 | H93: N/A | I93: =F93*E93*-1 -> -5571.94
A94: IMKTA | B94: Ingles Markets, Inc. | C94: Consumer Staples | D94: Sell to Close | E94: -307 | F94: 76.3155 | G94: 45338 | H94: -0.17621438 | I94: =F94*E94*-1 -> 23428.858
A95: VRSN | B95: VeriSign Inc. | C95: Technology | D95: Sell to Close | E95: -151 | F95: 196.3021 | G95: 45338 | H95: 0.1249404 | I95: =F95*E95*-1 -> 29641.617
A96: LNG | B96: Cheniere Energy | C96: Energy | D96: Buy to Add | E96: 118 | F96: 159.57 | G96: 45345 | H96: N/A | I96: =F96*E96*-1 -> -18829.26
A97: FANG | B97: Diamondback Energy Inc | C97: Energy | D97: Buy to Add | E97: 18 | F97: 117.16 | G97: 45345 | H97: N/A | I97: =F97*E97*-1 -> -2108.88
A98: CHRD | B98: Chord Energy Corp | C98: Energy | D98: Buy to Add | E98: 20 | F98: 157.6 | G98: 45345 | H98: N/A | I98: =F98*E98*-1 -> -3152
A99: VRTX | B99: Vertex Pharmaceuticals Inc. | C99: Healthcare | D99: Buy to Add | E99: 9 | F99: 430.57 | G99: 45345 | H99: N/A | I99: =F99*E99*-1 -> -3875.13
A100: TMO | B100: Thermo Fisher Scientific Inc. | C100: Healthcare | D100: Buy to Add | E100: 7 | F100: 565.15 | G100: 45345 | H100: N/A | I100: =F100*E100*-1 -> -3956.05
A101: UNH | B101: UnitedHealth Group Inc | C101: Healthcare | D101: Buy to Add | E101: 8 | F101: 526.3 | G101: 45345 | H101: N/A | I101: =F101*E101*-1 -> -4210.4
A102: VEEV | B102: Veeva Systems Inc. | C102: Healthcare | D102: Buy to Add | E102: 18 | F102: 223.13 | G102: 45345 | H102: N/A | I102: =F102*E102*-1 -> -4016.34
A103: BLCO | B103: Bausch and Lomb Corp | C103: Healthcare | D103: Buy to Add | E103: 227 | F103: 17.56 | G103: 45345 | H103: N/A | I103: =F103*E103*-1 -> -3986.12
A104: TDG | B104: TransDigm Group Inc | C104: Quant | D104: Sell to Close | E104: -2 | F104: 1174.73 | G104: 45350 | H104: 0.1456198 | I104: =F104*E104*-1 -> 2349.46
A105: PSX | B105: Phillips 66 | C105: Quant | D105: Sell to Close | E105: -16 | F105: 141.65 | G105: 45350 | H105: 0.087197624 | I105: =F105*E105*-1 -> 2266.4
A106: PM | B106: Philip Morris International Inc. | C106: Quant | D106: Sell to Close | E106: -22 | F106: 90.18 | G106: 45350 | H106: -0.0049652433 | I106: =F106*E106*-1 -> 1983.96
...

Sheet Target Allocations Fall 2024
A1: Sector | B1: Current Weight of the Portfolio | C1: Target Weight of the Portfolio | D1: % Overweight / (Underweight) | E1: $ Overweight / (Underweight)
A2: Consumer Discretionary | B2: ='Sector Holdings'!I8 -> 0.073680273 | C2: 0.08 | D2: =B2-C2 -> -0.0063197275 | E2: =D2*'Sector Holdings'!$H$121 -> -16846.419
A3: Consumer Staples | B3: ='Sector Holdings'!I15 -> 0.052005479 | C3: 0.06 | D3: =B3-C3 -> -0.0079945215 | E3: =D3*'Sector Holdings'!$H$121 -> -21310.897
A4: Energy | B4: ='Sector Holdings'!I23 -> 0.057907791 | C4: 0.05 | D4: =B4-C4 -> 0.0079077905 | E4: =D4*'Sector Holdings'!$H$121 -> 21079.699
A5: Financials | B5: ='Sector Holdings'!I33 -> 0.11412727 | C5: 0.11 | D5: =B5-C5 -> 0.0041272718 | E5: =D5*'Sector Holdings'!$H$121 -> 11002.017
A6: Healthcare | B6: ='Sector Holdings'!I42 -> 0.098908705 | C6: 0.105 | D6: =B6-C6 -> -0.006091295 | E6: =D6*'Sector Holdings'!$H$121 -> -16237.49
A7: Industrials | B7: ='Sector Holdings'!I50 -> 0.079285509 | C7: 0.075 | D7: =B7-C7 -> 0.0042855092 | E7: =D7*'Sector Holdings'!$H$121 -> 11423.829
A8: REITs | B8: ='Sector Holdings'!I56 -> 0.01605977 | C8: 0.03 | D8: =B8-C8 -> -0.01394023 | E8: =D8*'Sector Holdings'!$H$121 -> -37160.298
A9: Technology | B9: ='Sector Holdings'!I66 -> 0.2096609 | C9: 0.19 | D9: =B9-C9 -> 0.019660902 | E9: =D9*'Sector Holdings'!$H$121 -> 52409.823
A10: Media and Telecom | B10: ='Sector Holdings'!I72 -> 0.061311295 | C10: 0.055 | D10: =B10-C10 -> 0.0063112951 | E10: =D10*'Sector Holdings'!$H$121 -> 16823.941
A11: Utilities | B11: ='Sector Holdings'!I79 -> 0.027306065 | C11: 0.025 | D11: =B11-C11 -> 0.0023060653 | E11: =D11*'Sector Holdings'!$H$121 -> 6147.2496
A12: Quant | B12: ='Sector Holdings'!I98 -> 0.020075991 | C12: 0.02 | D12: =B12-C12 -> 7.5990787e-05 | E12: =D12*'Sector Holdings'!$H$121 -> 202.5677
A13: Equities Total | B13: =SUM(B2:B12) -> 0.81032905 | C13: =SUM(C2:C12) -> 0.8 | D13: =B13-C13 -> 0.010329051 | E13: =D13*'Sector Holdings'!$H$121 -> 27534.023
A14: Fixed Income | B14: ='Sector Holdings'!I116 -> 0.14 | C14: 0.15 | D14: =B14-C14 -> -0.01 | E14: =D14*'Sector Holdings'!$H$121 -> -26656.876
A15: Total Cash | B15: ='Sector Holdings'!I118 -> 0.054049094 | C15: 0.05 | D15: =B15-C15 -> 0.0040490938 | E15: =D15*'Sector Holdings'!$H$121 -> 10793.619
A16: Total | B16: =SUM(B2:B15)-B13-'Sector Holdings'!I115 -> 1 | C16: =SUM(C2:C15)-C13 -> 1 | D16: =B16-C16 -> 0 | E16: =D16*'Sector Holdings'!$H$121 -> -2.9595078e-10

Sheet Fall 2023 Trades
A1: SSF | B1: Description | C1: Sector | D1: Trade Type | E1: Shares | F1: Trade Price | G1: Trade Date | H1: % Gain on Sale | I1: Cash Gain/Loss
A2: XLP | B2: SPDR Consumer Staples ETF | C2: Consumer Staples | D2: Sell to Trim | E2: -102 | F2: 73.03 | G2: 45168 | H2: 0.00068511921 | I2: =F2*E2*-1 -> 7449.06
A3: XLE | B3: SPDR Energy ETF | C3: Energy | D3: Sell to Trim | E3: -51 | F3: 88.85 | G3: 45168 | H3: 0.10716511 | I3: =F3*E3*-1 -> 4531.35
A4: XLK | B4: SPDR Technology ETF | C4: Technology | D4: Sell to Trim | E4: -69 | F4: 174.42 | G4: 45168 | H4: 0.21420118 | I4: =F4*E4*-1 -> 12034.98
A5: ICE | B5: Intercontinental Exchange Inc | C5: Financials | D5: Sell to Trim | E5: -32 | F5: 118.01 | G5: 45168 | H5: 2.0407112 | I5: =F5*E5*-1 -> 3776.32
A6: MS | B6: Morgan Stanley | C6: Financials | D6: Sell to Trim | E6: -42 | F6: 85.43 | G6: 45168 | H6: 0.16342095 | I6: =F6*E6*-1 -> 3588.06
A7: PFG | B7: Principal Financial Group Inc | C7: Financials | D7: Sell to Trim | E7: -34 | F7: 78.13 | G7: 45168 | H7: 0.70366332 | I7: =F7*E7*-1 -> 2656.42
A8: NNI | B8: Nelnet Inc | C8: Financials | D8: Sell to Trim | E8: -48 | F8: 91.9 | G8: 45168 | H8: 0.23041907 | I8: =F8*E8*-1 -> 4411.2
A9: FI | B9: Fiserv Inc | C9: Financials | D9: Sell to Trim | E9: -41 | F9: 122.59 | G9: 45168 | H9: 0.2449477 | I9: =F9*E9*-1 -> 5026.19
A10: ACGL | B10: Arch Capital Group Ltd | C10: Financials | D10: Sell to Trim | E10: -62 | F10: 77.35 | G10: 45168 | H10: 0.64749734 | I10: =F10*E10*-1 -> 4795.7
A11: PLD | B11: Prologis Inc. | C11: REITs | D11: Sell to Trim | E11: -57 | F11: 125.11 | G11: 45168 | H11: 0.96097179 | I11: =F11*E11*-1 -> 7131.27
A12: CPT | B12: Camden Properties Trust | C12: REITs | D12: Sell to Trim | E12: -27 | F12: 107.83 | G12: 45168 | H12: 0.15486773 | I12: =F12*E12*-1 -> 2911.41
A13: IRM | B13: Iron Mountain, Inc. | C13: REITs | D13: Sell to Trim | E13: -74 | F13: 63.45 | G13: 45168 | H13: 0.3874918 | I13: =F13*E13*-1 -> 4695.3
... A24: CWEN | B24: Clearway Energy Inc. | C24: Utilities | D24: Sell to Trim | E24: -144 | F24: 25.31 | G24: 45168 | H24: -0.20107323 | I24: =F24*E24*-1 -> 3644.64
A25: BKI | B25: Black Knight Inc. | C25: Financials | D25: Sell to Close | E25: -417 | F25: 75.81 | G25: 45170 | H25: 0.34845251 | I25: =F25*E25*-1 -> 31612.77 | J25: 1
A26: XLF | B26: SPDR Financials ETF | C26: Financials | D26: Buy to Open | E26: 912 | F26: 34.68 | G26: 45170 | H26: N/A | I26: =F26*E26*-1 -> -31628.16
A27: FOXA | B27: Fox Corp Class A | C27: Quant | D27: Sell to Close | E27: -118 | F27: 31.52 | G27: 45175 | H27: -0.11286237 | I27: =F27*E27*-1 -> 3719.36 | J27: 2
A28: LEN | B28: Lennar Corp | C28: Quant | D28: Sell to Close | E28: -38 | F28: 116.96 | G28: 45175 | H28: 0.15254237 | I28: =F28*E28*-1 -> 4444.48
A29: HPE | B29: Hewlett Packard Enterprise | C29: Quant | D29: Sell to Close | E29: -259 | F29: 17.78 | G29: 45175 | H29: 0.19009371 | I29: =F29*E29*-1 -> 4605.02
A30: BG | B30: Bunge Ltd | C30: Quant | D30: Sell to Close | E30: -40 | F30: 110.55 | G30: 45175 | H30: 0.14310826 | I30: =F30*E30*-1 -> 4422
A31: MPC | B31: Marathon Petroleum Corp | C31: Quant | D31: Sell to Close | E31: -45 | F31: 147.65 | G31: 45175 | H31: 0.12581014 | I31: =F31*E31*-1 -> 6644.25
A32: LYB | B32: Lyondell Basell Industries | C32: Quant | D32: Sell to Close | E32: -21 | F32: 100.07 | G32: 45175 | H32: 0.058157978 | I32: =F32*E32*-1 -> 2101.47
A33: BWA | B33: Borg Warner Inc | C33: Quant | D33: Sell to Close | E33: -43 | F33: 40.5 | G33: 45175 | H33: 0.03079664 | I33: =F33*E33*-1 -> 1741.5
A34: FANG | B34: Diamondback Energy Inc | C34: Quant | D34: Sell to Close | E34: -14 | F34: 155.92 | G34: 45175 | H34: 1.1130234 | I34: =F34*E34*-1 -> 2182.88
A35: FLT | B35: Fleetcor Technologies Inc | C35: Quant | D35: Sell to Close | E35: -10 | F35: 275.17 | G35: 45175 | H35: 0.32303446 | I35: =F35*E35*-1 -> 2751.7
A36: HST | B36: Host Hotels & Resorts Inc | C36: Quant | D36: Sell to Close | E36: -124 | F36: 16.02 | G36: 45175 | H36: -0.0016203415 | I36: =F36*E36*-1 -> 1986.48
A37: LKQ | B37: LKQ Corp | C37: Quant | D37: Sell to Close | E37: -37 | F37: 50.95 | G37: 45175 | H37: -0.061486885 | I37: =F37*E37*-1 -> 1885.15
A38: REG | B38: Regency Centers Corp | C38: Quant | D38: Sell to Close | E38: -33 | F38: 63.33 | G38: 45175 | H38: 0.055324113 | I38: =F38*E38*-1 -> 2089.89
A39: WY | B39: Weyerhaeuser Co | C39: Quant | D39: Sell to Close | E39: -67 | F39: 32.36 | G39: 45175 | H39: 0.086059109 | I39: =F39*E39*-1 -> 2168.12
A40: ZBRA | B40: Zebra Technologies Co | C40: Quant | D40: Sell to Close | E40: -7 | F40: 271.42 | G40: 45175 | H40: -0.12567848 | I40: =F40*E40*-1 -> 1899.94
A41: SRE | B41: Sempra | C41: Quant | D41: Buy to Open | E41: 29 | F41: 69.375 | G41: 45175 | H41: N/A | I41: =F41*E41*-1 -> -2011.875 | J41: 3
A42: ADM | B42: Archer-Daniels-Midland Co | C42: Quant | D42: Buy to Open | E42: 26 | F42: 77.34 | G42: 45175 | H42: N/A | I42: =F42*E42*-1 -> -2010.84
A43: HST | B43: Host Hotels & Resorts Inc | C43: Quant | D43: Buy to Open | E43: 126 | F43: 16 | G43: 45175 | H43: N/A | I43: =F43*E43*-1 -> -2016
A44: PFE | B44: Pfizer Inc | C44: Quant | D44: Buy to Open | E44: 59 | F44: 34.41 | G44: 45175 | H44: N/A | I44: =F44*E44*-1 -> -2030.19
A45: NI | B45: NiSource Inc | C45: Quant | D45: Buy to Open | E45: 77 | F45: 26.2 | G45: 45175 | H45: N/A | I45: =F45*E45*-1 -> -2017.4
A46: LKQ | B46: LKQ Corp | C46: Quant | D46: Buy to Open | E46: 40 | F46: 50.9 | G46: 45175 | H46: N/A | I46: =F46*E46*-1 -> -2036
A47: PM | B47: Philip Morris International Inc | C47: Quant | D47: Buy to Open | E47: 22 | F47: 93.67 | G47: 45175 | H47: N/A | I47: =F47*E47*-1 -> -2060.74
A48: WY | B48: Weyerhaeuser Co | C48: Quant | D48: Buy to Open | E48: 62 | F48: 32.31 | G48: 45175 | H48: N/A | I48: =F48*E48*-1 -> -2003.22
A49: OGN | B49: Organon & Co | C49: Quant | D49: Buy to Open | E49: 101 | F49: 19.94 | G49: 45175 | H49: N/A | I49: =F49*E49*-1 -> -2013.94
A50: MRNA | B50: Moderna Inc | C50: Quant | D50: Buy to Open | E50: 19 | F50: 107.53 | G50: 45175 | H50: N/A | I50: =F50*E50*-1 -> -2043.07
A51: PXD | B51: Pioneer Natural Resources Co | C51: Quant | D51: Buy to Open | E51: 17 | F51: 241.32 | G51: 45175 | H51: N/A | I51: =F51*E51*-1 -> -4102.44
A52: MPC | B52: Marathon Petroleum Corp | C52: Quant | D52: Buy to Open | E52: 27 | F52: 147.66 | G52: 45175 | H52: N/A | I52: =F52*E52*-1 -> -3986.82
A53: VNO | B53: Vornado Realty Trust | C53: Quant | D53: Buy to Open | E53: 165 | F53: 24.52 | G53: 45175 | H53: N/A | I53: =F53*E53*-1 -> -4045.8
... A55: NRG | B55: NRG Energy Inc | C55: Quant | D55: Buy to Open | E55: 106 | F55: 37.88 | G55: 45175 | H55: N/A | I55: =F55*E55*-1 -> -4015.28
A56: RTX | B56: Raytheon Technologies Co | C56: Industrials | D56: Sell to Close | E56: -193 | F56: 83.41 | G56: 45177 | H56: 0.0716 | I56: =F56*E56*-1 -> 16098.13 | J56: 4
A57: 912797LL9 | B57: US TREAS BILLS ZERO CPN 0.00% 03/21/2024 | C57: Fixed Income | D57: Buy to Open | E57: 83 | F57: 972.78 | G57: 45177 | H57: N/A | I57: =F57*E57*-1 -> -80740.74 | J57: 5
A58: XLI | B58: SPDR Industrials ETF | C58: Industrials | D58: Buy to Open | E58: 152 | F58: 105.7556 | G58: 45181 | H58: N/A | I58: =F58*E58*-1 -> -16074.851
A59: HD | B59: Home Depot Inc/The | C59: Consumer Discretionary | D59: Sell to Close | E59: -91 | F59: 306.02 | G59: 45191 | H59: 3.9832275 | I59: =F59*E59*-1 -> 27847.82 | J59: 6
A60: WBD | B60: Warner Bros. Discovery, Inc. | C60: Media & Telecom | D60: Sell to Close | E60: -1632 | F60: 11.1207 | G60: 45191 | H60: -0.26741107 | I60: =F60*E60*-1 -> 18148.982 | J60: 7
A61: VMD | B61: Viemed Healthcare Inc | C61: Healthcare | D61: Sell to Close | E61: -2945 | F61: 7.1658 | G61: 45191 | H61: -0.21685246 | I61: =F61*E61*-1 -> 21103.281 | J61: 8
A62: AWK | B62: American Water Works Company, Inc. | C62: Utilities | D62: Sell to Close | E62: -100 | F62: 133.38 | G62: 45191 | H62: -0.092344335 | I62: =F62*E62*-1 -> 13338 | J62: 9
A63: XLU | B63: SPDR Utilities ETF | C63: Utilities | D63: Buy to Open | E63: 210 | F63: 63.48 | G63: 45191 | H63: N/A | I63: =F63*E63*-1 -> -13330.8
A64: XLV | B64: SPDR Healthcare ETF | C64: Healthcare | D64: Buy to Add | E64: 162 | F64: 130.33 | G64: 45191 | H64: N/A | I64: =F64*E64*-1 -> -21113.46
A65: XLC | B65: SPDR Communications Services ETF | C65: Media & Telecom | D65: Buy to Open | E65: 276 | F65: 65.78 | G65: 45191 | H65: N/A | I65: =F65*E65*-1 -> -18155.28
A66: XLY | B66: SPDR Discretionary ETF | C66: Consumer Staples | D66: Buy to Open | E66: 173 | F66: 160.97 | G66: 45191 | H66: N/A | I66: =F66*E66*-1 -> -27847.81
A67: IRM | B67: Iron Mountain Inc. | C67: REITs | D67: Sell to Close | E67: -237 | F67: 59.7 | G67: 45198 | H67: 0.30548874 | I67: =F67*E67*-1 -> 14148.9 | J67: 10
A68: XLI | B68: SPDR Industrials ETF | C68: Industrials | D68: Sell to Close | E68: -152 | F68: 101.17 | G68: 45198 | H68: -0.043400151 | I68: =F68*E68*-1 -> 15377.84
A69: XLRE | B69: SPDR REITs ETF | C69: REITs | D69: Buy to Open | E69: 416 | F69: 33.97 | G69: 45198 | H69: N/A | I69: =F69*E69*-1 -> -14131.52
A70: ATKR | B70: Atkore Inc | C70: Industrials | D70: Buy to Open | E70: 103 | F70: 149.02 | G70: 45198 | H70: N/A | I70: =F70*E70*-1 -> -15349.06 | J70: 11
A71: XLP | B71: SPDR Consumer Staples ETF | C71: Consumer Staples | D71: Sell to Trim | E71: -443 | F71: 66.435 | G71: 45212 | H71: =IF(OR(D71="Sell to Trim", D71="Sell to Close"),F71/VLOOKUP(A71, 'Sector Holdings'!$B$3:$M$121, 11, FALSE) - 1, "N/A") -> -0.089682105 | I71: =F71*E71*-1 -> 29430.705
A72: XLF | B72: SPDR Financials ETF | C72: Financials | D72: Sell to Close | E72: -912 | F72: 33.252 | G72: 45212 | H72: =IF(OR(D72="Sell to Trim", D72="Sell to Close"),F72/VLOOKUP(A72, 'Sector Holdings'!$B$3:$M$121, 11, FALSE) - 1, "N/A") -> -0.14055311 | I72: =F72*E72*-1 -> 30325.824
A73: POST | B73: N/A | C73: Consumer Staples | D73: Buy to Open | E73: 363 | F73: 81.03 | G73: 45212 | H73: N/A | I73: =F73*E73*-1 -> -29413.89 | J73: 12
A74: AGM | B74: N/A | C74: Financials | D74: Buy to Open | E74: 206 | F74: 147.16 | G74: 45212 | H74: N/A | I74: =F74*E74*-1 -> -30314.96 | J74: 13
A75: 71654QBV3 | B75: N/A | C75: Fixed Income | D75: Buy to Open | E75: 30 | F75: 963.91 | G75: 45212 | H75: N/A | I75: =F75*E75*-1 -> -28917.3 | J75: 14
A76: PXD | B76: Pioneer Natural Resources Co | C76: Quant | D76: Sell to Close | E76: -17 | F76: 255.63 | G76: 45218 | H76: 0.059298856 | I76: =F76*E76*-1 -> 4345.71 | J76: 15
A77: MPC | B77: Marathon Petroleum Corp | C77: Quant | D77: Sell to Close | E77: -27 | F77: 152.97 | G77: 45218 | H77: 0.035960991 | I77: =F77*E77*-1 -> 4130.19
A78: VNO | B78: Vornado Realty Trust | C78: Quant | D78: Sell to Close | E78: -165 | F78: 20.4 | G78: 45218 | H78: -0.1680261 | I78: =F78*E78*-1 -> 3366
A79: CF | B79: CF Industries Holdings Inc | C79: Quant | D79: Sell to Close | E79: -50 | F79: 85.54 | G79: 45218 | H79: 0.056049383 | I79: =F79*E79*-1 -> 4277
A80: NRG | B80: NRG Energy Inc | C80: Quant | D80: Sell to Close | E80: -106 | F80: 41.15 | G80: 45218 | H80: 0.086325238 | I80: =F80*E80*-1 -> 4361.9
A81: SRE | B81: Sempra | C81: Quant | D81: Sell to Close | E81: -29 | F81: 69.74 | G81: 45218 | H81: 0.0052612613 | I81: =F81*E81*-1 -> 2022.46
A82: ADM | B82: Archer-Daniels-Midland Co | C82: Quant | D82: Sell to Close | E82: -26 | F82: 73.74 | G82: 45218 | H82: -0.046547711 | I82: =F82*E82*-1 -> 1917.24
A83: HST | B83: Host Hotels & Resorts Inc | C83: Quant | D83: Sell to Close | E83: -126 | F83: 15.79 | G83: 45218 | H83: -0.013125 | I83: =F83*E83*-1 -> 1989.54
A84: PFE | B84: Pfizer Inc | C84: Quant | D84: Sell to Close | E84: -59 | F84: 31.12 | G84: 45218 | H84: -0.095611741 | I84: =F84*E84*-1 -> 1836.08
A85: NI | B85: NiSource Inc | C85: Quant | D85: Sell to Close | E85: -77 | F85: 25.83 | G85: 45218 | H85: -0.014122137 | I85: =F85*E85*-1 -> 1988.91
A86: LKQ | B86: LKQ Corp | C86: Quant | D86: Sell to Close | E86: -40 | F86: 48.97 | G86: 45218 | H86: -0.037917485 | I86: =F86*E86*-1 -> 1958.8
A87: PM | B87: Philip Morris International Inc. | C87: Quant | D87: Sell to Close | E87: -22 | F87: 90.69 | G87: 45218 | H87: -0.0314 | I87: =F87*E87*-1 -> 1995.18
A88: WY | B88: Weyerhaeuser Co | C88: Quant | D88: Sell to Close | E88: -62 | F88: 29.32 | G88: 45218 | H88: -0.092541009 | I88: =F88*E88*-1 -> 1817.84
... A90: MRNA | B90: Moderna Inc | C90: Quant | D90: Sell to Close | E90: -19 | F90: 80.96 | G90: 45218 | H90: -0.24709383 | I90: =F90*E90*-1 -> 1538.24
A91: CI | B91: Cigna Group | C91: Quant | D91: Buy to Open | E91: 13 | F91: 308.52 | G91: 45218 | H91: N/A | I91: =F91*E91*-1 -> -4010.76 | J91: 16
A92: NRG | B92: NRG Energy Inc | C92: Quant | D92: Buy to Open | E92: 95 | F92: 40.99 | G92: 45218 | H92: N/A | I92: =F92*E92*-1 -> -3894.05
A93: CTRA | B93: Coterra Energy Inc | C93: Quant | D93: Buy to Open | E93: 132 | F93: 29.54 | G93: 45218 | H93: N/A | I93: =F93*E93*-1 -> -3899.28
A94: WRK | B94: Westrock Co | C94: Quant | D94: Buy to Open | E94: 110 | F94: 35.52 | G94: 45218 | H94: N/A | I94: =F94*E94*-1 -> -3907.2
A95: DXC | B95: DXC Technology Co | C95: Quant | D95: Buy to Open | E95: 188 | F95: 20.66 | G95: 45218 | H95: N/A | I95: =F95*E95*-1 -> -3884.08
A96: GM | B96: General Motors Co | C96: Quant | D96: Buy to Open | E96: 66 | F96: 29.38 | G96: 45218 | H96: N/A | I96: =F96*E96*-1 -> -1939.08
A97: PFE | B97: Pfizer Inc | C97: Quant | D97: Buy to Open | E97: 63 | F97: 31.13 | G97: 45218 | H97: N/A | I97: =F97*E97*-1 -> -1961.19
A98: VFC | B98: VF Corp | C98: Quant | D98: Buy to Open | E98: 105 | F98: 18.57 | G98: 45218 | H98: N/A | I98: =F98*E98*-1 -> -1949.85
A99: WY | B99: Weyerhaeuser Co | C99: Quant | D99: Buy to Open | E99: 66 | F99: 29.44 | G99: 45218 | H99: N/A | I99: =F99*E99*-1 -> -1943.04
A100: TRMB | B100: Trimble Inc | C100: Quant | D100: Buy to Open | E100: 39 | F100: 49.89 | G100: 45218 | H100: N/A | I100: =F100*E100*-1 -> -1945.71
A101: BWA | B101: BorgWarner Inc | C101: Quant | D101: Buy to Open | E101: 52 | F101: 38 | G101: 45218 | H101: N/A | I101: =F101*E101*-1 -> -1976
A102: OGN | B102: Organon & Co | C102: Quant | D102: Buy to Open | E102: 121 | F102: 16.07 | G102: 45218 | H102: N/A | I102: =F102*E102*-1 -> -1944.47
A103: PM | B103: Philip Morris International Inc. | C103: Quant | D103: Buy to Open | E103: 21 | F103: 90.63 | G103: 45218 | H103: N/A | I103: =F103*E103*-1 -> -1903.23
... A105: MO | B105: Altria Group Inc | C105: Quant | D105: Buy to Open | E105: 45 | F105: 42.63 | G105: 45218 | H105: N/A | I105: =F105*E105*-1 -> -1918.35
A106: XLY | B106: SPDR Discretionary ETF | C106: Consumer Discretionary | D106: Sell to Close | E106: -173 | F106: 152.81 | G106: 45219 | H106: -0.14987483 | I106: =F106*E106*-1 -> 26436.13
A107: EVVTY | B107: Evolution ADR | C107: Consumer Discretionary | D107: Buy to Open | E107: 281 | F107: 93.93 | G107: 45219 | H107: N/A | I107: =F107*E107*-1 -> -26394.33 | J107: 17
A108: XLV | B108: SPDR Healthcare ETF | C108: Healthcare | D108: Sell to Close | E108: -240 | F108: 124.44 | G108: 45226 | H108: -0.065485131 | I108: =F108*E108*-1 -> 29865.6
A109: BLCO | B109: Bausch and Lomb Corp | C109: Healthcare | D109: Buy to Open | E109: 1886 | F109: 15.855 | G109: 45226 | H109: N/A | I109: =F109*E109*-1 -> -29902.53 | J109: 18
A110: XLRE | B110: SPDR REITs ETF | C110: REITs | D110: Sell to Close | E110: -416 | F110: 32.55 | G110: 45226 | H110: -0.04180159 | I110: =F110*E110*-1 -> 13540.8
A111: VICI | B111: Vici Properties Inc | C111: REITs | D111: Buy to Open | E111: 494 | F111: 27.43 | G111: 45226 | H111: N/A | I111: =F111*E111*-1 -> -13550.42 | J111: 19
A112: 3133EKMF0 | B112: FFCB 3.50 03/02/2034 | C112: Fixed Income | D112: Buy to Open | E112: 33 | F112: 854.34 | G112: 45230 | H112: N/A | I112: =F112*E112*-1 -> -28193.22 | J112: 20
A113: MS | B113: Morgan Stanley | C113: Financials | D113: Sell to Close | E113: -279 | F113: 75.26 | G113: 45237 | H113: 0.024921694 | I113: =F113*E113*-1 -> 20997.54 | J113: 21
...

Sheet Spring 2023 Trades
A1: SSF | B1: Description | C1: Sector | D1: Trade Type | E1: Shares | F1: Trade Price | G1: Trade Date | H1: % Gain on Sale | I1: Cash Gain/Loss
A2: XLP | B2: =VLOOKUP(A2, 'Sector Holdings'!B3:C121, 2, FALSE) -> SPDR Consumer Staples ETF | C2: Consumer Staples | D2: Buy to Add | E2: 159 | F2: 72.93 | G2: 44949 | H2: =IF(OR(D2="Sell to Trim", D2="Sell to Close"),F2/VLOOKUP(A2, 'Sector Holdings'!$B$3:$M$121, 11, FALSE) - 1, "N/A") -> N/A | I2: =F2*E2*-1 -> -11595.87
A3: ACGL | B3: =VLOOKUP(A3, 'Sector Holdings'!B4:C122, 2, FALSE) -> Arch Capital Group Ltd | C3: Financials | D3: Sell to Trim | E3: -126 | F3: 62.74 | G3: 44949 | H3: =IF(OR(D3="Sell to Trim", D3="Sell to Close"),F3/VLOOKUP(A3, 'Sector Holdings'!$B$3:$M$121, 11, FALSE) - 1, "N/A") -> 0.13783098 | I3: =F3*E3*-1 -> 7905.24
A4: HZNP | B4: Horizon Therapeutics | C4: Healthcare | D4: Sell to Close | E4: -365 | F4: 113 | G4: 44949 | H4: 0.46032567 | I4: =F4*E4*-1 -> 41245
A5: XLV | B5: =VLOOKUP(A5, 'Sector Holdings'!$B$4:$C$124, 2, FALSE) -> SPDR Healthcare ETF | C5: Healthcare | D5: Buy to Add | E5: 204 | F5: 135 | G5: 44949 | H5: =IF(OR(D5="Sell to Trim", D5="Sell to Close"),F5/VLOOKUP(A5, 'Sector Holdings'!$B$3:$M$121, 11, FALSE) - 1, "N/A") -> N/A | I5: =F5*E5*-1 -> -27540
A6: XLI | B6: SPDR Industrials ETF | C6: Industrials | D6: Sell to Close | E6: -378 | F6: 100.12 | G6: 44949 | H6: 0.007851822 | I6: =F6*E6*-1 -> 37845.36
A7: PLD | B7: =VLOOKUP(A7, 'Sector Holdings'!$B$4:$C$124, 2, FALSE) -> Prologis Inc. | C7: REITs | D7: Sell to Trim | E7: -56 | F7: 124.71 | G7: 44949 | H7: 0.94040766 | I7: =F7*E7*-1 -> 6983.76
A8: XLK | B8: =VLOOKUP(A8, 'Sector Holdings'!$B$4:$C$124, 2, FALSE) -> SPDR Technology ETF | C8: Technology | D8: Buy to Add | E8: 88 | F8: 134.28 | G8: 44949 | H8: =IF(OR(D8="Sell to Trim", D8="Sell to Close"),F8/VLOOKUP(A8, 'Sector Holdings'!$B$3:$M$121, 11, FALSE) - 1, "N/A") -> N/A | I8: =F8*E8*-1 -> -11816.64
A9: XLU | B9: =VLOOKUP(A9, 'Sector Holdings'!$B$4:$C$124, 2, FALSE) -> SPDR Utilities ETF | C9: Utilities | D9: Buy to Add | E9: 71 | F9: 69.63 | G9: 44949 | H9: =IF(OR(D9="Sell to Trim", D9="Sell to Close"),F9/VLOOKUP(A9, 'Sector Holdings'!$B$3:$M$121, 11, FALSE) - 1, "N/A") -> N/A | I9: =F9*E9*-1 -> -4943.73
A10: AGG | B10: =VLOOKUP(A10, 'Sector Holdings'!$B$4:$C$124, 2, FALSE) -> iShares Aggregate Bond ETF | C10: Fixed Income | D10: Buy to Add | E10: 98 | F10: 100.04 | G10: 44949 | H10: =IF(OR(D10="Sell to Trim", D10="Sell to Close"),F10/VLOOKUP(A10, 'Sector Holdings'!$B$3:$M$121, 11, FALSE) - 1, "N/A") -> N/A | I10: =F10*E10*-1 -> -9803.92
A11: CAH | B11: Cardinal Health Inc | C11: Quant | D11: Sell to Close | E11: -50 | F11: 74.9 | G11: 44950 | H11: -0.06228482 | I11: =F11*E11*-1 -> 3745
A12: HIG | B12: Hartford Financial Services | C12: Quant | D12: Sell to Close | E12: -53 | F12: 76.75 | G12: 44950 | H12: 0.035692598 | I12: =F12*E12*-1 -> 4067.75
A13: HPE | B13: Hewlett Packard | C13: Quant | D13: Sell to Close | E13: -247 | F13: 16.185 | G13: 44950 | H13: 0.034185304 | I13: =F13*E13*-1 -> 3997.695
A14: VTRS | B14: Viatris Inc | C14: Quant | D14: Sell to Close | E14: -353 | F14: 11.665 | G14: 44950 | H14: 0.067246112 | I14: =F14*E14*-1 -> 4117.745
A15: LEN | B15: Lennar | C15: Quant | D15: Sell to Trim | E15: -3 | F15: 98.94 | G15: 44950 | H15: 0.081547879 | I15: =F15*E15*-1 -> 296.82
A16: DAL | B16: Delta Air Lines Inc | C16: Quant | D16: Buy to Open | E16: 102 | F16: 38.93 | G16: 44950 | H16: N/A | I16: =F16*E16*-1 -> -3970.86
A17: DOW | B17: Dow Inc | C17: Quant | D17: Buy to Open | E17: 68 | F17: 58.11 | G17: 44950 | H17: N/A | I17: =F17*E17*-1 -> -3951.48
A18: FDX | B18: Fedex Corp | C18: Quant | D18: Buy to Open | E18: 21 | F18: 189.647 | G18: 44950 | H18: N/A | I18: =F18*E18*-1 -> -3982.587
A19: MHK | B19: Mohawk Industries | C19: Quant | D19: Buy to Open | E19: 34 | F19: 116.61 | G19: 44950 | H19: N/A | I19: =F19*E19*-1 -> -3964.74
A20: DBX | B20: Dropbox Inc. | C20: Technology | D20: Sell to Close | E20: -1144 | F20: 23.33 | G20: 44953 | H20: 0.15 | I20: =F20*E20*-1 -> 26689.52
A21: XLK | B21: =VLOOKUP(A21, 'Sector Holdings'!$B$4:$C$124, 2, FALSE) -> SPDR Technology ETF | C21: Technology | D21: Buy to Add | E21: 197 | F21: 135.76 | G21: 44953 | H21: =IF(OR(D21="Sell to Trim", D21="Sell to Close"),F21/VLOOKUP(A21, 'Sector Holdings'!$B$3:$M$121, 11, FALSE) - 1, "N/A") -> N/A | I21: =F21*E21*-1 -> -26744.72
A22: LH | B22: Laboratory Corporation of America Holdings | C22: Healthcare | D22: Sell to Close | E22: -160 | F22: 253.1 | G22: 44953 | H22: 0.77 | I22: =F22*E22*-1 -> 40496
A23: XLV | B23: =VLOOKUP(A23, 'Sector Holdings'!$B$4:$C$124, 2, FALSE) -> SPDR Healthcare ETF | C23: Healthcare | D23: Buy to Add | E23: 304 | F23: 132.99 | G23: 44953 | H23: =IF(OR(D23="Sell to Trim", D23="Sell to Close"),F23/VLOOKUP(A23, 'Sector Holdings'!$B$3:$M$121, 11, FALSE) - 1, "N/A") -> N/A | I23: =F23*E23*-1 -> -40428.96
A24: MODV | B24: Modivcare Inc | C24: Healthcare | D24: Sell to Close | E24: -99 | F24: 114.51 | G24: 44960 | H24: -0.2852 | I24: =F24*E24*-1 -> 11336.49
A25: XLV | B25: =VLOOKUP(A25, 'Sector Holdings'!$B$4:$C$124, 2, FALSE) -> SPDR Healthcare ETF | C25: Healthcare | D25: Buy to Add | E25: 85 | F25: 133.16 | G25: 44960 | H25: N/A | I25: =F25*E25*-1 -> -11318.6
A26: DEO | B26: Diageo | C26: Consumer Staples | D26: Sell to Close | E26: -154 | F26: 170.7 | G26: 44967 | H26: 0.255 | I26: =F26*E26*-1 -> 26287.8
A27: XLP | B27: =VLOOKUP(A27, 'Sector Holdings'!$B$4:$C$124, 2, FALSE) -> SPDR Consumer Staples ETF | C27: Consumer Staples | D27: Buy to Add | E27: 364 | F27: 72.24 | G27: 44967 | H27: N/A | I27: =F27*E27*-1 -> -26295.36
A28: MPW | B28: Medical Properties Trust | C28: REITs | D28: Sell to Close | E28: -745 | F28: 11.92 | G28: 44967 | H28: -0.0967 | I28: =F28*E28*-1 -> 8880.4
A29: XLRE | B29: =VLOOKUP(A29, 'Sector Holdings'!$B$4:$C$124, 2, FALSE) -> SPDR REITs ETF | C29: REITs | D29: Buy to Open | E29: 223 | F29: 39.84 | G29: 44967 | H29: N/A | I29: =F29*E29*-1 -> -8884.32
A30: 912796Y37 | B30: =VLOOKUP(A30, 'Sector Holdings'!$B$4:$C$124, 2, FALSE) -> #N/A | C30: Fixed Income | D30: Buy to Open | E30: 100 | F30: 977.81 | G30: 44967 | H30: N/A | I30: =F30*E30*-1 -> -97781
A31: AGG | B31: =VLOOKUP(A31, 'Sector Holdings'!$B$4:$C$124, 2, FALSE) -> iShares Aggregate Bond ETF | C31: Fixed Income | D31: Sell to Close | E31: -293 | F31: 98.44 | G31: 44967 | H31: -0.0678 | I31: =F31*E31*-1 -> 28842.92
A32: XLY | B32: SPDR Discretionary ETF | C32: Consumer Discretionary | D32: Sell to Close | E32: -41 | F32: 146.39 | G32: 44979 | H32: -0.19 | I32: =F32*E32*-1 -> 6001.99
A33: AMZN | B33: Amazon.com INc. | C33: Consumer Discretionary | D33: Buy to Add | E33: 62 | F33: 96.21 | G33: 44979 | H33: N/A | I33: =F33*E33*-1 -> -5965.02
A34: NEE | B34: NextEra Energy Inc | C34: Utilities | D34: Sell to Trim | E34: -109 | F34: 73.79 | G34: 44979 | H34: 0.81 | I34: =F34*E34*-1 -> 8043.11
A35: XLU | B35: SPDR Utilities ETF | C35: Utilities | D35: Buy to Add | E35: 120 | F35: 67.17 | G35: 44979 | H35: N/A | I35: =F35*E35*-1 -> -8060.4
A36: PYPL | B36: PayPal Holdings Inc | C36: Technology | D36: Sell to Close | E36: -216 | F36: 75.98 | G36: 44979 | H36: -0.4674 | I36: =F36*E36*-1 -> 16411.68
A37: XLK | B37: SPDR Technology ETF | C37: Technology | D37: Buy to Add | E37: 119 | F37: 136.98 | G37: 44979 | H37: N/A | I37: =F37*E37*-1 -> -16300.62
A38: XLC | B38: SPDR Communications Services ETF | C38: Media & Telecom | D38: Sell to Close | E38: -502 | F38: 54.32 | G38: 44979 | H38: -0.2135 | I38: =F38*E38*-1 -> 27268.64
A39: WBD | B39: Warner Bros Discovery Inc. | C39: Media & Telecom | D39: Buy to Add | E39: 1800 | F39: 15.18 | G39: 44979 | H39: N/A | I39: =F39*E39*-1 -> -27324
A40: SHYD | B40: VanEck Short High Yield Muni ETF | C40: Fixed Income | D40: Sell to Close | E40: -1433 | F40: 22.12 | G40: 44981 | H40: -0.11 | I40: =F40*E40*-1 -> 31697.96
A41: 50077LAD8 | B41: KHC 3.0 06/01/2026 | C41: Fixed Income | D41: Sell to Close | E41: -25 | F41: 930.28 | G41: 44981 | H41: N/A | I41: =F41*E41*-1 -> 23257
A42: DOW | B42: Dow Inc | C42: Quant | D42: Sell to Close | E42: -68 | F42: 56.96 | G42: 44984 | H42: -0.019790053 | I42: =F42*E42*-1 -> 3873.28
A43: LEN | B43: Lennar | C43: Quant | D43: Sell to Close | E43: -40 | F43: 95.93 | G43: 44984 | H43: 0.048644512 | I43: =F43*E43*-1 -> 3837.2
A44: MHK | B44: Mohawk Industries | C44: Quant | D44: Sell to Close | E44: -34 | F44: 103.43 | G44: 44984 | H44: -0.11302633 | I44: =F44*E44*-1 -> 3516.62
A45: DAL | B45: Delta Air Lines Inc | C45: Quant | D45: Sell to Close | E45: -102 | F45: 38.01 | G45: 44984 | H45: -0.02363216 | I45: =F45*E45*-1 -> 3877.02
A46: FDX | B46: Fedex Corp | C46: Quant | D46: Sell to Trim | E46: -1 | F46: 204.2 | G46: 44984 | H46: 0.076737307 | I46: =F46*E46*-1 -> 204.2
A47: FOXA | B47: Fox Corp Class A | C47: Quant | D47: Buy to Open | E47: 112 | F47: 35.67 | G47: 44984 | H47: =IF(OR(D47="Sell to Trim", D47="Sell to Close"),F47/VLOOKUP(A47, 'Sector Holdings'!$B$3:$M$121, 11, FALSE) - 1, "N/A") -> N/A | I47: =F47*E47*-1 -> -3995.04
A48: MOS | B48: Mosaic Co | C48: Quant | D48: Buy to Open | E48: 76 | F48: 52.8 | G48: 44984 | H48: =IF(OR(D48="Sell to Trim", D48="Sell to Close"),F48/VLOOKUP(A48, 'Sector Holdings'!$B$3:$M$121, 11, FALSE) - 1, "N/A") -> N/A | I48: =F48*E48*-1 -> -4012.8
A49: STLD | B49: Steel Dynamics Inc | C49: Quant | D49: Buy to Open | E49: 33 | F49: 122.02 | G49: 44984 | H49: =IF(OR(D49="Sell to Trim", D49="Sell to Close"),F49/VLOOKUP(A49, 'Sector Holdings'!$B$3:$M$121, 11, FALSE) - 1, "N/A") -> N/A | I49: =F49*E49*-1 -> -4026.66
A50: GM | B50: General Motors | C50: Quant | D50: Buy to Open | E50: 102 | F50: 39.34 | G50: 44984 | H50: =IF(OR(D50="Sell to Trim", D50="Sell to Close"),F50/VLOOKUP(A50, 'Sector Holdings'!$B$3:$M$121, 11, FALSE) - 1, "N/A") -> N/A | I50: =F50*E50*-1 -> -4012.68
A51: XLK | B51: =VLOOKUP(A51, 'Sector Holdings'!$B$4:$C$124, 2, FALSE) -> SPDR Technology ETF | C51: Technology | D51: Sell to Trim | E51: -212 | F51: 142.58 | G51: 44991 | H51: 0.002 | I51: =F51*E51*-1 -> 30226.96
A52: CNSWF | B52: Constellation Software | C52: Technology | D52: Buy to Open | E52: 18 | F52: 1671.87 | G52: 44991 | H52: N/A | I52: =F52*E52*-1 -> -30093.66
A53: XLV | B53: =VLOOKUP(A53, 'Sector Holdings'!$B$4:$C$124, 2, FALSE) -> SPDR Healthcare ETF | C53: Healthcare | D53: Sell to Trim | E53: -230 | F53: 129.4 | G53: 44991 | H53: -0.032 | I53: =F53*E53*-1 -> 29762
A54: VEEV | B54: =VLOOKUP(A54, 'Sector Holdings'!$B$4:$C$124, 2, FALSE) -> Veeva Systems Inc. | C54: Healthcare | D54: Buy to Open | E54: 165 | F54: 181.05 | G54: 44991 | H54: N/A | I54: =F54*E54*-1 -> -29873.25
A55: ICLN | B55: iShares Clean Energy ETF | C55: Energy | D55: Sell to Close | E55: -897 | F55: 20.06 | G55: 44991 | H55: 0.006 | I55: =F55*E55*-1 -> 17993.82
A56: XLE | B56: =VLOOKUP(A56, 'Sector Holdings'!$B$4:$C$124, 2, FALSE) -> SPDR Energy ETF | C56: Energy | D56: Buy to Add | E56: 206 | F56: 86.77 | G56: 44991 | H56: N/A | I56: =F56*E56*-1 -> -17874.62
A57: USB | B57: US Bancorp | C57: Financials | D57: Sell to Close | E57: -635 | F57: 36.96 | G57: 44998 | H57: -0.256 | I57: =F57*E57*-1 -> 23469.6
A58: XLV | B58: =VLOOKUP(A58, 'Sector Holdings'!$B$4:$C$124, 2, FALSE) -> SPDR Healthcare ETF | C58: Healthcare | D58: Sell to Trim | E58: -229 | F58: 127.41 | G58: 45002 | H58: -0.046 | I58: =F58*E58*-1 -> 29176.89
A59: INMD | B59: =VLOOKUP(A59, 'Sector Holdings'!$B$4:$C$124, 2, FALSE) -> #N/A | C59: Healthcare | D59: Buy to Open | E59: 949 | F59: 30.84 | G59: 45002 | H59: N/A | I59: =F59*E59*-1 -> -29267.16
A60: XLRE | B60: SPDR Real Estate ETF | C60: REITs | D60: Sell to Close | E60: -223 | F60: 36.96 | G60: 45002 | H60: -0.0693 | I60: =F60*E60*-1 -> 8242.08
A61: AMT | B61: =VLOOKUP(A61, 'Sector Holdings'!$B$4:$C$124, 2, FALSE) -> #N/A | C61: REITs | D61: Buy to Open | E61: 40 | F61: 205.5 | G61: 45002 | H61: N/A | I61: =F61*E61*-1 -> -8220
A62: FDX | B62: Fedex Corp | C62: Quant | D62: Sell to Close | E62: 20 | F62: 220.05 | G62: 45013 | H62: 0.0243 | I62: =F62*E62*-1 -> -4401
A63: MOS | B63: Mosaic Co | C63: Quant | D63: Sell to Close | E63: 76 | F63: 44.33 | G63: 45013 | H63: -0.1604 | I63: =F63*E63*-1 -> -3369.08
A64: STLD | B64: Steel Dynamics Inc | C64: Quant | D64: Sell to Close | E64: 33 | F64: 109.71 | G64: 45013 | H64: -0.1316 | I64: =F64*E64*-1 -> -3620.43
A65: GM | B65: General Motors | C65: Quant | D65: Sell to Close | E65: 102 | F65: 34.17 | G65: 45013 | I65: =F65*E65*-1 -> -3485.34
A66: FOXA | B66: Fox Corp Class A | C66: Quant | D66: Buy to Add | E66: 6 | F66: 32.83 | G66: 45013 | H66: N/A | I66: =F66*E66*-1 -> -196.98
A67: LEN | B67: Lennar | C67: Quant | D67: Buy to Open | E67: 38 | F67: 101.48 | G67: 45013 | H67: N/A | I67: =F67*E67*-1 -> -3856.24
A68: MPC | B68: Marathon Petroleum | C68: Quant | D68: Buy to Open | E68: 30 | F68: 131.15 | G68: 45013 | H68: N/A | I68: =F68*E68*-1 -> -3934.5
A69: BG | B69: Bunge Ltd | C69: Quant | D69: Buy to Open | E69: 40 | F69: 96.71 | G69: 45013 | H69: N/A | I69: =F69*E69*-1 -> -3868.4
A70: HPE | B70: Hewlett Packard | C70: Quant | D70: Buy to Open | E70: 259 | F70: 14.94 | G70: 45013 | H70: N/A | I70: =F70*E70*-1 -> -3869.46
A71: LYB | B71: Lyondell Basell Industries | C71: Quant | D71: Buy to Open | E71: 37 | F71: 54.288 | G71: 45022 | H71: N/A | I71: =F71*E71*-1 -> -2008.656
A72: BWA | B72: Borg Warner Inc | C72: Quant | D72: Buy to Open | E72: 40 | F72: 96.71 | G72: 45013 | H72: N/A | I72: =F72*E72*-1 -> -3868.4
A73: FANG | B73: Diamondback Energy Inc | C73: Quant | D73: Buy to Open | E73: 14 | F73: 141.5367 | G73: 45022 | H73: N/A | I73: =F73*E73*-1 -> -1981.5138
A74: FLT | B74: Fleetcor Technologies Inc | C74: Quant | D74: Buy to Open | E74: 10 | F74: 207.984 | G74: 45022 | H74: N/A | I74: =F74*E74*-1 -> -2079.84
A75: HST | B75: Host Hotels & Resorts Inc | C75: Quant | D75: Buy to Open | E75: 124 | F75: 16.046 | G75: 45022 | H75: N/A | I75: =F75*E75*-1 -> -1989.704
A76: LKQ | B76: LKQ Corp | C76: Quant | D76: Buy to Open | E76: 37 | F76: 54.288 | G76: 45022 | H76: N/A | I76: =F76*E76*-1 -> -2008.656
